package com.baidu.ufosdk;

final class c
  implements Runnable
{
  /* Error */
  public final void run()
  {
    // Byte code:
    //   0: new 16	com/baidu/ufosdk/util/d
    //   3: dup
    //   4: invokestatic 22	com/baidu/ufosdk/UfoSDK:access$0	()Landroid/content/Context;
    //   7: invokespecial 25	com/baidu/ufosdk/util/d:<init>	(Landroid/content/Context;)V
    //   10: astore_1
    //   11: aload_1
    //   12: invokevirtual 29	com/baidu/ufosdk/util/d:e	()Z
    //   15: ifeq +219 -> 234
    //   18: new 31	java/lang/StringBuilder
    //   21: dup
    //   22: new 31	java/lang/StringBuilder
    //   25: dup
    //   26: getstatic 37	com/baidu/ufosdk/a:ak	Ljava/lang/String;
    //   29: invokestatic 43	java/lang/String:valueOf	(Ljava/lang/Object;)Ljava/lang/String;
    //   32: invokespecial 46	java/lang/StringBuilder:<init>	(Ljava/lang/String;)V
    //   35: ldc 48
    //   37: invokevirtual 52	java/lang/StringBuilder:append	(Ljava/lang/String;)Ljava/lang/StringBuilder;
    //   40: invokevirtual 56	java/lang/StringBuilder:toString	()Ljava/lang/String;
    //   43: invokestatic 43	java/lang/String:valueOf	(Ljava/lang/Object;)Ljava/lang/String;
    //   46: invokespecial 46	java/lang/StringBuilder:<init>	(Ljava/lang/String;)V
    //   49: ldc 58
    //   51: invokevirtual 52	java/lang/StringBuilder:append	(Ljava/lang/String;)Ljava/lang/StringBuilder;
    //   54: invokevirtual 56	java/lang/StringBuilder:toString	()Ljava/lang/String;
    //   57: iconst_5
    //   58: anewarray 4	java/lang/Object
    //   61: dup
    //   62: iconst_0
    //   63: aload_1
    //   64: invokevirtual 62	com/baidu/ufosdk/util/d:a	()I
    //   67: invokestatic 67	java/lang/Integer:valueOf	(I)Ljava/lang/Integer;
    //   70: aastore
    //   71: dup
    //   72: iconst_1
    //   73: aload_1
    //   74: invokevirtual 70	com/baidu/ufosdk/util/d:b	()I
    //   77: invokestatic 67	java/lang/Integer:valueOf	(I)Ljava/lang/Integer;
    //   80: aastore
    //   81: dup
    //   82: iconst_2
    //   83: aload_1
    //   84: invokevirtual 73	com/baidu/ufosdk/util/d:c	()I
    //   87: invokestatic 67	java/lang/Integer:valueOf	(I)Ljava/lang/Integer;
    //   90: aastore
    //   91: dup
    //   92: iconst_3
    //   93: aload_1
    //   94: invokevirtual 76	com/baidu/ufosdk/util/d:d	()I
    //   97: invokestatic 67	java/lang/Integer:valueOf	(I)Ljava/lang/Integer;
    //   100: aastore
    //   101: dup
    //   102: iconst_4
    //   103: getstatic 79	com/baidu/ufosdk/UfoSDK:appid	Ljava/lang/String;
    //   106: aastore
    //   107: invokestatic 83	java/lang/String:format	(Ljava/lang/String;[Ljava/lang/Object;)Ljava/lang/String;
    //   110: astore_2
    //   111: new 31	java/lang/StringBuilder
    //   114: dup
    //   115: ldc 85
    //   117: invokespecial 46	java/lang/StringBuilder:<init>	(Ljava/lang/String;)V
    //   120: aload_2
    //   121: invokevirtual 52	java/lang/StringBuilder:append	(Ljava/lang/String;)Ljava/lang/StringBuilder;
    //   124: invokevirtual 56	java/lang/StringBuilder:toString	()Ljava/lang/String;
    //   127: invokestatic 90	com/baidu/ufosdk/util/c:b	(Ljava/lang/String;)I
    //   130: pop
    //   131: aconst_null
    //   132: astore_1
    //   133: aconst_null
    //   134: astore_3
    //   135: new 92	java/net/URL
    //   138: dup
    //   139: aload_2
    //   140: invokespecial 93	java/net/URL:<init>	(Ljava/lang/String;)V
    //   143: invokevirtual 97	java/net/URL:openConnection	()Ljava/net/URLConnection;
    //   146: checkcast 99	java/net/HttpURLConnection
    //   149: astore_2
    //   150: aload_2
    //   151: ldc 101
    //   153: invokevirtual 104	java/net/HttpURLConnection:setRequestMethod	(Ljava/lang/String;)V
    //   156: aload_2
    //   157: iconst_1
    //   158: invokevirtual 108	java/net/HttpURLConnection:setDoInput	(Z)V
    //   161: aload_2
    //   162: iconst_1
    //   163: invokevirtual 111	java/net/HttpURLConnection:setDoOutput	(Z)V
    //   166: aload_2
    //   167: iconst_0
    //   168: invokevirtual 114	java/net/HttpURLConnection:setUseCaches	(Z)V
    //   171: aload_2
    //   172: iconst_1
    //   173: invokevirtual 117	java/net/HttpURLConnection:setInstanceFollowRedirects	(Z)V
    //   176: aload_2
    //   177: sipush 3000
    //   180: invokevirtual 121	java/net/HttpURLConnection:setConnectTimeout	(I)V
    //   183: aload_2
    //   184: sipush 3000
    //   187: invokevirtual 124	java/net/HttpURLConnection:setReadTimeout	(I)V
    //   190: aload_2
    //   191: ldc 126
    //   193: ldc -128
    //   195: invokevirtual 132	java/net/HttpURLConnection:setRequestProperty	(Ljava/lang/String;Ljava/lang/String;)V
    //   198: aload_2
    //   199: ldc -122
    //   201: ldc -128
    //   203: invokevirtual 132	java/net/HttpURLConnection:setRequestProperty	(Ljava/lang/String;Ljava/lang/String;)V
    //   206: aload_2
    //   207: invokevirtual 137	java/net/HttpURLConnection:getResponseCode	()I
    //   210: sipush 200
    //   213: if_icmpne +9 -> 222
    //   216: ldc -117
    //   218: invokestatic 141	com/baidu/ufosdk/util/c:a	(Ljava/lang/String;)I
    //   221: pop
    //   222: aload_2
    //   223: invokevirtual 144	java/net/HttpURLConnection:disconnect	()V
    //   226: aload_2
    //   227: ifnull +7 -> 234
    //   230: aload_2
    //   231: invokevirtual 144	java/net/HttpURLConnection:disconnect	()V
    //   234: return
    //   235: astore_1
    //   236: aload_3
    //   237: astore_2
    //   238: aload_1
    //   239: astore_3
    //   240: aload_2
    //   241: astore_1
    //   242: aload_3
    //   243: invokevirtual 147	java/lang/Exception:printStackTrace	()V
    //   246: aload_2
    //   247: ifnull -13 -> 234
    //   250: aload_2
    //   251: invokevirtual 144	java/net/HttpURLConnection:disconnect	()V
    //   254: return
    //   255: astore_1
    //   256: aload_1
    //   257: invokevirtual 147	java/lang/Exception:printStackTrace	()V
    //   260: return
    //   261: astore_3
    //   262: aload_1
    //   263: astore_2
    //   264: aload_3
    //   265: astore_1
    //   266: aload_2
    //   267: ifnull +7 -> 274
    //   270: aload_2
    //   271: invokevirtual 144	java/net/HttpURLConnection:disconnect	()V
    //   274: aload_1
    //   275: athrow
    //   276: astore_2
    //   277: aload_2
    //   278: invokevirtual 147	java/lang/Exception:printStackTrace	()V
    //   281: goto -7 -> 274
    //   284: astore_1
    //   285: aload_1
    //   286: invokevirtual 147	java/lang/Exception:printStackTrace	()V
    //   289: return
    //   290: astore_1
    //   291: goto -25 -> 266
    //   294: astore_3
    //   295: goto -55 -> 240
    // Local variable table:
    //   start	length	slot	name	signature
    //   0	298	0	this	c
    //   10	123	1	locald	com.baidu.ufosdk.util.d
    //   235	4	1	localException1	Exception
    //   241	1	1	localObject1	Object
    //   255	8	1	localException2	Exception
    //   265	10	1	localObject2	Object
    //   284	2	1	localException3	Exception
    //   290	1	1	localObject3	Object
    //   110	161	2	localObject4	Object
    //   276	2	2	localException4	Exception
    //   134	109	3	localException5	Exception
    //   261	4	3	localObject5	Object
    //   294	1	3	localException6	Exception
    // Exception table:
    //   from	to	target	type
    //   135	150	235	java/lang/Exception
    //   250	254	255	java/lang/Exception
    //   135	150	261	finally
    //   242	246	261	finally
    //   270	274	276	java/lang/Exception
    //   230	234	284	java/lang/Exception
    //   150	222	290	finally
    //   222	226	290	finally
    //   150	222	294	java/lang/Exception
    //   222	226	294	java/lang/Exception
  }
}


/* Location:              /Users/objectyan/Documents/OY/baiduCarLife_40/dist/classes2-dex2jar.jar!/com/baidu/ufosdk/c.class
 * Java compiler version: 6 (50.0)
 * JD-Core Version:       0.7.1
 */