package com.baidu.speech.aidl;

import android.os.Binder;
import android.os.IBinder;
import android.os.IInterface;
import android.os.Parcel;
import android.os.RemoteException;

public abstract interface EventManager
  extends IInterface
{
  public abstract void registerListener(EventListener paramEventListener)
    throws RemoteException;
  
  public abstract void send(String paramString1, String paramString2, byte[] paramArrayOfByte, int paramInt1, int paramInt2)
    throws RemoteException;
  
  public abstract void unregisterListener(EventListener paramEventListener)
    throws RemoteException;
  
  public static abstract class Stub
    extends Binder
    implements EventManager
  {
    private static final String DESCRIPTOR = "com.baidu.speech.aidl.EventManager";
    static final int TRANSACTION_registerListener = 2;
    static final int TRANSACTION_send = 1;
    static final int TRANSACTION_unregisterListener = 3;
    
    public Stub()
    {
      attachInterface(this, "com.baidu.speech.aidl.EventManager");
    }
    
    public static EventManager asInterface(IBinder paramIBinder)
    {
      if (paramIBinder == null) {
        return null;
      }
      IInterface localIInterface = paramIBinder.queryLocalInterface("com.baidu.speech.aidl.EventManager");
      if ((localIInterface != null) && ((localIInterface instanceof EventManager))) {
        return (EventManager)localIInterface;
      }
      return new Proxy(paramIBinder);
    }
    
    public IBinder asBinder()
    {
      return this;
    }
    
    public boolean onTransact(int paramInt1, Parcel paramParcel1, Parcel paramParcel2, int paramInt2)
      throws RemoteException
    {
      switch (paramInt1)
      {
      default: 
        return super.onTransact(paramInt1, paramParcel1, paramParcel2, paramInt2);
      case 1598968902: 
        paramParcel2.writeString("com.baidu.speech.aidl.EventManager");
        return true;
      case 1: 
        paramParcel1.enforceInterface("com.baidu.speech.aidl.EventManager");
        String str1 = paramParcel1.readString();
        String str2 = paramParcel1.readString();
        byte[] arrayOfByte = paramParcel1.createByteArray();
        send(str1, str2, arrayOfByte, paramParcel1.readInt(), paramParcel1.readInt());
        paramParcel2.writeNoException();
        paramParcel2.writeByteArray(arrayOfByte);
        return true;
      case 2: 
        paramParcel1.enforceInterface("com.baidu.speech.aidl.EventManager");
        registerListener(EventListener.Stub.asInterface(paramParcel1.readStrongBinder()));
        paramParcel2.writeNoException();
        return true;
      }
      paramParcel1.enforceInterface("com.baidu.speech.aidl.EventManager");
      unregisterListener(EventListener.Stub.asInterface(paramParcel1.readStrongBinder()));
      paramParcel2.writeNoException();
      return true;
    }
    
    private static class Proxy
      implements EventManager
    {
      private IBinder mRemote;
      
      Proxy(IBinder paramIBinder)
      {
        this.mRemote = paramIBinder;
      }
      
      public IBinder asBinder()
      {
        return this.mRemote;
      }
      
      public String getInterfaceDescriptor()
      {
        return "com.baidu.speech.aidl.EventManager";
      }
      
      /* Error */
      public void registerListener(EventListener paramEventListener)
        throws RemoteException
      {
        // Byte code:
        //   0: invokestatic 36	android/os/Parcel:obtain	()Landroid/os/Parcel;
        //   3: astore_2
        //   4: invokestatic 36	android/os/Parcel:obtain	()Landroid/os/Parcel;
        //   7: astore_3
        //   8: aload_2
        //   9: ldc 26
        //   11: invokevirtual 40	android/os/Parcel:writeInterfaceToken	(Ljava/lang/String;)V
        //   14: aload_1
        //   15: ifnull +42 -> 57
        //   18: aload_1
        //   19: invokeinterface 44 1 0
        //   24: astore_1
        //   25: aload_2
        //   26: aload_1
        //   27: invokevirtual 47	android/os/Parcel:writeStrongBinder	(Landroid/os/IBinder;)V
        //   30: aload_0
        //   31: getfield 19	com/baidu/speech/aidl/EventManager$Stub$Proxy:mRemote	Landroid/os/IBinder;
        //   34: iconst_2
        //   35: aload_2
        //   36: aload_3
        //   37: iconst_0
        //   38: invokeinterface 53 5 0
        //   43: pop
        //   44: aload_3
        //   45: invokevirtual 56	android/os/Parcel:readException	()V
        //   48: aload_3
        //   49: invokevirtual 59	android/os/Parcel:recycle	()V
        //   52: aload_2
        //   53: invokevirtual 59	android/os/Parcel:recycle	()V
        //   56: return
        //   57: aconst_null
        //   58: astore_1
        //   59: goto -34 -> 25
        //   62: astore_1
        //   63: aload_3
        //   64: invokevirtual 59	android/os/Parcel:recycle	()V
        //   67: aload_2
        //   68: invokevirtual 59	android/os/Parcel:recycle	()V
        //   71: aload_1
        //   72: athrow
        // Local variable table:
        //   start	length	slot	name	signature
        //   0	73	0	this	Proxy
        //   0	73	1	paramEventListener	EventListener
        //   3	65	2	localParcel1	Parcel
        //   7	57	3	localParcel2	Parcel
        // Exception table:
        //   from	to	target	type
        //   8	14	62	finally
        //   18	25	62	finally
        //   25	48	62	finally
      }
      
      public void send(String paramString1, String paramString2, byte[] paramArrayOfByte, int paramInt1, int paramInt2)
        throws RemoteException
      {
        Parcel localParcel1 = Parcel.obtain();
        Parcel localParcel2 = Parcel.obtain();
        try
        {
          localParcel1.writeInterfaceToken("com.baidu.speech.aidl.EventManager");
          localParcel1.writeString(paramString1);
          localParcel1.writeString(paramString2);
          localParcel1.writeByteArray(paramArrayOfByte);
          localParcel1.writeInt(paramInt1);
          localParcel1.writeInt(paramInt2);
          this.mRemote.transact(1, localParcel1, localParcel2, 0);
          localParcel2.readException();
          localParcel2.readByteArray(paramArrayOfByte);
          return;
        }
        finally
        {
          localParcel2.recycle();
          localParcel1.recycle();
        }
      }
      
      /* Error */
      public void unregisterListener(EventListener paramEventListener)
        throws RemoteException
      {
        // Byte code:
        //   0: invokestatic 36	android/os/Parcel:obtain	()Landroid/os/Parcel;
        //   3: astore_2
        //   4: invokestatic 36	android/os/Parcel:obtain	()Landroid/os/Parcel;
        //   7: astore_3
        //   8: aload_2
        //   9: ldc 26
        //   11: invokevirtual 40	android/os/Parcel:writeInterfaceToken	(Ljava/lang/String;)V
        //   14: aload_1
        //   15: ifnull +42 -> 57
        //   18: aload_1
        //   19: invokeinterface 44 1 0
        //   24: astore_1
        //   25: aload_2
        //   26: aload_1
        //   27: invokevirtual 47	android/os/Parcel:writeStrongBinder	(Landroid/os/IBinder;)V
        //   30: aload_0
        //   31: getfield 19	com/baidu/speech/aidl/EventManager$Stub$Proxy:mRemote	Landroid/os/IBinder;
        //   34: iconst_3
        //   35: aload_2
        //   36: aload_3
        //   37: iconst_0
        //   38: invokeinterface 53 5 0
        //   43: pop
        //   44: aload_3
        //   45: invokevirtual 56	android/os/Parcel:readException	()V
        //   48: aload_3
        //   49: invokevirtual 59	android/os/Parcel:recycle	()V
        //   52: aload_2
        //   53: invokevirtual 59	android/os/Parcel:recycle	()V
        //   56: return
        //   57: aconst_null
        //   58: astore_1
        //   59: goto -34 -> 25
        //   62: astore_1
        //   63: aload_3
        //   64: invokevirtual 59	android/os/Parcel:recycle	()V
        //   67: aload_2
        //   68: invokevirtual 59	android/os/Parcel:recycle	()V
        //   71: aload_1
        //   72: athrow
        // Local variable table:
        //   start	length	slot	name	signature
        //   0	73	0	this	Proxy
        //   0	73	1	paramEventListener	EventListener
        //   3	65	2	localParcel1	Parcel
        //   7	57	3	localParcel2	Parcel
        // Exception table:
        //   from	to	target	type
        //   8	14	62	finally
        //   18	25	62	finally
        //   25	48	62	finally
      }
    }
  }
}


/* Location:              /Users/objectyan/Documents/OY/baiduCarLife_40/dist/classes2-dex2jar.jar!/com/baidu/speech/aidl/EventManager.class
 * Java compiler version: 6 (50.0)
 * JD-Core Version:       0.7.1
 */