package com.baidu.location.h;

import android.content.Context;
import android.net.ConnectivityManager;
import android.net.NetworkInfo;
import android.net.Proxy;
import com.baidu.location.f;
import java.util.Map;

public abstract class e
{
  private static String a = "10.0.0.172";
  private static int b = 80;
  public static int g = a.g;
  protected static int o = 0;
  public String h = null;
  public int i = 3;
  public String j = null;
  public Map<String, Object> k = null;
  public String l = null;
  public byte[] m = null;
  public String n = null;
  
  private static int a(Context paramContext, NetworkInfo paramNetworkInfo)
  {
    if ((paramNetworkInfo != null) && (paramNetworkInfo.getExtraInfo() != null))
    {
      paramContext = paramNetworkInfo.getExtraInfo().toLowerCase();
      if (paramContext != null)
      {
        if ((paramContext.startsWith("cmwap")) || (paramContext.startsWith("uniwap")) || (paramContext.startsWith("3gwap")))
        {
          paramContext = Proxy.getDefaultHost();
          if ((paramContext != null) && (!paramContext.equals("")) && (!paramContext.equals("null"))) {}
          for (;;)
          {
            a = paramContext;
            return a.d;
            paramContext = "10.0.0.172";
          }
        }
        if (paramContext.startsWith("ctwap"))
        {
          paramContext = Proxy.getDefaultHost();
          if ((paramContext != null) && (!paramContext.equals("")) && (!paramContext.equals("null"))) {}
          for (;;)
          {
            a = paramContext;
            return a.d;
            paramContext = "10.0.0.200";
          }
        }
        if ((paramContext.startsWith("cmnet")) || (paramContext.startsWith("uninet")) || (paramContext.startsWith("ctnet")) || (paramContext.startsWith("3gnet"))) {
          return a.e;
        }
      }
    }
    paramContext = Proxy.getDefaultHost();
    if ((paramContext != null) && (paramContext.length() > 0))
    {
      if ("10.0.0.172".equals(paramContext.trim()))
      {
        a = "10.0.0.172";
        return a.d;
      }
      if ("10.0.0.200".equals(paramContext.trim()))
      {
        a = "10.0.0.200";
        return a.d;
      }
    }
    return a.e;
  }
  
  private void b()
  {
    g = c();
  }
  
  private int c()
  {
    Object localObject1 = f.getServiceContext();
    try
    {
      Object localObject2 = (ConnectivityManager)((Context)localObject1).getSystemService("connectivity");
      if (localObject2 == null) {
        return a.g;
      }
      localObject2 = ((ConnectivityManager)localObject2).getActiveNetworkInfo();
      if ((localObject2 == null) || (!((NetworkInfo)localObject2).isAvailable())) {
        return a.g;
      }
      if (((NetworkInfo)localObject2).getType() == 1)
      {
        localObject1 = Proxy.getDefaultHost();
        if ((localObject1 != null) && (((String)localObject1).length() > 0)) {
          return a.h;
        }
        return a.f;
      }
      int i1 = a((Context)localObject1, (NetworkInfo)localObject2);
      return i1;
    }
    catch (Exception localException) {}
    return a.g;
  }
  
  public abstract void a();
  
  public abstract void a(boolean paramBoolean);
  
  public void a(final boolean paramBoolean, final String paramString)
  {
    new Thread()
    {
      /* Error */
      public void run()
      {
        // Byte code:
        //   0: aconst_null
        //   1: astore 12
        //   3: aload_0
        //   4: getfield 18	com/baidu/location/h/e$2:c	Lcom/baidu/location/h/e;
        //   7: invokestatic 37	com/baidu/location/h/g:e	()Ljava/lang/String;
        //   10: putfield 40	com/baidu/location/h/e:h	Ljava/lang/String;
        //   13: aload_0
        //   14: getfield 18	com/baidu/location/h/e$2:c	Lcom/baidu/location/h/e;
        //   17: invokestatic 43	com/baidu/location/h/e:a	(Lcom/baidu/location/h/e;)V
        //   20: aload_0
        //   21: getfield 18	com/baidu/location/h/e$2:c	Lcom/baidu/location/h/e;
        //   24: invokevirtual 45	com/baidu/location/h/e:a	()V
        //   27: aload_0
        //   28: getfield 18	com/baidu/location/h/e$2:c	Lcom/baidu/location/h/e;
        //   31: getfield 49	com/baidu/location/h/e:i	I
        //   34: istore_2
        //   35: aconst_null
        //   36: astore 4
        //   38: iload_2
        //   39: ifle +186 -> 225
        //   42: new 51	java/net/URL
        //   45: dup
        //   46: aload_0
        //   47: getfield 18	com/baidu/location/h/e$2:c	Lcom/baidu/location/h/e;
        //   50: getfield 40	com/baidu/location/h/e:h	Ljava/lang/String;
        //   53: invokespecial 54	java/net/URL:<init>	(Ljava/lang/String;)V
        //   56: astore_3
        //   57: new 56	java/lang/StringBuffer
        //   60: dup
        //   61: invokespecial 57	java/lang/StringBuffer:<init>	()V
        //   64: astore 5
        //   66: aload_0
        //   67: getfield 18	com/baidu/location/h/e$2:c	Lcom/baidu/location/h/e;
        //   70: getfield 61	com/baidu/location/h/e:k	Ljava/util/Map;
        //   73: invokeinterface 67 1 0
        //   78: invokeinterface 73 1 0
        //   83: astore 6
        //   85: aload 6
        //   87: invokeinterface 79 1 0
        //   92: ifeq +162 -> 254
        //   95: aload 6
        //   97: invokeinterface 83 1 0
        //   102: checkcast 85	java/util/Map$Entry
        //   105: astore 7
        //   107: aload 5
        //   109: aload 7
        //   111: invokeinterface 88 1 0
        //   116: checkcast 90	java/lang/String
        //   119: invokevirtual 94	java/lang/StringBuffer:append	(Ljava/lang/String;)Ljava/lang/StringBuffer;
        //   122: pop
        //   123: aload 5
        //   125: ldc 96
        //   127: invokevirtual 94	java/lang/StringBuffer:append	(Ljava/lang/String;)Ljava/lang/StringBuffer;
        //   130: pop
        //   131: aload 5
        //   133: aload 7
        //   135: invokeinterface 99 1 0
        //   140: invokevirtual 102	java/lang/StringBuffer:append	(Ljava/lang/Object;)Ljava/lang/StringBuffer;
        //   143: pop
        //   144: aload 5
        //   146: ldc 104
        //   148: invokevirtual 94	java/lang/StringBuffer:append	(Ljava/lang/String;)Ljava/lang/StringBuffer;
        //   151: pop
        //   152: goto -67 -> 85
        //   155: astore_3
        //   156: aconst_null
        //   157: astore 5
        //   159: aconst_null
        //   160: astore 7
        //   162: aload 4
        //   164: astore_3
        //   165: aconst_null
        //   166: astore 6
        //   168: aload 7
        //   170: astore 4
        //   172: getstatic 107	com/baidu/location/h/a:a	Ljava/lang/String;
        //   175: ldc 109
        //   177: invokestatic 115	android/util/Log:d	(Ljava/lang/String;Ljava/lang/String;)I
        //   180: pop
        //   181: aload_3
        //   182: ifnull +7 -> 189
        //   185: aload_3
        //   186: invokevirtual 120	java/net/HttpURLConnection:disconnect	()V
        //   189: aload 5
        //   191: ifnull +8 -> 199
        //   194: aload 5
        //   196: invokevirtual 125	java/io/OutputStream:close	()V
        //   199: aload 6
        //   201: ifnull +8 -> 209
        //   204: aload 6
        //   206: invokevirtual 128	java/io/InputStream:close	()V
        //   209: aload 4
        //   211: ifnull +8 -> 219
        //   214: aload 4
        //   216: invokevirtual 131	java/io/ByteArrayOutputStream:close	()V
        //   219: iconst_0
        //   220: istore_1
        //   221: iload_1
        //   222: ifeq +787 -> 1009
        //   225: iload_2
        //   226: ifgt +793 -> 1019
        //   229: getstatic 134	com/baidu/location/h/e:o	I
        //   232: iconst_1
        //   233: iadd
        //   234: putstatic 134	com/baidu/location/h/e:o	I
        //   237: aload_0
        //   238: getfield 18	com/baidu/location/h/e$2:c	Lcom/baidu/location/h/e;
        //   241: aconst_null
        //   242: putfield 137	com/baidu/location/h/e:j	Ljava/lang/String;
        //   245: aload_0
        //   246: getfield 18	com/baidu/location/h/e$2:c	Lcom/baidu/location/h/e;
        //   249: iconst_0
        //   250: invokevirtual 140	com/baidu/location/h/e:a	(Z)V
        //   253: return
        //   254: aload 5
        //   256: invokevirtual 144	java/lang/StringBuffer:length	()I
        //   259: ifle +16 -> 275
        //   262: aload 5
        //   264: aload 5
        //   266: invokevirtual 144	java/lang/StringBuffer:length	()I
        //   269: iconst_1
        //   270: isub
        //   271: invokevirtual 148	java/lang/StringBuffer:deleteCharAt	(I)Ljava/lang/StringBuffer;
        //   274: pop
        //   275: aload_3
        //   276: invokevirtual 152	java/net/URL:openConnection	()Ljava/net/URLConnection;
        //   279: checkcast 117	java/net/HttpURLConnection
        //   282: astore_3
        //   283: aload_3
        //   284: ldc -102
        //   286: invokevirtual 157	java/net/HttpURLConnection:setRequestMethod	(Ljava/lang/String;)V
        //   289: aload_3
        //   290: iconst_1
        //   291: invokevirtual 160	java/net/HttpURLConnection:setDoInput	(Z)V
        //   294: aload_3
        //   295: iconst_1
        //   296: invokevirtual 163	java/net/HttpURLConnection:setDoOutput	(Z)V
        //   299: aload_3
        //   300: iconst_0
        //   301: invokevirtual 166	java/net/HttpURLConnection:setUseCaches	(Z)V
        //   304: aload_3
        //   305: getstatic 168	com/baidu/location/h/a:b	I
        //   308: invokevirtual 172	java/net/HttpURLConnection:setConnectTimeout	(I)V
        //   311: aload_3
        //   312: getstatic 168	com/baidu/location/h/a:b	I
        //   315: invokevirtual 175	java/net/HttpURLConnection:setReadTimeout	(I)V
        //   318: aload_3
        //   319: ldc -79
        //   321: ldc -77
        //   323: invokevirtual 183	java/net/HttpURLConnection:setRequestProperty	(Ljava/lang/String;Ljava/lang/String;)V
        //   326: aload_3
        //   327: ldc -71
        //   329: ldc -69
        //   331: invokevirtual 183	java/net/HttpURLConnection:setRequestProperty	(Ljava/lang/String;Ljava/lang/String;)V
        //   334: aload_3
        //   335: ldc -67
        //   337: ldc -65
        //   339: invokevirtual 183	java/net/HttpURLConnection:setRequestProperty	(Ljava/lang/String;Ljava/lang/String;)V
        //   342: aload_0
        //   343: getfield 20	com/baidu/location/h/e$2:a	Ljava/lang/String;
        //   346: invokestatic 197	android/text/TextUtils:isEmpty	(Ljava/lang/CharSequence;)Z
        //   349: ifne +13 -> 362
        //   352: aload_3
        //   353: ldc -57
        //   355: aload_0
        //   356: getfield 20	com/baidu/location/h/e$2:a	Ljava/lang/String;
        //   359: invokevirtual 183	java/net/HttpURLConnection:setRequestProperty	(Ljava/lang/String;Ljava/lang/String;)V
        //   362: aload_3
        //   363: invokevirtual 203	java/net/HttpURLConnection:getOutputStream	()Ljava/io/OutputStream;
        //   366: astore 4
        //   368: aload 4
        //   370: aload 5
        //   372: invokevirtual 206	java/lang/StringBuffer:toString	()Ljava/lang/String;
        //   375: invokevirtual 210	java/lang/String:getBytes	()[B
        //   378: invokevirtual 214	java/io/OutputStream:write	([B)V
        //   381: aload 4
        //   383: invokevirtual 217	java/io/OutputStream:flush	()V
        //   386: aload_3
        //   387: invokevirtual 220	java/net/HttpURLConnection:getResponseCode	()I
        //   390: sipush 200
        //   393: if_icmpne +925 -> 1318
        //   396: aload_3
        //   397: invokevirtual 224	java/net/HttpURLConnection:getInputStream	()Ljava/io/InputStream;
        //   400: astore 6
        //   402: aload_3
        //   403: invokevirtual 227	java/net/HttpURLConnection:getContentEncoding	()Ljava/lang/String;
        //   406: astore 5
        //   408: aload 5
        //   410: ifnull +901 -> 1311
        //   413: aload 5
        //   415: ldc -65
        //   417: invokevirtual 230	java/lang/String:contains	(Ljava/lang/CharSequence;)Z
        //   420: ifeq +891 -> 1311
        //   423: new 232	java/util/zip/GZIPInputStream
        //   426: dup
        //   427: new 234	java/io/BufferedInputStream
        //   430: dup
        //   431: aload 6
        //   433: invokespecial 237	java/io/BufferedInputStream:<init>	(Ljava/io/InputStream;)V
        //   436: invokespecial 238	java/util/zip/GZIPInputStream:<init>	(Ljava/io/InputStream;)V
        //   439: astore 5
        //   441: new 130	java/io/ByteArrayOutputStream
        //   444: dup
        //   445: invokespecial 239	java/io/ByteArrayOutputStream:<init>	()V
        //   448: astore 7
        //   450: aload_3
        //   451: astore 10
        //   453: aload 4
        //   455: astore 11
        //   457: aload 7
        //   459: astore 9
        //   461: aload 5
        //   463: astore 8
        //   465: sipush 1024
        //   468: newarray <illegal type>
        //   470: astore 6
        //   472: aload_3
        //   473: astore 10
        //   475: aload 4
        //   477: astore 11
        //   479: aload 7
        //   481: astore 9
        //   483: aload 5
        //   485: astore 8
        //   487: aload 5
        //   489: aload 6
        //   491: invokevirtual 243	java/io/InputStream:read	([B)I
        //   494: istore_1
        //   495: iload_1
        //   496: iconst_m1
        //   497: if_icmpeq +30 -> 527
        //   500: aload_3
        //   501: astore 10
        //   503: aload 4
        //   505: astore 11
        //   507: aload 7
        //   509: astore 9
        //   511: aload 5
        //   513: astore 8
        //   515: aload 7
        //   517: aload 6
        //   519: iconst_0
        //   520: iload_1
        //   521: invokevirtual 246	java/io/ByteArrayOutputStream:write	([BII)V
        //   524: goto -52 -> 472
        //   527: aload_3
        //   528: astore 10
        //   530: aload 4
        //   532: astore 11
        //   534: aload 7
        //   536: astore 9
        //   538: aload 5
        //   540: astore 8
        //   542: aload_0
        //   543: getfield 18	com/baidu/location/h/e$2:c	Lcom/baidu/location/h/e;
        //   546: new 90	java/lang/String
        //   549: dup
        //   550: aload 7
        //   552: invokevirtual 249	java/io/ByteArrayOutputStream:toByteArray	()[B
        //   555: ldc -5
        //   557: invokespecial 254	java/lang/String:<init>	([BLjava/lang/String;)V
        //   560: putfield 137	com/baidu/location/h/e:j	Ljava/lang/String;
        //   563: aload_3
        //   564: astore 10
        //   566: aload 4
        //   568: astore 11
        //   570: aload 7
        //   572: astore 9
        //   574: aload 5
        //   576: astore 8
        //   578: aload_0
        //   579: getfield 22	com/baidu/location/h/e$2:b	Z
        //   582: ifeq +30 -> 612
        //   585: aload_3
        //   586: astore 10
        //   588: aload 4
        //   590: astore 11
        //   592: aload 7
        //   594: astore 9
        //   596: aload 5
        //   598: astore 8
        //   600: aload_0
        //   601: getfield 18	com/baidu/location/h/e$2:c	Lcom/baidu/location/h/e;
        //   604: aload 7
        //   606: invokevirtual 249	java/io/ByteArrayOutputStream:toByteArray	()[B
        //   609: putfield 258	com/baidu/location/h/e:m	[B
        //   612: aload_3
        //   613: astore 10
        //   615: aload 4
        //   617: astore 11
        //   619: aload 7
        //   621: astore 9
        //   623: aload 5
        //   625: astore 8
        //   627: aload_0
        //   628: getfield 18	com/baidu/location/h/e$2:c	Lcom/baidu/location/h/e;
        //   631: iconst_1
        //   632: invokevirtual 140	com/baidu/location/h/e:a	(Z)V
        //   635: iconst_1
        //   636: istore_1
        //   637: aload 5
        //   639: astore 6
        //   641: aload 7
        //   643: astore 5
        //   645: aload_3
        //   646: ifnull +7 -> 653
        //   649: aload_3
        //   650: invokevirtual 120	java/net/HttpURLConnection:disconnect	()V
        //   653: aload 4
        //   655: ifnull +8 -> 663
        //   658: aload 4
        //   660: invokevirtual 125	java/io/OutputStream:close	()V
        //   663: aload 6
        //   665: ifnull +8 -> 673
        //   668: aload 6
        //   670: invokevirtual 128	java/io/InputStream:close	()V
        //   673: aload 5
        //   675: ifnull +8 -> 683
        //   678: aload 5
        //   680: invokevirtual 131	java/io/ByteArrayOutputStream:close	()V
        //   683: goto -462 -> 221
        //   686: astore 4
        //   688: getstatic 107	com/baidu/location/h/a:a	Ljava/lang/String;
        //   691: ldc_w 260
        //   694: invokestatic 115	android/util/Log:d	(Ljava/lang/String;Ljava/lang/String;)I
        //   697: pop
        //   698: goto -35 -> 663
        //   701: astore 4
        //   703: getstatic 107	com/baidu/location/h/a:a	Ljava/lang/String;
        //   706: ldc_w 262
        //   709: invokestatic 115	android/util/Log:d	(Ljava/lang/String;Ljava/lang/String;)I
        //   712: pop
        //   713: goto -40 -> 673
        //   716: astore 4
        //   718: getstatic 107	com/baidu/location/h/a:a	Ljava/lang/String;
        //   721: ldc_w 264
        //   724: invokestatic 115	android/util/Log:d	(Ljava/lang/String;Ljava/lang/String;)I
        //   727: pop
        //   728: goto -507 -> 221
        //   731: astore 5
        //   733: getstatic 107	com/baidu/location/h/a:a	Ljava/lang/String;
        //   736: ldc_w 260
        //   739: invokestatic 115	android/util/Log:d	(Ljava/lang/String;Ljava/lang/String;)I
        //   742: pop
        //   743: goto -544 -> 199
        //   746: astore 5
        //   748: getstatic 107	com/baidu/location/h/a:a	Ljava/lang/String;
        //   751: ldc_w 262
        //   754: invokestatic 115	android/util/Log:d	(Ljava/lang/String;Ljava/lang/String;)I
        //   757: pop
        //   758: goto -549 -> 209
        //   761: astore 4
        //   763: getstatic 107	com/baidu/location/h/a:a	Ljava/lang/String;
        //   766: ldc_w 264
        //   769: invokestatic 115	android/util/Log:d	(Ljava/lang/String;Ljava/lang/String;)I
        //   772: pop
        //   773: iconst_0
        //   774: istore_1
        //   775: goto -554 -> 221
        //   778: astore 4
        //   780: aconst_null
        //   781: astore 6
        //   783: aconst_null
        //   784: astore 4
        //   786: aconst_null
        //   787: astore 5
        //   789: aload_3
        //   790: astore 10
        //   792: aload 6
        //   794: astore 11
        //   796: aload 4
        //   798: astore 9
        //   800: aload 5
        //   802: astore 8
        //   804: getstatic 107	com/baidu/location/h/a:a	Ljava/lang/String;
        //   807: ldc_w 266
        //   810: invokestatic 115	android/util/Log:d	(Ljava/lang/String;Ljava/lang/String;)I
        //   813: pop
        //   814: aload_3
        //   815: ifnull +7 -> 822
        //   818: aload_3
        //   819: invokevirtual 120	java/net/HttpURLConnection:disconnect	()V
        //   822: aload 6
        //   824: ifnull +8 -> 832
        //   827: aload 6
        //   829: invokevirtual 125	java/io/OutputStream:close	()V
        //   832: aload 5
        //   834: ifnull +8 -> 842
        //   837: aload 5
        //   839: invokevirtual 128	java/io/InputStream:close	()V
        //   842: aload 4
        //   844: ifnull +8 -> 852
        //   847: aload 4
        //   849: invokevirtual 131	java/io/ByteArrayOutputStream:close	()V
        //   852: iconst_0
        //   853: istore_1
        //   854: goto -633 -> 221
        //   857: astore 6
        //   859: getstatic 107	com/baidu/location/h/a:a	Ljava/lang/String;
        //   862: ldc_w 260
        //   865: invokestatic 115	android/util/Log:d	(Ljava/lang/String;Ljava/lang/String;)I
        //   868: pop
        //   869: goto -37 -> 832
        //   872: astore 5
        //   874: getstatic 107	com/baidu/location/h/a:a	Ljava/lang/String;
        //   877: ldc_w 262
        //   880: invokestatic 115	android/util/Log:d	(Ljava/lang/String;Ljava/lang/String;)I
        //   883: pop
        //   884: goto -42 -> 842
        //   887: astore 4
        //   889: getstatic 107	com/baidu/location/h/a:a	Ljava/lang/String;
        //   892: ldc_w 264
        //   895: invokestatic 115	android/util/Log:d	(Ljava/lang/String;Ljava/lang/String;)I
        //   898: pop
        //   899: iconst_0
        //   900: istore_1
        //   901: goto -680 -> 221
        //   904: astore 8
        //   906: aconst_null
        //   907: astore 6
        //   909: aconst_null
        //   910: astore 5
        //   912: aload 12
        //   914: astore 7
        //   916: aload_3
        //   917: astore 4
        //   919: aload 8
        //   921: astore_3
        //   922: aload 4
        //   924: ifnull +8 -> 932
        //   927: aload 4
        //   929: invokevirtual 120	java/net/HttpURLConnection:disconnect	()V
        //   932: aload 7
        //   934: ifnull +8 -> 942
        //   937: aload 7
        //   939: invokevirtual 125	java/io/OutputStream:close	()V
        //   942: aload 5
        //   944: ifnull +8 -> 952
        //   947: aload 5
        //   949: invokevirtual 128	java/io/InputStream:close	()V
        //   952: aload 6
        //   954: ifnull +8 -> 962
        //   957: aload 6
        //   959: invokevirtual 131	java/io/ByteArrayOutputStream:close	()V
        //   962: aload_3
        //   963: athrow
        //   964: astore 4
        //   966: getstatic 107	com/baidu/location/h/a:a	Ljava/lang/String;
        //   969: ldc_w 260
        //   972: invokestatic 115	android/util/Log:d	(Ljava/lang/String;Ljava/lang/String;)I
        //   975: pop
        //   976: goto -34 -> 942
        //   979: astore 4
        //   981: getstatic 107	com/baidu/location/h/a:a	Ljava/lang/String;
        //   984: ldc_w 262
        //   987: invokestatic 115	android/util/Log:d	(Ljava/lang/String;Ljava/lang/String;)I
        //   990: pop
        //   991: goto -39 -> 952
        //   994: astore 4
        //   996: getstatic 107	com/baidu/location/h/a:a	Ljava/lang/String;
        //   999: ldc_w 264
        //   1002: invokestatic 115	android/util/Log:d	(Ljava/lang/String;Ljava/lang/String;)I
        //   1005: pop
        //   1006: goto -44 -> 962
        //   1009: iload_2
        //   1010: iconst_1
        //   1011: isub
        //   1012: istore_2
        //   1013: aload_3
        //   1014: astore 4
        //   1016: goto -978 -> 38
        //   1019: iconst_0
        //   1020: putstatic 134	com/baidu/location/h/e:o	I
        //   1023: return
        //   1024: astore 6
        //   1026: aconst_null
        //   1027: astore 8
        //   1029: aload_3
        //   1030: astore 5
        //   1032: aload 6
        //   1034: astore_3
        //   1035: aconst_null
        //   1036: astore 6
        //   1038: aload 4
        //   1040: astore 7
        //   1042: aload 5
        //   1044: astore 4
        //   1046: aload 8
        //   1048: astore 5
        //   1050: goto -128 -> 922
        //   1053: astore 8
        //   1055: aload 6
        //   1057: astore 5
        //   1059: aconst_null
        //   1060: astore 6
        //   1062: aload 4
        //   1064: astore 7
        //   1066: aload_3
        //   1067: astore 4
        //   1069: aload 8
        //   1071: astore_3
        //   1072: goto -150 -> 922
        //   1075: astore 8
        //   1077: aconst_null
        //   1078: astore 6
        //   1080: aload 4
        //   1082: astore 7
        //   1084: aload_3
        //   1085: astore 4
        //   1087: aload 8
        //   1089: astore_3
        //   1090: goto -168 -> 922
        //   1093: astore_3
        //   1094: aload 11
        //   1096: astore 7
        //   1098: aload 10
        //   1100: astore 4
        //   1102: aload 9
        //   1104: astore 6
        //   1106: aload 8
        //   1108: astore 5
        //   1110: goto -188 -> 922
        //   1113: astore 7
        //   1115: aload_3
        //   1116: astore 9
        //   1118: aload 6
        //   1120: astore 8
        //   1122: aload 4
        //   1124: astore 6
        //   1126: aload 7
        //   1128: astore_3
        //   1129: aload 9
        //   1131: astore 4
        //   1133: aload 5
        //   1135: astore 7
        //   1137: aload 8
        //   1139: astore 5
        //   1141: goto -219 -> 922
        //   1144: astore_3
        //   1145: aconst_null
        //   1146: astore 5
        //   1148: aconst_null
        //   1149: astore 6
        //   1151: aload 12
        //   1153: astore 7
        //   1155: goto -233 -> 922
        //   1158: astore 5
        //   1160: aconst_null
        //   1161: astore 7
        //   1163: aconst_null
        //   1164: astore 5
        //   1166: aload 4
        //   1168: astore 6
        //   1170: aload 7
        //   1172: astore 4
        //   1174: goto -385 -> 789
        //   1177: astore 5
        //   1179: aload 6
        //   1181: astore 5
        //   1183: aconst_null
        //   1184: astore 7
        //   1186: aload 4
        //   1188: astore 6
        //   1190: aload 7
        //   1192: astore 4
        //   1194: goto -405 -> 789
        //   1197: astore 6
        //   1199: aconst_null
        //   1200: astore 7
        //   1202: aload 4
        //   1204: astore 6
        //   1206: aload 7
        //   1208: astore 4
        //   1210: goto -421 -> 789
        //   1213: astore 6
        //   1215: aload 4
        //   1217: astore 6
        //   1219: aload 7
        //   1221: astore 4
        //   1223: goto -434 -> 789
        //   1226: astore_3
        //   1227: aconst_null
        //   1228: astore 6
        //   1230: aconst_null
        //   1231: astore 5
        //   1233: aload 4
        //   1235: astore_3
        //   1236: aconst_null
        //   1237: astore 4
        //   1239: goto -450 -> 789
        //   1242: astore 4
        //   1244: aconst_null
        //   1245: astore 4
        //   1247: aconst_null
        //   1248: astore 6
        //   1250: aconst_null
        //   1251: astore 5
        //   1253: goto -1081 -> 172
        //   1256: astore 5
        //   1258: aconst_null
        //   1259: astore 6
        //   1261: aconst_null
        //   1262: astore 7
        //   1264: aload 4
        //   1266: astore 5
        //   1268: aload 7
        //   1270: astore 4
        //   1272: goto -1100 -> 172
        //   1275: astore 5
        //   1277: aconst_null
        //   1278: astore 7
        //   1280: aload 4
        //   1282: astore 5
        //   1284: aload 7
        //   1286: astore 4
        //   1288: goto -1116 -> 172
        //   1291: astore 6
        //   1293: aload 5
        //   1295: astore 6
        //   1297: aconst_null
        //   1298: astore 7
        //   1300: aload 4
        //   1302: astore 5
        //   1304: aload 7
        //   1306: astore 4
        //   1308: goto -1136 -> 172
        //   1311: aload 6
        //   1313: astore 5
        //   1315: goto -874 -> 441
        //   1318: iconst_0
        //   1319: istore_1
        //   1320: aconst_null
        //   1321: astore 5
        //   1323: aconst_null
        //   1324: astore 6
        //   1326: goto -681 -> 645
        //   1329: astore 6
        //   1331: aload 5
        //   1333: astore 6
        //   1335: aload 4
        //   1337: astore 5
        //   1339: aload 7
        //   1341: astore 4
        //   1343: goto -1171 -> 172
        // Local variable table:
        //   start	length	slot	name	signature
        //   0	1346	0	this	2
        //   220	1100	1	i	int
        //   34	979	2	j	int
        //   56	1	3	localURL	java.net.URL
        //   155	1	3	localException1	Exception
        //   164	926	3	localObject1	Object
        //   1093	23	3	localObject2	Object
        //   1128	1	3	localObject3	Object
        //   1144	1	3	localObject4	Object
        //   1226	1	3	localError1	Error
        //   1235	1	3	localObject5	Object
        //   36	623	4	localObject6	Object
        //   686	1	4	localException2	Exception
        //   701	1	4	localException3	Exception
        //   716	1	4	localException4	Exception
        //   761	1	4	localException5	Exception
        //   778	1	4	localError2	Error
        //   784	64	4	localObject7	Object
        //   887	1	4	localException6	Exception
        //   917	11	4	localObject8	Object
        //   964	1	4	localException7	Exception
        //   979	1	4	localException8	Exception
        //   994	1	4	localException9	Exception
        //   1014	224	4	localObject9	Object
        //   1242	1	4	localException10	Exception
        //   1245	97	4	localObject10	Object
        //   64	615	5	localObject11	Object
        //   731	1	5	localException11	Exception
        //   746	1	5	localException12	Exception
        //   787	51	5	localObject12	Object
        //   872	1	5	localException13	Exception
        //   910	237	5	localObject13	Object
        //   1158	1	5	localError3	Error
        //   1164	1	5	localObject14	Object
        //   1177	1	5	localError4	Error
        //   1181	71	5	localObject15	Object
        //   1256	1	5	localException14	Exception
        //   1266	1	5	localObject16	Object
        //   1275	1	5	localException15	Exception
        //   1282	56	5	localObject17	Object
        //   83	745	6	localObject18	Object
        //   857	1	6	localException16	Exception
        //   907	51	6	localObject19	Object
        //   1024	9	6	localObject20	Object
        //   1036	153	6	localObject21	Object
        //   1197	1	6	localError5	Error
        //   1204	1	6	localObject22	Object
        //   1213	1	6	localError6	Error
        //   1217	43	6	localObject23	Object
        //   1291	1	6	localException17	Exception
        //   1295	30	6	localObject24	Object
        //   1329	1	6	localException18	Exception
        //   1333	1	6	localObject25	Object
        //   105	992	7	localObject26	Object
        //   1113	14	7	localObject27	Object
        //   1135	205	7	localObject28	Object
        //   463	340	8	localObject29	Object
        //   904	16	8	localObject30	Object
        //   1027	20	8	localObject31	Object
        //   1053	17	8	localObject32	Object
        //   1075	32	8	localObject33	Object
        //   1120	18	8	localObject34	Object
        //   459	671	9	localObject35	Object
        //   451	648	10	localObject36	Object
        //   455	640	11	localObject37	Object
        //   1	1151	12	localObject38	Object
        // Exception table:
        //   from	to	target	type
        //   42	85	155	java/lang/Exception
        //   85	152	155	java/lang/Exception
        //   254	275	155	java/lang/Exception
        //   275	283	155	java/lang/Exception
        //   658	663	686	java/lang/Exception
        //   668	673	701	java/lang/Exception
        //   678	683	716	java/lang/Exception
        //   194	199	731	java/lang/Exception
        //   204	209	746	java/lang/Exception
        //   214	219	761	java/lang/Exception
        //   283	362	778	java/lang/Error
        //   362	368	778	java/lang/Error
        //   827	832	857	java/lang/Exception
        //   837	842	872	java/lang/Exception
        //   847	852	887	java/lang/Exception
        //   283	362	904	finally
        //   362	368	904	finally
        //   937	942	964	java/lang/Exception
        //   947	952	979	java/lang/Exception
        //   957	962	994	java/lang/Exception
        //   368	402	1024	finally
        //   402	408	1053	finally
        //   413	441	1053	finally
        //   441	450	1075	finally
        //   465	472	1093	finally
        //   487	495	1093	finally
        //   515	524	1093	finally
        //   542	563	1093	finally
        //   578	585	1093	finally
        //   600	612	1093	finally
        //   627	635	1093	finally
        //   804	814	1093	finally
        //   172	181	1113	finally
        //   42	85	1144	finally
        //   85	152	1144	finally
        //   254	275	1144	finally
        //   275	283	1144	finally
        //   368	402	1158	java/lang/Error
        //   402	408	1177	java/lang/Error
        //   413	441	1177	java/lang/Error
        //   441	450	1197	java/lang/Error
        //   465	472	1213	java/lang/Error
        //   487	495	1213	java/lang/Error
        //   515	524	1213	java/lang/Error
        //   542	563	1213	java/lang/Error
        //   578	585	1213	java/lang/Error
        //   600	612	1213	java/lang/Error
        //   627	635	1213	java/lang/Error
        //   42	85	1226	java/lang/Error
        //   85	152	1226	java/lang/Error
        //   254	275	1226	java/lang/Error
        //   275	283	1226	java/lang/Error
        //   283	362	1242	java/lang/Exception
        //   362	368	1242	java/lang/Exception
        //   368	402	1256	java/lang/Exception
        //   402	408	1275	java/lang/Exception
        //   413	441	1275	java/lang/Exception
        //   441	450	1291	java/lang/Exception
        //   465	472	1329	java/lang/Exception
        //   487	495	1329	java/lang/Exception
        //   515	524	1329	java/lang/Exception
        //   542	563	1329	java/lang/Exception
        //   578	585	1329	java/lang/Exception
        //   600	612	1329	java/lang/Exception
        //   627	635	1329	java/lang/Exception
      }
    }.start();
  }
  
  public void c(final String paramString)
  {
    new Thread()
    {
      /* Error */
      public void run()
      {
        // Byte code:
        //   0: aconst_null
        //   1: astore 7
        //   3: aconst_null
        //   4: astore 8
        //   6: aconst_null
        //   7: astore 9
        //   9: aload_0
        //   10: getfield 17	com/baidu/location/h/e$4:b	Lcom/baidu/location/h/e;
        //   13: invokevirtual 30	com/baidu/location/h/e:a	()V
        //   16: aload_0
        //   17: getfield 17	com/baidu/location/h/e$4:b	Lcom/baidu/location/h/e;
        //   20: invokestatic 33	com/baidu/location/h/e:a	(Lcom/baidu/location/h/e;)V
        //   23: aload_0
        //   24: getfield 17	com/baidu/location/h/e$4:b	Lcom/baidu/location/h/e;
        //   27: aload_0
        //   28: getfield 19	com/baidu/location/h/e$4:a	Ljava/lang/String;
        //   31: putfield 36	com/baidu/location/h/e:h	Ljava/lang/String;
        //   34: new 38	java/lang/StringBuffer
        //   37: dup
        //   38: invokespecial 39	java/lang/StringBuffer:<init>	()V
        //   41: astore 4
        //   43: new 41	java/net/URL
        //   46: dup
        //   47: aload_0
        //   48: getfield 17	com/baidu/location/h/e$4:b	Lcom/baidu/location/h/e;
        //   51: getfield 36	com/baidu/location/h/e:h	Ljava/lang/String;
        //   54: invokespecial 43	java/net/URL:<init>	(Ljava/lang/String;)V
        //   57: astore 5
        //   59: aload 5
        //   61: invokevirtual 47	java/net/URL:openConnection	()Ljava/net/URLConnection;
        //   64: checkcast 49	javax/net/ssl/HttpsURLConnection
        //   67: astore_2
        //   68: aload_2
        //   69: iconst_0
        //   70: invokevirtual 53	javax/net/ssl/HttpsURLConnection:setInstanceFollowRedirects	(Z)V
        //   73: aload_2
        //   74: iconst_1
        //   75: invokevirtual 56	javax/net/ssl/HttpsURLConnection:setDoOutput	(Z)V
        //   78: aload_2
        //   79: iconst_1
        //   80: invokevirtual 59	javax/net/ssl/HttpsURLConnection:setDoInput	(Z)V
        //   83: aload_2
        //   84: getstatic 64	com/baidu/location/h/a:b	I
        //   87: invokevirtual 68	javax/net/ssl/HttpsURLConnection:setConnectTimeout	(I)V
        //   90: aload_2
        //   91: getstatic 70	com/baidu/location/h/a:c	I
        //   94: invokevirtual 73	javax/net/ssl/HttpsURLConnection:setReadTimeout	(I)V
        //   97: aload_2
        //   98: ldc 75
        //   100: invokevirtual 78	javax/net/ssl/HttpsURLConnection:setRequestMethod	(Ljava/lang/String;)V
        //   103: aload_2
        //   104: ldc 80
        //   106: ldc 82
        //   108: invokevirtual 86	javax/net/ssl/HttpsURLConnection:setRequestProperty	(Ljava/lang/String;Ljava/lang/String;)V
        //   111: aload_2
        //   112: ldc 88
        //   114: ldc 90
        //   116: invokevirtual 86	javax/net/ssl/HttpsURLConnection:setRequestProperty	(Ljava/lang/String;Ljava/lang/String;)V
        //   119: aload_0
        //   120: getfield 17	com/baidu/location/h/e$4:b	Lcom/baidu/location/h/e;
        //   123: getfield 94	com/baidu/location/h/e:k	Ljava/util/Map;
        //   126: invokeinterface 100 1 0
        //   131: invokeinterface 106 1 0
        //   136: astore_3
        //   137: aload_3
        //   138: invokeinterface 112 1 0
        //   143: ifeq +155 -> 298
        //   146: aload_3
        //   147: invokeinterface 116 1 0
        //   152: checkcast 118	java/util/Map$Entry
        //   155: astore 6
        //   157: aload 4
        //   159: aload 6
        //   161: invokeinterface 121 1 0
        //   166: checkcast 123	java/lang/String
        //   169: invokevirtual 127	java/lang/StringBuffer:append	(Ljava/lang/String;)Ljava/lang/StringBuffer;
        //   172: pop
        //   173: aload 4
        //   175: ldc -127
        //   177: invokevirtual 127	java/lang/StringBuffer:append	(Ljava/lang/String;)Ljava/lang/StringBuffer;
        //   180: pop
        //   181: aload 4
        //   183: aload 6
        //   185: invokeinterface 132 1 0
        //   190: invokevirtual 135	java/lang/StringBuffer:append	(Ljava/lang/Object;)Ljava/lang/StringBuffer;
        //   193: pop
        //   194: aload 4
        //   196: ldc -119
        //   198: invokevirtual 127	java/lang/StringBuffer:append	(Ljava/lang/String;)Ljava/lang/StringBuffer;
        //   201: pop
        //   202: goto -65 -> 137
        //   205: astore 6
        //   207: aconst_null
        //   208: astore_3
        //   209: aload 5
        //   211: astore 4
        //   213: aconst_null
        //   214: astore 8
        //   216: aload_2
        //   217: astore 5
        //   219: aload 9
        //   221: astore 7
        //   223: aload 8
        //   225: astore_2
        //   226: aload 6
        //   228: invokevirtual 140	java/lang/Exception:printStackTrace	()V
        //   231: getstatic 141	com/baidu/location/h/a:a	Ljava/lang/String;
        //   234: ldc -113
        //   236: invokestatic 149	android/util/Log:i	(Ljava/lang/String;Ljava/lang/String;)I
        //   239: pop
        //   240: aload_0
        //   241: getfield 17	com/baidu/location/h/e$4:b	Lcom/baidu/location/h/e;
        //   244: aconst_null
        //   245: putfield 152	com/baidu/location/h/e:j	Ljava/lang/String;
        //   248: aload_0
        //   249: getfield 17	com/baidu/location/h/e$4:b	Lcom/baidu/location/h/e;
        //   252: iconst_0
        //   253: invokevirtual 154	com/baidu/location/h/e:a	(Z)V
        //   256: aload 5
        //   258: ifnull +8 -> 266
        //   261: aload 5
        //   263: invokevirtual 157	javax/net/ssl/HttpsURLConnection:disconnect	()V
        //   266: aload 4
        //   268: ifnull +3 -> 271
        //   271: aload_2
        //   272: ifnull +7 -> 279
        //   275: aload_2
        //   276: invokevirtual 162	java/io/OutputStream:close	()V
        //   279: aload_3
        //   280: ifnull +7 -> 287
        //   283: aload_3
        //   284: invokevirtual 165	java/io/InputStream:close	()V
        //   287: aload 7
        //   289: ifnull +8 -> 297
        //   292: aload 7
        //   294: invokevirtual 168	java/io/ByteArrayOutputStream:close	()V
        //   297: return
        //   298: aload 4
        //   300: invokevirtual 172	java/lang/StringBuffer:length	()I
        //   303: ifle +16 -> 319
        //   306: aload 4
        //   308: aload 4
        //   310: invokevirtual 172	java/lang/StringBuffer:length	()I
        //   313: iconst_1
        //   314: isub
        //   315: invokevirtual 176	java/lang/StringBuffer:deleteCharAt	(I)Ljava/lang/StringBuffer;
        //   318: pop
        //   319: aload_2
        //   320: invokevirtual 180	javax/net/ssl/HttpsURLConnection:getOutputStream	()Ljava/io/OutputStream;
        //   323: astore_3
        //   324: aload_3
        //   325: aload 4
        //   327: invokevirtual 184	java/lang/StringBuffer:toString	()Ljava/lang/String;
        //   330: invokevirtual 188	java/lang/String:getBytes	()[B
        //   333: invokevirtual 192	java/io/OutputStream:write	([B)V
        //   336: aload_3
        //   337: invokevirtual 195	java/io/OutputStream:flush	()V
        //   340: aload_2
        //   341: invokevirtual 198	javax/net/ssl/HttpsURLConnection:getResponseCode	()I
        //   344: sipush 200
        //   347: if_icmpne +171 -> 518
        //   350: aload_2
        //   351: invokevirtual 202	javax/net/ssl/HttpsURLConnection:getInputStream	()Ljava/io/InputStream;
        //   354: astore 4
        //   356: aload_2
        //   357: invokevirtual 205	javax/net/ssl/HttpsURLConnection:getContentEncoding	()Ljava/lang/String;
        //   360: astore 6
        //   362: aload 6
        //   364: ifnull +810 -> 1174
        //   367: aload 6
        //   369: ldc 90
        //   371: invokevirtual 209	java/lang/String:contains	(Ljava/lang/CharSequence;)Z
        //   374: ifeq +800 -> 1174
        //   377: new 211	java/util/zip/GZIPInputStream
        //   380: dup
        //   381: new 213	java/io/BufferedInputStream
        //   384: dup
        //   385: aload 4
        //   387: invokespecial 216	java/io/BufferedInputStream:<init>	(Ljava/io/InputStream;)V
        //   390: invokespecial 217	java/util/zip/GZIPInputStream:<init>	(Ljava/io/InputStream;)V
        //   393: astore 6
        //   395: new 167	java/io/ByteArrayOutputStream
        //   398: dup
        //   399: invokespecial 218	java/io/ByteArrayOutputStream:<init>	()V
        //   402: astore 4
        //   404: sipush 1024
        //   407: newarray <illegal type>
        //   409: astore 7
        //   411: aload 6
        //   413: aload 7
        //   415: invokevirtual 222	java/io/InputStream:read	([B)I
        //   418: istore_1
        //   419: iload_1
        //   420: iconst_m1
        //   421: if_icmpeq +15 -> 436
        //   424: aload 4
        //   426: aload 7
        //   428: iconst_0
        //   429: iload_1
        //   430: invokevirtual 225	java/io/ByteArrayOutputStream:write	([BII)V
        //   433: goto -22 -> 411
        //   436: aload_0
        //   437: getfield 17	com/baidu/location/h/e$4:b	Lcom/baidu/location/h/e;
        //   440: new 123	java/lang/String
        //   443: dup
        //   444: aload 4
        //   446: invokevirtual 228	java/io/ByteArrayOutputStream:toByteArray	()[B
        //   449: ldc -26
        //   451: invokespecial 233	java/lang/String:<init>	([BLjava/lang/String;)V
        //   454: putfield 152	com/baidu/location/h/e:j	Ljava/lang/String;
        //   457: aload_0
        //   458: getfield 17	com/baidu/location/h/e$4:b	Lcom/baidu/location/h/e;
        //   461: iconst_1
        //   462: invokevirtual 154	com/baidu/location/h/e:a	(Z)V
        //   465: aload_2
        //   466: ifnull +7 -> 473
        //   469: aload_2
        //   470: invokevirtual 157	javax/net/ssl/HttpsURLConnection:disconnect	()V
        //   473: aload 5
        //   475: ifnull +3 -> 478
        //   478: aload_3
        //   479: ifnull +7 -> 486
        //   482: aload_3
        //   483: invokevirtual 162	java/io/OutputStream:close	()V
        //   486: aload 6
        //   488: ifnull +8 -> 496
        //   491: aload 6
        //   493: invokevirtual 165	java/io/InputStream:close	()V
        //   496: aload 4
        //   498: ifnull -201 -> 297
        //   501: aload 4
        //   503: invokevirtual 168	java/io/ByteArrayOutputStream:close	()V
        //   506: return
        //   507: astore_2
        //   508: getstatic 141	com/baidu/location/h/a:a	Ljava/lang/String;
        //   511: ldc -21
        //   513: invokestatic 238	android/util/Log:d	(Ljava/lang/String;Ljava/lang/String;)I
        //   516: pop
        //   517: return
        //   518: aload_0
        //   519: getfield 17	com/baidu/location/h/e$4:b	Lcom/baidu/location/h/e;
        //   522: aconst_null
        //   523: putfield 152	com/baidu/location/h/e:j	Ljava/lang/String;
        //   526: aload_0
        //   527: getfield 17	com/baidu/location/h/e$4:b	Lcom/baidu/location/h/e;
        //   530: iconst_0
        //   531: invokevirtual 154	com/baidu/location/h/e:a	(Z)V
        //   534: aconst_null
        //   535: astore 4
        //   537: aconst_null
        //   538: astore 6
        //   540: goto -75 -> 465
        //   543: astore_2
        //   544: getstatic 141	com/baidu/location/h/a:a	Ljava/lang/String;
        //   547: ldc -16
        //   549: invokestatic 238	android/util/Log:d	(Ljava/lang/String;Ljava/lang/String;)I
        //   552: pop
        //   553: goto -67 -> 486
        //   556: astore_2
        //   557: getstatic 141	com/baidu/location/h/a:a	Ljava/lang/String;
        //   560: ldc -14
        //   562: invokestatic 238	android/util/Log:d	(Ljava/lang/String;Ljava/lang/String;)I
        //   565: pop
        //   566: goto -70 -> 496
        //   569: astore_2
        //   570: getstatic 141	com/baidu/location/h/a:a	Ljava/lang/String;
        //   573: ldc -16
        //   575: invokestatic 238	android/util/Log:d	(Ljava/lang/String;Ljava/lang/String;)I
        //   578: pop
        //   579: goto -300 -> 279
        //   582: astore_2
        //   583: getstatic 141	com/baidu/location/h/a:a	Ljava/lang/String;
        //   586: ldc -14
        //   588: invokestatic 238	android/util/Log:d	(Ljava/lang/String;Ljava/lang/String;)I
        //   591: pop
        //   592: goto -305 -> 287
        //   595: astore_2
        //   596: getstatic 141	com/baidu/location/h/a:a	Ljava/lang/String;
        //   599: ldc -21
        //   601: invokestatic 238	android/util/Log:d	(Ljava/lang/String;Ljava/lang/String;)I
        //   604: pop
        //   605: return
        //   606: astore_2
        //   607: aconst_null
        //   608: astore 4
        //   610: aconst_null
        //   611: astore 6
        //   613: aconst_null
        //   614: astore 5
        //   616: aconst_null
        //   617: astore_3
        //   618: aload_2
        //   619: invokevirtual 243	java/lang/Error:printStackTrace	()V
        //   622: getstatic 141	com/baidu/location/h/a:a	Ljava/lang/String;
        //   625: ldc -11
        //   627: invokestatic 149	android/util/Log:i	(Ljava/lang/String;Ljava/lang/String;)I
        //   630: pop
        //   631: aload_0
        //   632: getfield 17	com/baidu/location/h/e$4:b	Lcom/baidu/location/h/e;
        //   635: aconst_null
        //   636: putfield 152	com/baidu/location/h/e:j	Ljava/lang/String;
        //   639: aload_0
        //   640: getfield 17	com/baidu/location/h/e$4:b	Lcom/baidu/location/h/e;
        //   643: iconst_0
        //   644: invokevirtual 154	com/baidu/location/h/e:a	(Z)V
        //   647: aload_3
        //   648: ifnull +7 -> 655
        //   651: aload_3
        //   652: invokevirtual 157	javax/net/ssl/HttpsURLConnection:disconnect	()V
        //   655: aload 5
        //   657: ifnull +3 -> 660
        //   660: aload 7
        //   662: ifnull +8 -> 670
        //   665: aload 7
        //   667: invokevirtual 162	java/io/OutputStream:close	()V
        //   670: aload 6
        //   672: ifnull +8 -> 680
        //   675: aload 6
        //   677: invokevirtual 165	java/io/InputStream:close	()V
        //   680: aload 4
        //   682: ifnull -385 -> 297
        //   685: aload 4
        //   687: invokevirtual 168	java/io/ByteArrayOutputStream:close	()V
        //   690: return
        //   691: astore_2
        //   692: getstatic 141	com/baidu/location/h/a:a	Ljava/lang/String;
        //   695: ldc -21
        //   697: invokestatic 238	android/util/Log:d	(Ljava/lang/String;Ljava/lang/String;)I
        //   700: pop
        //   701: return
        //   702: astore_2
        //   703: getstatic 141	com/baidu/location/h/a:a	Ljava/lang/String;
        //   706: ldc -16
        //   708: invokestatic 238	android/util/Log:d	(Ljava/lang/String;Ljava/lang/String;)I
        //   711: pop
        //   712: goto -42 -> 670
        //   715: astore_2
        //   716: getstatic 141	com/baidu/location/h/a:a	Ljava/lang/String;
        //   719: ldc -14
        //   721: invokestatic 238	android/util/Log:d	(Ljava/lang/String;Ljava/lang/String;)I
        //   724: pop
        //   725: goto -45 -> 680
        //   728: astore_2
        //   729: aconst_null
        //   730: astore 4
        //   732: aconst_null
        //   733: astore 6
        //   735: aconst_null
        //   736: astore 5
        //   738: aconst_null
        //   739: astore_3
        //   740: aload 8
        //   742: astore 7
        //   744: aload_3
        //   745: ifnull +7 -> 752
        //   748: aload_3
        //   749: invokevirtual 157	javax/net/ssl/HttpsURLConnection:disconnect	()V
        //   752: aload 5
        //   754: ifnull +3 -> 757
        //   757: aload 7
        //   759: ifnull +8 -> 767
        //   762: aload 7
        //   764: invokevirtual 162	java/io/OutputStream:close	()V
        //   767: aload 6
        //   769: ifnull +8 -> 777
        //   772: aload 6
        //   774: invokevirtual 165	java/io/InputStream:close	()V
        //   777: aload 4
        //   779: ifnull +8 -> 787
        //   782: aload 4
        //   784: invokevirtual 168	java/io/ByteArrayOutputStream:close	()V
        //   787: aload_2
        //   788: athrow
        //   789: astore_3
        //   790: getstatic 141	com/baidu/location/h/a:a	Ljava/lang/String;
        //   793: ldc -16
        //   795: invokestatic 238	android/util/Log:d	(Ljava/lang/String;Ljava/lang/String;)I
        //   798: pop
        //   799: goto -32 -> 767
        //   802: astore_3
        //   803: getstatic 141	com/baidu/location/h/a:a	Ljava/lang/String;
        //   806: ldc -14
        //   808: invokestatic 238	android/util/Log:d	(Ljava/lang/String;Ljava/lang/String;)I
        //   811: pop
        //   812: goto -35 -> 777
        //   815: astore_3
        //   816: getstatic 141	com/baidu/location/h/a:a	Ljava/lang/String;
        //   819: ldc -21
        //   821: invokestatic 238	android/util/Log:d	(Ljava/lang/String;Ljava/lang/String;)I
        //   824: pop
        //   825: goto -38 -> 787
        //   828: astore_2
        //   829: aconst_null
        //   830: astore 4
        //   832: aconst_null
        //   833: astore 6
        //   835: aconst_null
        //   836: astore_3
        //   837: aload 8
        //   839: astore 7
        //   841: goto -97 -> 744
        //   844: astore 7
        //   846: aconst_null
        //   847: astore 4
        //   849: aconst_null
        //   850: astore 6
        //   852: aload_2
        //   853: astore_3
        //   854: aload 7
        //   856: astore_2
        //   857: aload 8
        //   859: astore 7
        //   861: goto -117 -> 744
        //   864: astore 8
        //   866: aconst_null
        //   867: astore 4
        //   869: aconst_null
        //   870: astore 6
        //   872: aload_3
        //   873: astore 7
        //   875: aload_2
        //   876: astore_3
        //   877: aload 8
        //   879: astore_2
        //   880: goto -136 -> 744
        //   883: astore 8
        //   885: aload 4
        //   887: astore 6
        //   889: aconst_null
        //   890: astore 4
        //   892: aload_3
        //   893: astore 7
        //   895: aload_2
        //   896: astore_3
        //   897: aload 8
        //   899: astore_2
        //   900: goto -156 -> 744
        //   903: astore 8
        //   905: aconst_null
        //   906: astore 4
        //   908: aload_3
        //   909: astore 7
        //   911: aload_2
        //   912: astore_3
        //   913: aload 8
        //   915: astore_2
        //   916: goto -172 -> 744
        //   919: astore 8
        //   921: aload_3
        //   922: astore 7
        //   924: aload_2
        //   925: astore_3
        //   926: aload 8
        //   928: astore_2
        //   929: goto -185 -> 744
        //   932: astore 9
        //   934: aload 4
        //   936: astore 8
        //   938: aload 7
        //   940: astore 4
        //   942: aload_2
        //   943: astore 7
        //   945: aload_3
        //   946: astore 6
        //   948: aload 9
        //   950: astore_2
        //   951: aload 5
        //   953: astore_3
        //   954: aload 8
        //   956: astore 5
        //   958: goto -214 -> 744
        //   961: astore_2
        //   962: goto -218 -> 744
        //   965: astore_2
        //   966: aconst_null
        //   967: astore 4
        //   969: aconst_null
        //   970: astore 6
        //   972: aconst_null
        //   973: astore_3
        //   974: goto -356 -> 618
        //   977: astore 8
        //   979: aconst_null
        //   980: astore 4
        //   982: aconst_null
        //   983: astore 6
        //   985: aload_2
        //   986: astore_3
        //   987: aload 8
        //   989: astore_2
        //   990: goto -372 -> 618
        //   993: astore 8
        //   995: aconst_null
        //   996: astore 4
        //   998: aconst_null
        //   999: astore 6
        //   1001: aload_3
        //   1002: astore 7
        //   1004: aload_2
        //   1005: astore_3
        //   1006: aload 8
        //   1008: astore_2
        //   1009: goto -391 -> 618
        //   1012: astore 8
        //   1014: aload 4
        //   1016: astore 6
        //   1018: aconst_null
        //   1019: astore 4
        //   1021: aload_3
        //   1022: astore 7
        //   1024: aload_2
        //   1025: astore_3
        //   1026: aload 8
        //   1028: astore_2
        //   1029: goto -411 -> 618
        //   1032: astore 8
        //   1034: aconst_null
        //   1035: astore 4
        //   1037: aload_3
        //   1038: astore 7
        //   1040: aload_2
        //   1041: astore_3
        //   1042: aload 8
        //   1044: astore_2
        //   1045: goto -427 -> 618
        //   1048: astore 8
        //   1050: aload_3
        //   1051: astore 7
        //   1053: aload_2
        //   1054: astore_3
        //   1055: aload 8
        //   1057: astore_2
        //   1058: goto -440 -> 618
        //   1061: astore 6
        //   1063: aconst_null
        //   1064: astore_2
        //   1065: aconst_null
        //   1066: astore_3
        //   1067: aconst_null
        //   1068: astore 4
        //   1070: aconst_null
        //   1071: astore 5
        //   1073: aload 9
        //   1075: astore 7
        //   1077: goto -851 -> 226
        //   1080: astore 6
        //   1082: aconst_null
        //   1083: astore_2
        //   1084: aconst_null
        //   1085: astore_3
        //   1086: aload 5
        //   1088: astore 4
        //   1090: aconst_null
        //   1091: astore 5
        //   1093: aload 9
        //   1095: astore 7
        //   1097: goto -871 -> 226
        //   1100: astore 6
        //   1102: aload 5
        //   1104: astore 4
        //   1106: aload_2
        //   1107: astore 5
        //   1109: aload_3
        //   1110: astore_2
        //   1111: aconst_null
        //   1112: astore_3
        //   1113: aload 9
        //   1115: astore 7
        //   1117: goto -891 -> 226
        //   1120: astore 6
        //   1122: aload_2
        //   1123: astore 8
        //   1125: aload_3
        //   1126: astore_2
        //   1127: aload 4
        //   1129: astore_3
        //   1130: aload 5
        //   1132: astore 4
        //   1134: aload 9
        //   1136: astore 7
        //   1138: aload 8
        //   1140: astore 5
        //   1142: goto -916 -> 226
        //   1145: astore 8
        //   1147: aload 5
        //   1149: astore 4
        //   1151: aload 6
        //   1153: astore 7
        //   1155: aload_2
        //   1156: astore 5
        //   1158: aload 8
        //   1160: astore 6
        //   1162: aload_3
        //   1163: astore_2
        //   1164: aload 7
        //   1166: astore_3
        //   1167: aload 9
        //   1169: astore 7
        //   1171: goto -945 -> 226
        //   1174: aload 4
        //   1176: astore 6
        //   1178: goto -783 -> 395
        //   1181: astore 9
        //   1183: aload 6
        //   1185: astore 7
        //   1187: aload_2
        //   1188: astore 8
        //   1190: aload 9
        //   1192: astore 6
        //   1194: aload_3
        //   1195: astore_2
        //   1196: aload 7
        //   1198: astore_3
        //   1199: aload 4
        //   1201: astore 7
        //   1203: aload 5
        //   1205: astore 4
        //   1207: aload 8
        //   1209: astore 5
        //   1211: goto -985 -> 226
        // Local variable table:
        //   start	length	slot	name	signature
        //   0	1214	0	this	4
        //   418	12	1	i	int
        //   67	403	2	localObject1	Object
        //   507	1	2	localException1	Exception
        //   543	1	2	localException2	Exception
        //   556	1	2	localException3	Exception
        //   569	1	2	localException4	Exception
        //   582	1	2	localException5	Exception
        //   595	1	2	localException6	Exception
        //   606	13	2	localError1	Error
        //   691	1	2	localException7	Exception
        //   702	1	2	localException8	Exception
        //   715	1	2	localException9	Exception
        //   728	60	2	localObject2	Object
        //   828	25	2	localObject3	Object
        //   856	95	2	localObject4	Object
        //   961	1	2	localObject5	Object
        //   965	21	2	localError2	Error
        //   989	207	2	localObject6	Object
        //   136	613	3	localObject7	Object
        //   789	1	3	localException10	Exception
        //   802	1	3	localException11	Exception
        //   815	1	3	localException12	Exception
        //   836	363	3	localObject8	Object
        //   41	1165	4	localObject9	Object
        //   57	1153	5	localObject10	Object
        //   155	29	6	localEntry	java.util.Map.Entry
        //   205	22	6	localException13	Exception
        //   360	657	6	localObject11	Object
        //   1061	1	6	localException14	Exception
        //   1080	1	6	localException15	Exception
        //   1100	1	6	localException16	Exception
        //   1120	32	6	localException17	Exception
        //   1160	33	6	localObject12	Object
        //   1	839	7	localObject13	Object
        //   844	11	7	localObject14	Object
        //   859	343	7	localObject15	Object
        //   4	854	8	localObject16	Object
        //   864	14	8	localObject17	Object
        //   883	15	8	localObject18	Object
        //   903	11	8	localObject19	Object
        //   919	8	8	localObject20	Object
        //   936	19	8	localObject21	Object
        //   977	11	8	localError3	Error
        //   993	14	8	localError4	Error
        //   1012	15	8	localError5	Error
        //   1032	11	8	localError6	Error
        //   1048	8	8	localError7	Error
        //   1123	16	8	localObject22	Object
        //   1145	14	8	localException18	Exception
        //   1188	20	8	localObject23	Object
        //   7	213	9	localObject24	Object
        //   932	236	9	localObject25	Object
        //   1181	10	9	localException19	Exception
        // Exception table:
        //   from	to	target	type
        //   68	137	205	java/lang/Exception
        //   137	202	205	java/lang/Exception
        //   298	319	205	java/lang/Exception
        //   319	324	205	java/lang/Exception
        //   501	506	507	java/lang/Exception
        //   482	486	543	java/lang/Exception
        //   491	496	556	java/lang/Exception
        //   275	279	569	java/lang/Exception
        //   283	287	582	java/lang/Exception
        //   292	297	595	java/lang/Exception
        //   34	59	606	java/lang/Error
        //   685	690	691	java/lang/Exception
        //   665	670	702	java/lang/Exception
        //   675	680	715	java/lang/Exception
        //   34	59	728	finally
        //   762	767	789	java/lang/Exception
        //   772	777	802	java/lang/Exception
        //   782	787	815	java/lang/Exception
        //   59	68	828	finally
        //   68	137	844	finally
        //   137	202	844	finally
        //   298	319	844	finally
        //   319	324	844	finally
        //   324	356	864	finally
        //   518	534	864	finally
        //   356	362	883	finally
        //   367	395	883	finally
        //   395	404	903	finally
        //   404	411	919	finally
        //   411	419	919	finally
        //   424	433	919	finally
        //   436	465	919	finally
        //   226	256	932	finally
        //   618	647	961	finally
        //   59	68	965	java/lang/Error
        //   68	137	977	java/lang/Error
        //   137	202	977	java/lang/Error
        //   298	319	977	java/lang/Error
        //   319	324	977	java/lang/Error
        //   324	356	993	java/lang/Error
        //   518	534	993	java/lang/Error
        //   356	362	1012	java/lang/Error
        //   367	395	1012	java/lang/Error
        //   395	404	1032	java/lang/Error
        //   404	411	1048	java/lang/Error
        //   411	419	1048	java/lang/Error
        //   424	433	1048	java/lang/Error
        //   436	465	1048	java/lang/Error
        //   34	59	1061	java/lang/Exception
        //   59	68	1080	java/lang/Exception
        //   324	356	1100	java/lang/Exception
        //   518	534	1100	java/lang/Exception
        //   356	362	1120	java/lang/Exception
        //   367	395	1120	java/lang/Exception
        //   395	404	1145	java/lang/Exception
        //   404	411	1181	java/lang/Exception
        //   411	419	1181	java/lang/Exception
        //   424	433	1181	java/lang/Exception
        //   436	465	1181	java/lang/Exception
      }
    }.start();
  }
  
  public void h()
  {
    new Thread()
    {
      /* Error */
      public void run()
      {
        // Byte code:
        //   0: aconst_null
        //   1: astore 8
        //   3: aload_0
        //   4: getfield 15	com/baidu/location/h/e$1:a	Lcom/baidu/location/h/e;
        //   7: invokestatic 27	com/baidu/location/h/g:e	()Ljava/lang/String;
        //   10: putfield 30	com/baidu/location/h/e:h	Ljava/lang/String;
        //   13: aload_0
        //   14: getfield 15	com/baidu/location/h/e$1:a	Lcom/baidu/location/h/e;
        //   17: invokestatic 32	com/baidu/location/h/e:a	(Lcom/baidu/location/h/e;)V
        //   20: aload_0
        //   21: getfield 15	com/baidu/location/h/e$1:a	Lcom/baidu/location/h/e;
        //   24: invokevirtual 34	com/baidu/location/h/e:a	()V
        //   27: aload_0
        //   28: getfield 15	com/baidu/location/h/e$1:a	Lcom/baidu/location/h/e;
        //   31: getfield 38	com/baidu/location/h/e:i	I
        //   34: istore_2
        //   35: aconst_null
        //   36: astore 5
        //   38: iload_2
        //   39: ifle +189 -> 228
        //   42: new 40	java/net/URL
        //   45: dup
        //   46: aload_0
        //   47: getfield 15	com/baidu/location/h/e$1:a	Lcom/baidu/location/h/e;
        //   50: getfield 30	com/baidu/location/h/e:h	Ljava/lang/String;
        //   53: invokespecial 43	java/net/URL:<init>	(Ljava/lang/String;)V
        //   56: invokevirtual 47	java/net/URL:openConnection	()Ljava/net/URLConnection;
        //   59: checkcast 49	java/net/HttpURLConnection
        //   62: astore_3
        //   63: aload_3
        //   64: ldc 51
        //   66: invokevirtual 54	java/net/HttpURLConnection:setRequestMethod	(Ljava/lang/String;)V
        //   69: aload_3
        //   70: iconst_1
        //   71: invokevirtual 58	java/net/HttpURLConnection:setDoInput	(Z)V
        //   74: aload_3
        //   75: iconst_1
        //   76: invokevirtual 61	java/net/HttpURLConnection:setDoOutput	(Z)V
        //   79: aload_3
        //   80: iconst_0
        //   81: invokevirtual 64	java/net/HttpURLConnection:setUseCaches	(Z)V
        //   84: aload_3
        //   85: getstatic 69	com/baidu/location/h/a:b	I
        //   88: invokevirtual 73	java/net/HttpURLConnection:setConnectTimeout	(I)V
        //   91: aload_3
        //   92: getstatic 69	com/baidu/location/h/a:b	I
        //   95: invokevirtual 76	java/net/HttpURLConnection:setReadTimeout	(I)V
        //   98: aload_3
        //   99: ldc 78
        //   101: ldc 80
        //   103: invokevirtual 84	java/net/HttpURLConnection:setRequestProperty	(Ljava/lang/String;Ljava/lang/String;)V
        //   106: aload_3
        //   107: ldc 86
        //   109: ldc 88
        //   111: invokevirtual 84	java/net/HttpURLConnection:setRequestProperty	(Ljava/lang/String;Ljava/lang/String;)V
        //   114: aload_3
        //   115: invokevirtual 92	java/net/HttpURLConnection:getResponseCode	()I
        //   118: sipush 200
        //   121: if_icmpne +220 -> 341
        //   124: aload_3
        //   125: invokevirtual 96	java/net/HttpURLConnection:getInputStream	()Ljava/io/InputStream;
        //   128: astore 4
        //   130: new 98	java/io/ByteArrayOutputStream
        //   133: dup
        //   134: invokespecial 99	java/io/ByteArrayOutputStream:<init>	()V
        //   137: astore 5
        //   139: sipush 1024
        //   142: newarray <illegal type>
        //   144: astore 6
        //   146: aload 4
        //   148: aload 6
        //   150: invokevirtual 105	java/io/InputStream:read	([B)I
        //   153: istore_1
        //   154: iload_1
        //   155: iconst_m1
        //   156: if_icmpeq +101 -> 257
        //   159: aload 5
        //   161: aload 6
        //   163: iconst_0
        //   164: iload_1
        //   165: invokevirtual 109	java/io/ByteArrayOutputStream:write	([BII)V
        //   168: goto -22 -> 146
        //   171: astore 6
        //   173: aload 5
        //   175: astore 6
        //   177: aload 4
        //   179: astore 5
        //   181: aload 6
        //   183: astore 4
        //   185: getstatic 111	com/baidu/location/h/a:a	Ljava/lang/String;
        //   188: ldc 113
        //   190: invokestatic 119	android/util/Log:d	(Ljava/lang/String;Ljava/lang/String;)I
        //   193: pop
        //   194: aload_3
        //   195: ifnull +7 -> 202
        //   198: aload_3
        //   199: invokevirtual 122	java/net/HttpURLConnection:disconnect	()V
        //   202: aload 5
        //   204: ifnull +8 -> 212
        //   207: aload 5
        //   209: invokevirtual 125	java/io/InputStream:close	()V
        //   212: aload 4
        //   214: ifnull +370 -> 584
        //   217: aload 4
        //   219: invokevirtual 126	java/io/ByteArrayOutputStream:close	()V
        //   222: iconst_0
        //   223: istore_1
        //   224: iload_1
        //   225: ifeq +240 -> 465
        //   228: iload_2
        //   229: ifgt +246 -> 475
        //   232: getstatic 129	com/baidu/location/h/e:o	I
        //   235: iconst_1
        //   236: iadd
        //   237: putstatic 129	com/baidu/location/h/e:o	I
        //   240: aload_0
        //   241: getfield 15	com/baidu/location/h/e$1:a	Lcom/baidu/location/h/e;
        //   244: aconst_null
        //   245: putfield 132	com/baidu/location/h/e:j	Ljava/lang/String;
        //   248: aload_0
        //   249: getfield 15	com/baidu/location/h/e$1:a	Lcom/baidu/location/h/e;
        //   252: iconst_0
        //   253: invokevirtual 134	com/baidu/location/h/e:a	(Z)V
        //   256: return
        //   257: aload 4
        //   259: invokevirtual 125	java/io/InputStream:close	()V
        //   262: aload 5
        //   264: invokevirtual 126	java/io/ByteArrayOutputStream:close	()V
        //   267: aload_0
        //   268: getfield 15	com/baidu/location/h/e$1:a	Lcom/baidu/location/h/e;
        //   271: new 136	java/lang/String
        //   274: dup
        //   275: aload 5
        //   277: invokevirtual 140	java/io/ByteArrayOutputStream:toByteArray	()[B
        //   280: ldc -114
        //   282: invokespecial 145	java/lang/String:<init>	([BLjava/lang/String;)V
        //   285: putfield 132	com/baidu/location/h/e:j	Ljava/lang/String;
        //   288: aload_0
        //   289: getfield 15	com/baidu/location/h/e$1:a	Lcom/baidu/location/h/e;
        //   292: iconst_1
        //   293: invokevirtual 134	com/baidu/location/h/e:a	(Z)V
        //   296: aload_3
        //   297: invokevirtual 122	java/net/HttpURLConnection:disconnect	()V
        //   300: iconst_1
        //   301: istore_1
        //   302: aload 4
        //   304: astore 6
        //   306: aload 5
        //   308: astore 4
        //   310: aload_3
        //   311: ifnull +7 -> 318
        //   314: aload_3
        //   315: invokevirtual 122	java/net/HttpURLConnection:disconnect	()V
        //   318: aload 6
        //   320: ifnull +8 -> 328
        //   323: aload 6
        //   325: invokevirtual 125	java/io/InputStream:close	()V
        //   328: aload 4
        //   330: ifnull +259 -> 589
        //   333: aload 4
        //   335: invokevirtual 126	java/io/ByteArrayOutputStream:close	()V
        //   338: goto -114 -> 224
        //   341: aload_3
        //   342: invokevirtual 122	java/net/HttpURLConnection:disconnect	()V
        //   345: iconst_0
        //   346: istore_1
        //   347: aconst_null
        //   348: astore 4
        //   350: aconst_null
        //   351: astore 6
        //   353: goto -43 -> 310
        //   356: astore 5
        //   358: aload 5
        //   360: invokevirtual 148	java/lang/Exception:printStackTrace	()V
        //   363: goto -35 -> 328
        //   366: astore 4
        //   368: aload 4
        //   370: invokevirtual 148	java/lang/Exception:printStackTrace	()V
        //   373: goto -149 -> 224
        //   376: astore 5
        //   378: aload 5
        //   380: invokevirtual 148	java/lang/Exception:printStackTrace	()V
        //   383: goto -171 -> 212
        //   386: astore 4
        //   388: aload 4
        //   390: invokevirtual 148	java/lang/Exception:printStackTrace	()V
        //   393: iconst_0
        //   394: istore_1
        //   395: goto -171 -> 224
        //   398: astore 7
        //   400: aconst_null
        //   401: astore 4
        //   403: aload 8
        //   405: astore 6
        //   407: aload_3
        //   408: astore 5
        //   410: aload 7
        //   412: astore_3
        //   413: aload 5
        //   415: ifnull +8 -> 423
        //   418: aload 5
        //   420: invokevirtual 122	java/net/HttpURLConnection:disconnect	()V
        //   423: aload 4
        //   425: ifnull +8 -> 433
        //   428: aload 4
        //   430: invokevirtual 125	java/io/InputStream:close	()V
        //   433: aload 6
        //   435: ifnull +8 -> 443
        //   438: aload 6
        //   440: invokevirtual 126	java/io/ByteArrayOutputStream:close	()V
        //   443: aload_3
        //   444: athrow
        //   445: astore 4
        //   447: aload 4
        //   449: invokevirtual 148	java/lang/Exception:printStackTrace	()V
        //   452: goto -19 -> 433
        //   455: astore 4
        //   457: aload 4
        //   459: invokevirtual 148	java/lang/Exception:printStackTrace	()V
        //   462: goto -19 -> 443
        //   465: iload_2
        //   466: iconst_1
        //   467: isub
        //   468: istore_2
        //   469: aload_3
        //   470: astore 5
        //   472: goto -434 -> 38
        //   475: iconst_0
        //   476: putstatic 129	com/baidu/location/h/e:o	I
        //   479: return
        //   480: astore 6
        //   482: aload_3
        //   483: astore 5
        //   485: aload 6
        //   487: astore_3
        //   488: aload 8
        //   490: astore 6
        //   492: goto -79 -> 413
        //   495: astore 7
        //   497: aload 5
        //   499: astore 6
        //   501: aload_3
        //   502: astore 5
        //   504: aload 7
        //   506: astore_3
        //   507: goto -94 -> 413
        //   510: astore 6
        //   512: aload_3
        //   513: astore 8
        //   515: aload 5
        //   517: astore 7
        //   519: aload 6
        //   521: astore_3
        //   522: aload 8
        //   524: astore 5
        //   526: aload 4
        //   528: astore 6
        //   530: aload 7
        //   532: astore 4
        //   534: goto -121 -> 413
        //   537: astore_3
        //   538: aconst_null
        //   539: astore 4
        //   541: aload 8
        //   543: astore 6
        //   545: goto -132 -> 413
        //   548: astore 4
        //   550: aconst_null
        //   551: astore 5
        //   553: aconst_null
        //   554: astore 4
        //   556: goto -371 -> 185
        //   559: astore 5
        //   561: aload 4
        //   563: astore 5
        //   565: aconst_null
        //   566: astore 4
        //   568: goto -383 -> 185
        //   571: astore_3
        //   572: aconst_null
        //   573: astore 4
        //   575: aload 5
        //   577: astore_3
        //   578: aconst_null
        //   579: astore 5
        //   581: goto -396 -> 185
        //   584: iconst_0
        //   585: istore_1
        //   586: goto -362 -> 224
        //   589: goto -365 -> 224
        // Local variable table:
        //   start	length	slot	name	signature
        //   0	592	0	this	1
        //   153	433	1	i	int
        //   34	435	2	j	int
        //   62	460	3	localObject1	Object
        //   537	1	3	localObject2	Object
        //   571	1	3	localException1	Exception
        //   577	1	3	localObject3	Object
        //   128	221	4	localObject4	Object
        //   366	3	4	localException2	Exception
        //   386	3	4	localException3	Exception
        //   401	28	4	localObject5	Object
        //   445	3	4	localException4	Exception
        //   455	72	4	localException5	Exception
        //   532	8	4	localObject6	Object
        //   548	1	4	localException6	Exception
        //   554	20	4	localObject7	Object
        //   36	271	5	localObject8	Object
        //   356	3	5	localException7	Exception
        //   376	3	5	localException8	Exception
        //   408	144	5	localObject9	Object
        //   559	1	5	localException9	Exception
        //   563	17	5	localObject10	Object
        //   144	18	6	arrayOfByte	byte[]
        //   171	1	6	localException10	Exception
        //   175	264	6	localObject11	Object
        //   480	6	6	localObject12	Object
        //   490	10	6	localObject13	Object
        //   510	10	6	localObject14	Object
        //   528	16	6	localObject15	Object
        //   398	13	7	localObject16	Object
        //   495	10	7	localObject17	Object
        //   517	14	7	localObject18	Object
        //   1	541	8	localObject19	Object
        // Exception table:
        //   from	to	target	type
        //   139	146	171	java/lang/Exception
        //   146	154	171	java/lang/Exception
        //   159	168	171	java/lang/Exception
        //   257	300	171	java/lang/Exception
        //   323	328	356	java/lang/Exception
        //   333	338	366	java/lang/Exception
        //   207	212	376	java/lang/Exception
        //   217	222	386	java/lang/Exception
        //   63	130	398	finally
        //   341	345	398	finally
        //   428	433	445	java/lang/Exception
        //   438	443	455	java/lang/Exception
        //   130	139	480	finally
        //   139	146	495	finally
        //   146	154	495	finally
        //   159	168	495	finally
        //   257	300	495	finally
        //   185	194	510	finally
        //   42	63	537	finally
        //   63	130	548	java/lang/Exception
        //   341	345	548	java/lang/Exception
        //   130	139	559	java/lang/Exception
        //   42	63	571	java/lang/Exception
      }
    }.start();
  }
  
  public void i()
  {
    a(false, "loc.map.baidu.com");
  }
  
  public void j()
  {
    new Thread()
    {
      /* Error */
      public void run()
      {
        // Byte code:
        //   0: aconst_null
        //   1: astore 14
        //   3: aload_0
        //   4: getfield 15	com/baidu/location/h/e$3:a	Lcom/baidu/location/h/e;
        //   7: invokestatic 29	com/baidu/location/h/g:e	()Ljava/lang/String;
        //   10: putfield 33	com/baidu/location/h/e:h	Ljava/lang/String;
        //   13: aload_0
        //   14: getfield 15	com/baidu/location/h/e$3:a	Lcom/baidu/location/h/e;
        //   17: invokestatic 35	com/baidu/location/h/e:a	(Lcom/baidu/location/h/e;)V
        //   20: aload_0
        //   21: getfield 15	com/baidu/location/h/e$3:a	Lcom/baidu/location/h/e;
        //   24: invokevirtual 37	com/baidu/location/h/e:a	()V
        //   27: aload_0
        //   28: getfield 15	com/baidu/location/h/e$3:a	Lcom/baidu/location/h/e;
        //   31: getfield 41	com/baidu/location/h/e:i	I
        //   34: istore_2
        //   35: aconst_null
        //   36: astore 4
        //   38: iload_2
        //   39: ifle +385 -> 424
        //   42: new 43	java/net/URL
        //   45: dup
        //   46: aload_0
        //   47: getfield 15	com/baidu/location/h/e$3:a	Lcom/baidu/location/h/e;
        //   50: getfield 33	com/baidu/location/h/e:h	Ljava/lang/String;
        //   53: invokespecial 46	java/net/URL:<init>	(Ljava/lang/String;)V
        //   56: astore_3
        //   57: new 48	java/io/FileInputStream
        //   60: dup
        //   61: aload_0
        //   62: getfield 15	com/baidu/location/h/e$3:a	Lcom/baidu/location/h/e;
        //   65: getfield 51	com/baidu/location/h/e:l	Ljava/lang/String;
        //   68: invokespecial 52	java/io/FileInputStream:<init>	(Ljava/lang/String;)V
        //   71: astore 5
        //   73: aload 5
        //   75: invokevirtual 56	java/io/FileInputStream:available	()I
        //   78: newarray <illegal type>
        //   80: astore 6
        //   82: aload 5
        //   84: aload 6
        //   86: invokevirtual 60	java/io/FileInputStream:read	([B)I
        //   89: pop
        //   90: aload_3
        //   91: invokevirtual 64	java/net/URL:openConnection	()Ljava/net/URLConnection;
        //   94: checkcast 66	java/net/HttpURLConnection
        //   97: astore_3
        //   98: aload_3
        //   99: ldc 68
        //   101: invokevirtual 71	java/net/HttpURLConnection:setRequestMethod	(Ljava/lang/String;)V
        //   104: aload_3
        //   105: iconst_1
        //   106: invokevirtual 75	java/net/HttpURLConnection:setDoInput	(Z)V
        //   109: aload_3
        //   110: iconst_1
        //   111: invokevirtual 78	java/net/HttpURLConnection:setDoOutput	(Z)V
        //   114: aload_3
        //   115: iconst_0
        //   116: invokevirtual 81	java/net/HttpURLConnection:setUseCaches	(Z)V
        //   119: aload_3
        //   120: getstatic 86	com/baidu/location/h/a:b	I
        //   123: invokevirtual 90	java/net/HttpURLConnection:setConnectTimeout	(I)V
        //   126: aload_3
        //   127: getstatic 93	com/baidu/location/h/a:c	I
        //   130: invokevirtual 96	java/net/HttpURLConnection:setReadTimeout	(I)V
        //   133: aload_3
        //   134: ldc 98
        //   136: ldc 100
        //   138: invokevirtual 104	java/net/HttpURLConnection:setRequestProperty	(Ljava/lang/String;Ljava/lang/String;)V
        //   141: aload_3
        //   142: ldc 106
        //   144: ldc 108
        //   146: invokevirtual 104	java/net/HttpURLConnection:setRequestProperty	(Ljava/lang/String;Ljava/lang/String;)V
        //   149: aload_3
        //   150: ldc 110
        //   152: ldc 112
        //   154: invokevirtual 104	java/net/HttpURLConnection:setRequestProperty	(Ljava/lang/String;Ljava/lang/String;)V
        //   157: aload_3
        //   158: ldc 114
        //   160: ldc 116
        //   162: invokevirtual 104	java/net/HttpURLConnection:setRequestProperty	(Ljava/lang/String;Ljava/lang/String;)V
        //   165: aload_3
        //   166: invokevirtual 120	java/net/HttpURLConnection:getOutputStream	()Ljava/io/OutputStream;
        //   169: astore 4
        //   171: aload 4
        //   173: aload 6
        //   175: invokevirtual 126	java/io/OutputStream:write	([B)V
        //   178: aload 4
        //   180: invokevirtual 129	java/io/OutputStream:flush	()V
        //   183: aload_3
        //   184: invokevirtual 132	java/net/HttpURLConnection:getResponseCode	()I
        //   187: sipush 200
        //   190: if_icmpne +1245 -> 1435
        //   193: aload_3
        //   194: invokevirtual 136	java/net/HttpURLConnection:getInputStream	()Ljava/io/InputStream;
        //   197: astore 7
        //   199: aload_3
        //   200: invokevirtual 139	java/net/HttpURLConnection:getContentEncoding	()Ljava/lang/String;
        //   203: astore 6
        //   205: aload 6
        //   207: ifnull +1221 -> 1428
        //   210: aload 6
        //   212: ldc 112
        //   214: invokevirtual 145	java/lang/String:contains	(Ljava/lang/CharSequence;)Z
        //   217: ifeq +1211 -> 1428
        //   220: new 147	java/util/zip/GZIPInputStream
        //   223: dup
        //   224: new 149	java/io/BufferedInputStream
        //   227: dup
        //   228: aload 7
        //   230: invokespecial 152	java/io/BufferedInputStream:<init>	(Ljava/io/InputStream;)V
        //   233: invokespecial 153	java/util/zip/GZIPInputStream:<init>	(Ljava/io/InputStream;)V
        //   236: astore 6
        //   238: new 155	java/io/ByteArrayOutputStream
        //   241: dup
        //   242: invokespecial 156	java/io/ByteArrayOutputStream:<init>	()V
        //   245: astore 8
        //   247: aload_3
        //   248: astore 12
        //   250: aload 5
        //   252: astore 11
        //   254: aload 4
        //   256: astore 13
        //   258: aload 8
        //   260: astore 10
        //   262: aload 6
        //   264: astore 9
        //   266: sipush 1024
        //   269: newarray <illegal type>
        //   271: astore 7
        //   273: aload_3
        //   274: astore 12
        //   276: aload 5
        //   278: astore 11
        //   280: aload 4
        //   282: astore 13
        //   284: aload 8
        //   286: astore 10
        //   288: aload 6
        //   290: astore 9
        //   292: aload 6
        //   294: aload 7
        //   296: invokevirtual 159	java/io/InputStream:read	([B)I
        //   299: istore_1
        //   300: iload_1
        //   301: iconst_m1
        //   302: if_icmpeq +151 -> 453
        //   305: aload_3
        //   306: astore 12
        //   308: aload 5
        //   310: astore 11
        //   312: aload 4
        //   314: astore 13
        //   316: aload 8
        //   318: astore 10
        //   320: aload 6
        //   322: astore 9
        //   324: aload 8
        //   326: aload 7
        //   328: iconst_0
        //   329: iload_1
        //   330: invokevirtual 162	java/io/ByteArrayOutputStream:write	([BII)V
        //   333: goto -60 -> 273
        //   336: astore 7
        //   338: aload 5
        //   340: astore 9
        //   342: aload 6
        //   344: astore 7
        //   346: aload 8
        //   348: astore 5
        //   350: aload 4
        //   352: astore 6
        //   354: aload 9
        //   356: astore 4
        //   358: getstatic 164	com/baidu/location/h/a:a	Ljava/lang/String;
        //   361: ldc -90
        //   363: invokestatic 172	android/util/Log:d	(Ljava/lang/String;Ljava/lang/String;)I
        //   366: pop
        //   367: aload_3
        //   368: ifnull +7 -> 375
        //   371: aload_3
        //   372: invokevirtual 175	java/net/HttpURLConnection:disconnect	()V
        //   375: aload 4
        //   377: ifnull +8 -> 385
        //   380: aload 4
        //   382: invokevirtual 178	java/io/FileInputStream:close	()V
        //   385: aload 6
        //   387: ifnull +8 -> 395
        //   390: aload 6
        //   392: invokevirtual 179	java/io/OutputStream:close	()V
        //   395: aload 7
        //   397: ifnull +8 -> 405
        //   400: aload 7
        //   402: invokevirtual 180	java/io/InputStream:close	()V
        //   405: aload 5
        //   407: ifnull +8 -> 415
        //   410: aload 5
        //   412: invokevirtual 181	java/io/ByteArrayOutputStream:close	()V
        //   415: iconst_0
        //   416: istore_1
        //   417: aload_3
        //   418: astore 4
        //   420: iload_1
        //   421: ifeq +565 -> 986
        //   424: iload_2
        //   425: ifgt +568 -> 993
        //   428: getstatic 184	com/baidu/location/h/e:o	I
        //   431: iconst_1
        //   432: iadd
        //   433: putstatic 184	com/baidu/location/h/e:o	I
        //   436: aload_0
        //   437: getfield 15	com/baidu/location/h/e$3:a	Lcom/baidu/location/h/e;
        //   440: aconst_null
        //   441: putfield 186	com/baidu/location/h/e:j	Ljava/lang/String;
        //   444: aload_0
        //   445: getfield 15	com/baidu/location/h/e$3:a	Lcom/baidu/location/h/e;
        //   448: iconst_0
        //   449: invokevirtual 188	com/baidu/location/h/e:a	(Z)V
        //   452: return
        //   453: aload_3
        //   454: astore 12
        //   456: aload 5
        //   458: astore 11
        //   460: aload 4
        //   462: astore 13
        //   464: aload 8
        //   466: astore 10
        //   468: aload 6
        //   470: astore 9
        //   472: aload_0
        //   473: getfield 15	com/baidu/location/h/e$3:a	Lcom/baidu/location/h/e;
        //   476: new 141	java/lang/String
        //   479: dup
        //   480: aload 8
        //   482: invokevirtual 192	java/io/ByteArrayOutputStream:toByteArray	()[B
        //   485: ldc -62
        //   487: invokespecial 197	java/lang/String:<init>	([BLjava/lang/String;)V
        //   490: putfield 186	com/baidu/location/h/e:j	Ljava/lang/String;
        //   493: aload_3
        //   494: astore 12
        //   496: aload 5
        //   498: astore 11
        //   500: aload 4
        //   502: astore 13
        //   504: aload 8
        //   506: astore 10
        //   508: aload 6
        //   510: astore 9
        //   512: aload_0
        //   513: getfield 15	com/baidu/location/h/e$3:a	Lcom/baidu/location/h/e;
        //   516: iconst_1
        //   517: invokevirtual 188	com/baidu/location/h/e:a	(Z)V
        //   520: iconst_1
        //   521: istore_1
        //   522: aload 6
        //   524: astore 7
        //   526: aload 8
        //   528: astore 6
        //   530: aload_3
        //   531: ifnull +7 -> 538
        //   534: aload_3
        //   535: invokevirtual 175	java/net/HttpURLConnection:disconnect	()V
        //   538: aload 5
        //   540: ifnull +8 -> 548
        //   543: aload 5
        //   545: invokevirtual 178	java/io/FileInputStream:close	()V
        //   548: aload 4
        //   550: ifnull +8 -> 558
        //   553: aload 4
        //   555: invokevirtual 179	java/io/OutputStream:close	()V
        //   558: aload 7
        //   560: ifnull +8 -> 568
        //   563: aload 7
        //   565: invokevirtual 180	java/io/InputStream:close	()V
        //   568: aload 6
        //   570: ifnull +8 -> 578
        //   573: aload 6
        //   575: invokevirtual 181	java/io/ByteArrayOutputStream:close	()V
        //   578: aload_3
        //   579: astore 4
        //   581: goto -161 -> 420
        //   584: astore 5
        //   586: getstatic 164	com/baidu/location/h/a:a	Ljava/lang/String;
        //   589: ldc -57
        //   591: invokestatic 172	android/util/Log:d	(Ljava/lang/String;Ljava/lang/String;)I
        //   594: pop
        //   595: goto -47 -> 548
        //   598: astore 4
        //   600: getstatic 164	com/baidu/location/h/a:a	Ljava/lang/String;
        //   603: ldc -55
        //   605: invokestatic 172	android/util/Log:d	(Ljava/lang/String;Ljava/lang/String;)I
        //   608: pop
        //   609: goto -51 -> 558
        //   612: astore 4
        //   614: getstatic 164	com/baidu/location/h/a:a	Ljava/lang/String;
        //   617: ldc -53
        //   619: invokestatic 172	android/util/Log:d	(Ljava/lang/String;Ljava/lang/String;)I
        //   622: pop
        //   623: goto -55 -> 568
        //   626: astore 4
        //   628: getstatic 164	com/baidu/location/h/a:a	Ljava/lang/String;
        //   631: ldc -51
        //   633: invokestatic 172	android/util/Log:d	(Ljava/lang/String;Ljava/lang/String;)I
        //   636: pop
        //   637: aload_3
        //   638: astore 4
        //   640: goto -220 -> 420
        //   643: astore 4
        //   645: getstatic 164	com/baidu/location/h/a:a	Ljava/lang/String;
        //   648: ldc -57
        //   650: invokestatic 172	android/util/Log:d	(Ljava/lang/String;Ljava/lang/String;)I
        //   653: pop
        //   654: goto -269 -> 385
        //   657: astore 4
        //   659: getstatic 164	com/baidu/location/h/a:a	Ljava/lang/String;
        //   662: ldc -55
        //   664: invokestatic 172	android/util/Log:d	(Ljava/lang/String;Ljava/lang/String;)I
        //   667: pop
        //   668: goto -273 -> 395
        //   671: astore 4
        //   673: getstatic 164	com/baidu/location/h/a:a	Ljava/lang/String;
        //   676: ldc -53
        //   678: invokestatic 172	android/util/Log:d	(Ljava/lang/String;Ljava/lang/String;)I
        //   681: pop
        //   682: goto -277 -> 405
        //   685: astore 4
        //   687: getstatic 164	com/baidu/location/h/a:a	Ljava/lang/String;
        //   690: ldc -51
        //   692: invokestatic 172	android/util/Log:d	(Ljava/lang/String;Ljava/lang/String;)I
        //   695: pop
        //   696: iconst_0
        //   697: istore_1
        //   698: aload_3
        //   699: astore 4
        //   701: goto -281 -> 420
        //   704: astore 4
        //   706: aconst_null
        //   707: astore 7
        //   709: aconst_null
        //   710: astore 4
        //   712: aconst_null
        //   713: astore 6
        //   715: aload_3
        //   716: astore 12
        //   718: aload 5
        //   720: astore 11
        //   722: aload 7
        //   724: astore 13
        //   726: aload 4
        //   728: astore 10
        //   730: aload 6
        //   732: astore 9
        //   734: getstatic 164	com/baidu/location/h/a:a	Ljava/lang/String;
        //   737: ldc -49
        //   739: invokestatic 172	android/util/Log:d	(Ljava/lang/String;Ljava/lang/String;)I
        //   742: pop
        //   743: aload_3
        //   744: ifnull +7 -> 751
        //   747: aload_3
        //   748: invokevirtual 175	java/net/HttpURLConnection:disconnect	()V
        //   751: aload 5
        //   753: ifnull +8 -> 761
        //   756: aload 5
        //   758: invokevirtual 178	java/io/FileInputStream:close	()V
        //   761: aload 7
        //   763: ifnull +8 -> 771
        //   766: aload 7
        //   768: invokevirtual 179	java/io/OutputStream:close	()V
        //   771: aload 6
        //   773: ifnull +8 -> 781
        //   776: aload 6
        //   778: invokevirtual 180	java/io/InputStream:close	()V
        //   781: aload 4
        //   783: ifnull +8 -> 791
        //   786: aload 4
        //   788: invokevirtual 181	java/io/ByteArrayOutputStream:close	()V
        //   791: iconst_0
        //   792: istore_1
        //   793: aload_3
        //   794: astore 4
        //   796: goto -376 -> 420
        //   799: astore 5
        //   801: getstatic 164	com/baidu/location/h/a:a	Ljava/lang/String;
        //   804: ldc -57
        //   806: invokestatic 172	android/util/Log:d	(Ljava/lang/String;Ljava/lang/String;)I
        //   809: pop
        //   810: goto -49 -> 761
        //   813: astore 5
        //   815: getstatic 164	com/baidu/location/h/a:a	Ljava/lang/String;
        //   818: ldc -55
        //   820: invokestatic 172	android/util/Log:d	(Ljava/lang/String;Ljava/lang/String;)I
        //   823: pop
        //   824: goto -53 -> 771
        //   827: astore 5
        //   829: getstatic 164	com/baidu/location/h/a:a	Ljava/lang/String;
        //   832: ldc -53
        //   834: invokestatic 172	android/util/Log:d	(Ljava/lang/String;Ljava/lang/String;)I
        //   837: pop
        //   838: goto -57 -> 781
        //   841: astore 4
        //   843: getstatic 164	com/baidu/location/h/a:a	Ljava/lang/String;
        //   846: ldc -51
        //   848: invokestatic 172	android/util/Log:d	(Ljava/lang/String;Ljava/lang/String;)I
        //   851: pop
        //   852: iconst_0
        //   853: istore_1
        //   854: aload_3
        //   855: astore 4
        //   857: goto -437 -> 420
        //   860: astore 8
        //   862: aconst_null
        //   863: astore 4
        //   865: aconst_null
        //   866: astore 6
        //   868: aload_3
        //   869: astore 7
        //   871: aload 8
        //   873: astore_3
        //   874: aload 14
        //   876: astore 8
        //   878: aload 7
        //   880: ifnull +8 -> 888
        //   883: aload 7
        //   885: invokevirtual 175	java/net/HttpURLConnection:disconnect	()V
        //   888: aload 5
        //   890: ifnull +8 -> 898
        //   893: aload 5
        //   895: invokevirtual 178	java/io/FileInputStream:close	()V
        //   898: aload 8
        //   900: ifnull +8 -> 908
        //   903: aload 8
        //   905: invokevirtual 179	java/io/OutputStream:close	()V
        //   908: aload 6
        //   910: ifnull +8 -> 918
        //   913: aload 6
        //   915: invokevirtual 180	java/io/InputStream:close	()V
        //   918: aload 4
        //   920: ifnull +8 -> 928
        //   923: aload 4
        //   925: invokevirtual 181	java/io/ByteArrayOutputStream:close	()V
        //   928: aload_3
        //   929: athrow
        //   930: astore 5
        //   932: getstatic 164	com/baidu/location/h/a:a	Ljava/lang/String;
        //   935: ldc -57
        //   937: invokestatic 172	android/util/Log:d	(Ljava/lang/String;Ljava/lang/String;)I
        //   940: pop
        //   941: goto -43 -> 898
        //   944: astore 5
        //   946: getstatic 164	com/baidu/location/h/a:a	Ljava/lang/String;
        //   949: ldc -55
        //   951: invokestatic 172	android/util/Log:d	(Ljava/lang/String;Ljava/lang/String;)I
        //   954: pop
        //   955: goto -47 -> 908
        //   958: astore 5
        //   960: getstatic 164	com/baidu/location/h/a:a	Ljava/lang/String;
        //   963: ldc -53
        //   965: invokestatic 172	android/util/Log:d	(Ljava/lang/String;Ljava/lang/String;)I
        //   968: pop
        //   969: goto -51 -> 918
        //   972: astore 4
        //   974: getstatic 164	com/baidu/location/h/a:a	Ljava/lang/String;
        //   977: ldc -51
        //   979: invokestatic 172	android/util/Log:d	(Ljava/lang/String;Ljava/lang/String;)I
        //   982: pop
        //   983: goto -55 -> 928
        //   986: iload_2
        //   987: iconst_1
        //   988: isub
        //   989: istore_2
        //   990: goto -952 -> 38
        //   993: iconst_0
        //   994: putstatic 184	com/baidu/location/h/e:o	I
        //   997: return
        //   998: astore 8
        //   1000: aconst_null
        //   1001: astore 6
        //   1003: aload_3
        //   1004: astore 7
        //   1006: aload 8
        //   1008: astore_3
        //   1009: aconst_null
        //   1010: astore 9
        //   1012: aload 4
        //   1014: astore 8
        //   1016: aload 9
        //   1018: astore 4
        //   1020: goto -142 -> 878
        //   1023: astore 8
        //   1025: aload 7
        //   1027: astore 6
        //   1029: aconst_null
        //   1030: astore 9
        //   1032: aload_3
        //   1033: astore 7
        //   1035: aload 8
        //   1037: astore_3
        //   1038: aload 4
        //   1040: astore 8
        //   1042: aload 9
        //   1044: astore 4
        //   1046: goto -168 -> 878
        //   1049: astore 8
        //   1051: aconst_null
        //   1052: astore 9
        //   1054: aload_3
        //   1055: astore 7
        //   1057: aload 8
        //   1059: astore_3
        //   1060: aload 4
        //   1062: astore 8
        //   1064: aload 9
        //   1066: astore 4
        //   1068: goto -190 -> 878
        //   1071: astore_3
        //   1072: aload 13
        //   1074: astore 8
        //   1076: aload 12
        //   1078: astore 7
        //   1080: aload 11
        //   1082: astore 5
        //   1084: aload 10
        //   1086: astore 4
        //   1088: aload 9
        //   1090: astore 6
        //   1092: goto -214 -> 878
        //   1095: astore 8
        //   1097: aload_3
        //   1098: astore 10
        //   1100: aload 7
        //   1102: astore 9
        //   1104: aload 5
        //   1106: astore 11
        //   1108: aload 8
        //   1110: astore_3
        //   1111: aload 4
        //   1113: astore 5
        //   1115: aload 6
        //   1117: astore 8
        //   1119: aload 10
        //   1121: astore 7
        //   1123: aload 11
        //   1125: astore 4
        //   1127: aload 9
        //   1129: astore 6
        //   1131: goto -253 -> 878
        //   1134: astore_3
        //   1135: aconst_null
        //   1136: astore 5
        //   1138: aconst_null
        //   1139: astore 9
        //   1141: aconst_null
        //   1142: astore 6
        //   1144: aload 14
        //   1146: astore 8
        //   1148: aload 4
        //   1150: astore 7
        //   1152: aload 9
        //   1154: astore 4
        //   1156: goto -278 -> 878
        //   1159: astore_3
        //   1160: aconst_null
        //   1161: astore 9
        //   1163: aconst_null
        //   1164: astore 6
        //   1166: aload 14
        //   1168: astore 8
        //   1170: aload 4
        //   1172: astore 7
        //   1174: aload 9
        //   1176: astore 4
        //   1178: goto -300 -> 878
        //   1181: astore 6
        //   1183: aconst_null
        //   1184: astore 8
        //   1186: aconst_null
        //   1187: astore 6
        //   1189: aload 4
        //   1191: astore 7
        //   1193: aload 8
        //   1195: astore 4
        //   1197: goto -482 -> 715
        //   1200: astore 6
        //   1202: aload 7
        //   1204: astore 6
        //   1206: aconst_null
        //   1207: astore 8
        //   1209: aload 4
        //   1211: astore 7
        //   1213: aload 8
        //   1215: astore 4
        //   1217: goto -502 -> 715
        //   1220: astore 7
        //   1222: aconst_null
        //   1223: astore 8
        //   1225: aload 4
        //   1227: astore 7
        //   1229: aload 8
        //   1231: astore 4
        //   1233: goto -518 -> 715
        //   1236: astore 7
        //   1238: aload 4
        //   1240: astore 7
        //   1242: aload 8
        //   1244: astore 4
        //   1246: goto -531 -> 715
        //   1249: astore_3
        //   1250: aconst_null
        //   1251: astore 5
        //   1253: aconst_null
        //   1254: astore 8
        //   1256: aconst_null
        //   1257: astore 6
        //   1259: aload 4
        //   1261: astore_3
        //   1262: aconst_null
        //   1263: astore 7
        //   1265: aload 8
        //   1267: astore 4
        //   1269: goto -554 -> 715
        //   1272: astore_3
        //   1273: aconst_null
        //   1274: astore 8
        //   1276: aconst_null
        //   1277: astore 6
        //   1279: aload 4
        //   1281: astore_3
        //   1282: aconst_null
        //   1283: astore 7
        //   1285: aload 8
        //   1287: astore 4
        //   1289: goto -574 -> 715
        //   1292: astore 4
        //   1294: aconst_null
        //   1295: astore 8
        //   1297: aconst_null
        //   1298: astore 7
        //   1300: aload 5
        //   1302: astore 4
        //   1304: aconst_null
        //   1305: astore 6
        //   1307: aload 8
        //   1309: astore 5
        //   1311: goto -953 -> 358
        //   1314: astore 6
        //   1316: aconst_null
        //   1317: astore 7
        //   1319: aload 4
        //   1321: astore 6
        //   1323: aconst_null
        //   1324: astore 8
        //   1326: aload 5
        //   1328: astore 4
        //   1330: aload 8
        //   1332: astore 5
        //   1334: goto -976 -> 358
        //   1337: astore 6
        //   1339: aload 4
        //   1341: astore 6
        //   1343: aconst_null
        //   1344: astore 8
        //   1346: aload 5
        //   1348: astore 4
        //   1350: aload 8
        //   1352: astore 5
        //   1354: goto -996 -> 358
        //   1357: astore 7
        //   1359: aload 6
        //   1361: astore 7
        //   1363: aload 4
        //   1365: astore 6
        //   1367: aconst_null
        //   1368: astore 8
        //   1370: aload 5
        //   1372: astore 4
        //   1374: aload 8
        //   1376: astore 5
        //   1378: goto -1020 -> 358
        //   1381: astore_3
        //   1382: aconst_null
        //   1383: astore 8
        //   1385: aconst_null
        //   1386: astore 6
        //   1388: aconst_null
        //   1389: astore 7
        //   1391: aload 4
        //   1393: astore_3
        //   1394: aconst_null
        //   1395: astore 5
        //   1397: aload 8
        //   1399: astore 4
        //   1401: goto -1043 -> 358
        //   1404: astore_3
        //   1405: aconst_null
        //   1406: astore 7
        //   1408: aload 4
        //   1410: astore_3
        //   1411: aconst_null
        //   1412: astore 6
        //   1414: aconst_null
        //   1415: astore 8
        //   1417: aload 5
        //   1419: astore 4
        //   1421: aload 8
        //   1423: astore 5
        //   1425: goto -1067 -> 358
        //   1428: aload 7
        //   1430: astore 6
        //   1432: goto -1194 -> 238
        //   1435: iconst_0
        //   1436: istore_1
        //   1437: aconst_null
        //   1438: astore 6
        //   1440: aconst_null
        //   1441: astore 7
        //   1443: goto -913 -> 530
        // Local variable table:
        //   start	length	slot	name	signature
        //   0	1446	0	this	3
        //   299	1138	1	i	int
        //   34	956	2	j	int
        //   56	1004	3	localObject1	Object
        //   1071	27	3	localObject2	Object
        //   1110	1	3	localObject3	Object
        //   1134	1	3	localObject4	Object
        //   1159	1	3	localObject5	Object
        //   1249	1	3	localError1	Error
        //   1261	1	3	localObject6	Object
        //   1272	1	3	localError2	Error
        //   1281	1	3	localObject7	Object
        //   1381	1	3	localException1	Exception
        //   1393	1	3	localObject8	Object
        //   1404	1	3	localException2	Exception
        //   1410	1	3	localObject9	Object
        //   36	544	4	localObject10	Object
        //   598	1	4	localException3	Exception
        //   612	1	4	localException4	Exception
        //   626	1	4	localException5	Exception
        //   638	1	4	localObject11	Object
        //   643	1	4	localException6	Exception
        //   657	1	4	localException7	Exception
        //   671	1	4	localException8	Exception
        //   685	1	4	localException9	Exception
        //   699	1	4	localObject12	Object
        //   704	1	4	localError3	Error
        //   710	85	4	localObject13	Object
        //   841	1	4	localException10	Exception
        //   855	69	4	localObject14	Object
        //   972	41	4	localException11	Exception
        //   1018	270	4	localObject15	Object
        //   1292	1	4	localException12	Exception
        //   1302	118	4	localObject16	Object
        //   71	473	5	localObject17	Object
        //   584	173	5	localException13	Exception
        //   799	1	5	localException14	Exception
        //   813	1	5	localException15	Exception
        //   827	67	5	localException16	Exception
        //   930	1	5	localException17	Exception
        //   944	1	5	localException18	Exception
        //   958	1	5	localException19	Exception
        //   1082	342	5	localObject18	Object
        //   80	1085	6	localObject19	Object
        //   1181	1	6	localError4	Error
        //   1187	1	6	localObject20	Object
        //   1200	1	6	localError5	Error
        //   1204	102	6	localObject21	Object
        //   1314	1	6	localException20	Exception
        //   1321	1	6	localObject22	Object
        //   1337	1	6	localException21	Exception
        //   1341	98	6	localObject23	Object
        //   197	130	7	localObject24	Object
        //   336	1	7	localException22	Exception
        //   344	868	7	localObject25	Object
        //   1220	1	7	localError6	Error
        //   1227	1	7	localObject26	Object
        //   1236	1	7	localError7	Error
        //   1240	78	7	localObject27	Object
        //   1357	1	7	localException23	Exception
        //   1361	81	7	localObject28	Object
        //   245	282	8	localByteArrayOutputStream	java.io.ByteArrayOutputStream
        //   860	12	8	localObject29	Object
        //   876	28	8	localObject30	Object
        //   998	9	8	localObject31	Object
        //   1014	1	8	localException24	Exception
        //   1023	13	8	localObject32	Object
        //   1040	1	8	localObject33	Object
        //   1049	9	8	localObject34	Object
        //   1062	13	8	localObject35	Object
        //   1095	14	8	localObject36	Object
        //   1117	305	8	localObject37	Object
        //   264	911	9	localObject38	Object
        //   260	860	10	localObject39	Object
        //   252	872	11	localObject40	Object
        //   248	829	12	localObject41	Object
        //   256	817	13	localObject42	Object
        //   1	1166	14	localObject43	Object
        // Exception table:
        //   from	to	target	type
        //   266	273	336	java/lang/Exception
        //   292	300	336	java/lang/Exception
        //   324	333	336	java/lang/Exception
        //   472	493	336	java/lang/Exception
        //   512	520	336	java/lang/Exception
        //   543	548	584	java/lang/Exception
        //   553	558	598	java/lang/Exception
        //   563	568	612	java/lang/Exception
        //   573	578	626	java/lang/Exception
        //   380	385	643	java/lang/Exception
        //   390	395	657	java/lang/Exception
        //   400	405	671	java/lang/Exception
        //   410	415	685	java/lang/Exception
        //   98	171	704	java/lang/Error
        //   756	761	799	java/lang/Exception
        //   766	771	813	java/lang/Exception
        //   776	781	827	java/lang/Exception
        //   786	791	841	java/lang/Exception
        //   98	171	860	finally
        //   893	898	930	java/lang/Exception
        //   903	908	944	java/lang/Exception
        //   913	918	958	java/lang/Exception
        //   923	928	972	java/lang/Exception
        //   171	199	998	finally
        //   199	205	1023	finally
        //   210	238	1023	finally
        //   238	247	1049	finally
        //   266	273	1071	finally
        //   292	300	1071	finally
        //   324	333	1071	finally
        //   472	493	1071	finally
        //   512	520	1071	finally
        //   734	743	1071	finally
        //   358	367	1095	finally
        //   42	73	1134	finally
        //   73	98	1159	finally
        //   171	199	1181	java/lang/Error
        //   199	205	1200	java/lang/Error
        //   210	238	1200	java/lang/Error
        //   238	247	1220	java/lang/Error
        //   266	273	1236	java/lang/Error
        //   292	300	1236	java/lang/Error
        //   324	333	1236	java/lang/Error
        //   472	493	1236	java/lang/Error
        //   512	520	1236	java/lang/Error
        //   42	73	1249	java/lang/Error
        //   73	98	1272	java/lang/Error
        //   98	171	1292	java/lang/Exception
        //   171	199	1314	java/lang/Exception
        //   199	205	1337	java/lang/Exception
        //   210	238	1337	java/lang/Exception
        //   238	247	1357	java/lang/Exception
        //   42	73	1381	java/lang/Exception
        //   73	98	1404	java/lang/Exception
      }
    }.start();
  }
}


/* Location:              /Users/objectyan/Documents/OY/baiduCarLife_40/dist/classes2-dex2jar.jar!/com/baidu/location/h/e.class
 * Java compiler version: 6 (50.0)
 * JD-Core Version:       0.7.1
 */