package com.indooratlas.android.sdk._internal;

import java.io.IOException;

public final class by
  implements cb
{
  private cj a;
  
  public by(cj paramcj)
  {
    this.a = paramcj;
  }
  
  /* Error */
  public final void a(bz... paramVarArgs)
    throws IOException
  {
    // Byte code:
    //   0: iconst_0
    //   1: istore_3
    //   2: iconst_0
    //   3: istore 4
    //   5: iconst_0
    //   6: istore 5
    //   8: aload_0
    //   9: getfield 15	com/indooratlas/android/sdk/_internal/by:a	Lcom/indooratlas/android/sdk/_internal/cj;
    //   12: astore 7
    //   14: aload 7
    //   16: invokevirtual 32	com/indooratlas/android/sdk/_internal/cj:a	()Landroid/database/sqlite/SQLiteDatabase;
    //   19: astore 6
    //   21: aload 6
    //   23: ifnull +147 -> 170
    //   26: aload 6
    //   28: invokevirtual 37	android/database/sqlite/SQLiteDatabase:beginTransaction	()V
    //   31: aload 6
    //   33: ldc 39
    //   35: invokevirtual 43	android/database/sqlite/SQLiteDatabase:compileStatement	(Ljava/lang/String;)Landroid/database/sqlite/SQLiteStatement;
    //   38: astore 8
    //   40: iconst_0
    //   41: istore_2
    //   42: iload_2
    //   43: ifgt +43 -> 86
    //   46: aload_1
    //   47: iconst_0
    //   48: aaload
    //   49: astore 9
    //   51: aload 8
    //   53: iconst_1
    //   54: aload 9
    //   56: getfield 48	com/indooratlas/android/sdk/_internal/bz:a	I
    //   59: i2l
    //   60: invokevirtual 54	android/database/sqlite/SQLiteStatement:bindLong	(IJ)V
    //   63: aload 8
    //   65: iconst_2
    //   66: aload 9
    //   68: invokevirtual 57	com/indooratlas/android/sdk/_internal/bz:a	()Ljava/lang/String;
    //   71: invokevirtual 61	android/database/sqlite/SQLiteStatement:bindString	(ILjava/lang/String;)V
    //   74: aload 8
    //   76: invokevirtual 64	android/database/sqlite/SQLiteStatement:execute	()V
    //   79: iload_2
    //   80: iconst_1
    //   81: iadd
    //   82: istore_2
    //   83: goto -41 -> 42
    //   86: aload 6
    //   88: invokevirtual 67	android/database/sqlite/SQLiteDatabase:setTransactionSuccessful	()V
    //   91: aload_1
    //   92: invokestatic 73	java/util/Arrays:toString	([Ljava/lang/Object;)Ljava/lang/String;
    //   95: pop
    //   96: aload 6
    //   98: invokestatic 76	com/indooratlas/android/sdk/_internal/cj:a	(Landroid/database/sqlite/SQLiteDatabase;)V
    //   101: aload 7
    //   103: invokevirtual 32	com/indooratlas/android/sdk/_internal/cj:a	()Landroid/database/sqlite/SQLiteDatabase;
    //   106: astore_1
    //   107: aload_1
    //   108: ifnull +62 -> 170
    //   111: iload 5
    //   113: istore_2
    //   114: aload_1
    //   115: ldc 78
    //   117: invokestatic 84	android/database/DatabaseUtils:queryNumEntries	(Landroid/database/sqlite/SQLiteDatabase;Ljava/lang/String;)J
    //   120: ldc2_w 85
    //   123: lcmp
    //   124: ifle +5 -> 129
    //   127: iconst_1
    //   128: istore_2
    //   129: iload_2
    //   130: ifeq +32 -> 162
    //   133: iload_2
    //   134: istore_3
    //   135: iload_2
    //   136: istore 4
    //   138: aload_1
    //   139: invokevirtual 37	android/database/sqlite/SQLiteDatabase:beginTransaction	()V
    //   142: iload_2
    //   143: istore_3
    //   144: iload_2
    //   145: istore 4
    //   147: aload_1
    //   148: ldc 88
    //   150: invokevirtual 92	android/database/sqlite/SQLiteDatabase:execSQL	(Ljava/lang/String;)V
    //   153: iload_2
    //   154: istore_3
    //   155: iload_2
    //   156: istore 4
    //   158: aload_1
    //   159: invokevirtual 67	android/database/sqlite/SQLiteDatabase:setTransactionSuccessful	()V
    //   162: iload_2
    //   163: ifeq +7 -> 170
    //   166: aload_1
    //   167: invokestatic 76	com/indooratlas/android/sdk/_internal/cj:a	(Landroid/database/sqlite/SQLiteDatabase;)V
    //   170: return
    //   171: astore_1
    //   172: ldc 94
    //   174: new 96	java/lang/StringBuilder
    //   177: dup
    //   178: ldc 98
    //   180: invokespecial 100	java/lang/StringBuilder:<init>	(Ljava/lang/String;)V
    //   183: aload_1
    //   184: invokevirtual 102	android/database/sqlite/SQLiteFullException:toString	()Ljava/lang/String;
    //   187: invokevirtual 106	java/lang/StringBuilder:append	(Ljava/lang/String;)Ljava/lang/StringBuilder;
    //   190: invokevirtual 107	java/lang/StringBuilder:toString	()Ljava/lang/String;
    //   193: iconst_0
    //   194: anewarray 4	java/lang/Object
    //   197: invokestatic 112	com/indooratlas/android/sdk/_internal/ee:a	(Ljava/lang/String;Ljava/lang/String;[Ljava/lang/Object;)V
    //   200: aload 7
    //   202: invokevirtual 115	com/indooratlas/android/sdk/_internal/cj:c	()V
    //   205: aload 6
    //   207: invokestatic 76	com/indooratlas/android/sdk/_internal/cj:a	(Landroid/database/sqlite/SQLiteDatabase;)V
    //   210: goto -109 -> 101
    //   213: astore_1
    //   214: new 19	java/io/IOException
    //   217: dup
    //   218: aload_1
    //   219: invokespecial 118	java/io/IOException:<init>	(Ljava/lang/Throwable;)V
    //   222: athrow
    //   223: astore_1
    //   224: ldc 94
    //   226: new 96	java/lang/StringBuilder
    //   229: dup
    //   230: ldc 120
    //   232: invokespecial 100	java/lang/StringBuilder:<init>	(Ljava/lang/String;)V
    //   235: aload_1
    //   236: invokevirtual 121	android/database/sqlite/SQLiteException:toString	()Ljava/lang/String;
    //   239: invokevirtual 106	java/lang/StringBuilder:append	(Ljava/lang/String;)Ljava/lang/StringBuilder;
    //   242: invokevirtual 107	java/lang/StringBuilder:toString	()Ljava/lang/String;
    //   245: iconst_0
    //   246: anewarray 4	java/lang/Object
    //   249: invokestatic 112	com/indooratlas/android/sdk/_internal/ee:a	(Ljava/lang/String;Ljava/lang/String;[Ljava/lang/Object;)V
    //   252: aload 6
    //   254: invokestatic 76	com/indooratlas/android/sdk/_internal/cj:a	(Landroid/database/sqlite/SQLiteDatabase;)V
    //   257: goto -156 -> 101
    //   260: astore_1
    //   261: aload 6
    //   263: invokestatic 76	com/indooratlas/android/sdk/_internal/cj:a	(Landroid/database/sqlite/SQLiteDatabase;)V
    //   266: aload_1
    //   267: athrow
    //   268: astore 6
    //   270: iload_3
    //   271: istore 4
    //   273: ldc 94
    //   275: new 96	java/lang/StringBuilder
    //   278: dup
    //   279: ldc 123
    //   281: invokespecial 100	java/lang/StringBuilder:<init>	(Ljava/lang/String;)V
    //   284: aload 6
    //   286: invokevirtual 121	android/database/sqlite/SQLiteException:toString	()Ljava/lang/String;
    //   289: invokevirtual 106	java/lang/StringBuilder:append	(Ljava/lang/String;)Ljava/lang/StringBuilder;
    //   292: invokevirtual 107	java/lang/StringBuilder:toString	()Ljava/lang/String;
    //   295: iconst_0
    //   296: anewarray 4	java/lang/Object
    //   299: invokestatic 112	com/indooratlas/android/sdk/_internal/ee:a	(Ljava/lang/String;Ljava/lang/String;[Ljava/lang/Object;)V
    //   302: iload_3
    //   303: ifeq -133 -> 170
    //   306: aload_1
    //   307: invokestatic 76	com/indooratlas/android/sdk/_internal/cj:a	(Landroid/database/sqlite/SQLiteDatabase;)V
    //   310: return
    //   311: astore 6
    //   313: iload 4
    //   315: ifeq +7 -> 322
    //   318: aload_1
    //   319: invokestatic 76	com/indooratlas/android/sdk/_internal/cj:a	(Landroid/database/sqlite/SQLiteDatabase;)V
    //   322: aload 6
    //   324: athrow
    //   325: astore_1
    //   326: return
    // Local variable table:
    //   start	length	slot	name	signature
    //   0	327	0	this	by
    //   0	327	1	paramVarArgs	bz[]
    //   41	122	2	i	int
    //   1	302	3	j	int
    //   3	311	4	k	int
    //   6	106	5	m	int
    //   19	243	6	localSQLiteDatabase	android.database.sqlite.SQLiteDatabase
    //   268	17	6	localSQLiteException	android.database.sqlite.SQLiteException
    //   311	12	6	localObject	Object
    //   12	189	7	localcj	cj
    //   38	37	8	localSQLiteStatement	android.database.sqlite.SQLiteStatement
    //   49	18	9	localbz	bz
    // Exception table:
    //   from	to	target	type
    //   26	40	171	android/database/sqlite/SQLiteFullException
    //   51	79	171	android/database/sqlite/SQLiteFullException
    //   86	96	171	android/database/sqlite/SQLiteFullException
    //   8	21	213	org/json/JSONException
    //   96	101	213	org/json/JSONException
    //   101	107	213	org/json/JSONException
    //   166	170	213	org/json/JSONException
    //   205	210	213	org/json/JSONException
    //   252	257	213	org/json/JSONException
    //   261	268	213	org/json/JSONException
    //   306	310	213	org/json/JSONException
    //   318	322	213	org/json/JSONException
    //   322	325	213	org/json/JSONException
    //   26	40	223	android/database/sqlite/SQLiteException
    //   51	79	223	android/database/sqlite/SQLiteException
    //   86	96	223	android/database/sqlite/SQLiteException
    //   26	40	260	finally
    //   51	79	260	finally
    //   86	96	260	finally
    //   172	205	260	finally
    //   224	252	260	finally
    //   114	127	268	android/database/sqlite/SQLiteException
    //   138	142	268	android/database/sqlite/SQLiteException
    //   147	153	268	android/database/sqlite/SQLiteException
    //   158	162	268	android/database/sqlite/SQLiteException
    //   114	127	311	finally
    //   138	142	311	finally
    //   147	153	311	finally
    //   158	162	311	finally
    //   273	302	311	finally
    //   8	21	325	java/lang/IllegalStateException
    //   96	101	325	java/lang/IllegalStateException
    //   101	107	325	java/lang/IllegalStateException
    //   166	170	325	java/lang/IllegalStateException
    //   205	210	325	java/lang/IllegalStateException
    //   252	257	325	java/lang/IllegalStateException
    //   261	268	325	java/lang/IllegalStateException
    //   306	310	325	java/lang/IllegalStateException
    //   318	322	325	java/lang/IllegalStateException
    //   322	325	325	java/lang/IllegalStateException
  }
  
  public final void close()
    throws IOException
  {}
}


/* Location:              /Users/objectyan/Documents/OY/baiduCarLife_40/dist/classes2-dex2jar.jar!/com/indooratlas/android/sdk/_internal/by.class
 * Java compiler version: 6 (50.0)
 * JD-Core Version:       0.7.1
 */