package com.baidu.android.pushservice.k;

public class c
{
  /* Error */
  public static java.util.ArrayList<String> a(String paramString, java.io.File paramFile)
  {
    // Byte code:
    //   0: aconst_null
    //   1: astore 4
    //   3: new 12	java/util/ArrayList
    //   6: dup
    //   7: invokespecial 16	java/util/ArrayList:<init>	()V
    //   10: astore 5
    //   12: invokestatic 22	java/lang/Runtime:getRuntime	()Ljava/lang/Runtime;
    //   15: aload_0
    //   16: invokevirtual 26	java/lang/Runtime:exec	(Ljava/lang/String;)Ljava/lang/Process;
    //   19: astore 6
    //   21: new 28	java/io/InputStreamReader
    //   24: dup
    //   25: aload 6
    //   27: invokevirtual 34	java/lang/Process:getInputStream	()Ljava/io/InputStream;
    //   30: ldc 36
    //   32: invokespecial 39	java/io/InputStreamReader:<init>	(Ljava/io/InputStream;Ljava/lang/String;)V
    //   35: astore_3
    //   36: aload_3
    //   37: astore_2
    //   38: new 41	java/io/LineNumberReader
    //   41: dup
    //   42: aload_3
    //   43: invokespecial 44	java/io/LineNumberReader:<init>	(Ljava/io/Reader;)V
    //   46: astore 7
    //   48: aload_1
    //   49: ifnull +64 -> 113
    //   52: aload_3
    //   53: astore_2
    //   54: aload_1
    //   55: invokevirtual 50	java/io/File:exists	()Z
    //   58: ifne +10 -> 68
    //   61: aload_3
    //   62: astore_2
    //   63: aload_1
    //   64: invokevirtual 53	java/io/File:createNewFile	()Z
    //   67: pop
    //   68: aload_3
    //   69: astore_2
    //   70: new 55	java/io/FileWriter
    //   73: dup
    //   74: aload_1
    //   75: iconst_1
    //   76: invokespecial 58	java/io/FileWriter:<init>	(Ljava/io/File;Z)V
    //   79: astore 4
    //   81: aload_3
    //   82: astore_2
    //   83: aload 4
    //   85: new 60	java/lang/StringBuilder
    //   88: dup
    //   89: invokespecial 61	java/lang/StringBuilder:<init>	()V
    //   92: ldc 63
    //   94: invokevirtual 67	java/lang/StringBuilder:append	(Ljava/lang/String;)Ljava/lang/StringBuilder;
    //   97: aload_0
    //   98: invokevirtual 67	java/lang/StringBuilder:append	(Ljava/lang/String;)Ljava/lang/StringBuilder;
    //   101: ldc 69
    //   103: invokevirtual 67	java/lang/StringBuilder:append	(Ljava/lang/String;)Ljava/lang/StringBuilder;
    //   106: invokevirtual 73	java/lang/StringBuilder:toString	()Ljava/lang/String;
    //   109: invokevirtual 76	java/io/FileWriter:append	(Ljava/lang/CharSequence;)Ljava/io/Writer;
    //   112: pop
    //   113: aload_3
    //   114: astore_2
    //   115: aload 7
    //   117: invokevirtual 81	java/io/BufferedReader:readLine	()Ljava/lang/String;
    //   120: astore_0
    //   121: aload_0
    //   122: ifnull +77 -> 199
    //   125: aload_3
    //   126: astore_2
    //   127: aload 5
    //   129: aload_0
    //   130: invokevirtual 85	java/util/ArrayList:add	(Ljava/lang/Object;)Z
    //   133: pop
    //   134: aload 4
    //   136: ifnull -23 -> 113
    //   139: aload_3
    //   140: astore_2
    //   141: aload 4
    //   143: new 60	java/lang/StringBuilder
    //   146: dup
    //   147: invokespecial 61	java/lang/StringBuilder:<init>	()V
    //   150: aload_0
    //   151: invokevirtual 67	java/lang/StringBuilder:append	(Ljava/lang/String;)Ljava/lang/StringBuilder;
    //   154: ldc 87
    //   156: invokevirtual 67	java/lang/StringBuilder:append	(Ljava/lang/String;)Ljava/lang/StringBuilder;
    //   159: invokevirtual 73	java/lang/StringBuilder:toString	()Ljava/lang/String;
    //   162: invokevirtual 76	java/io/FileWriter:append	(Ljava/lang/CharSequence;)Ljava/io/Writer;
    //   165: pop
    //   166: goto -53 -> 113
    //   169: astore_1
    //   170: aload_3
    //   171: astore_0
    //   172: aload_0
    //   173: astore_2
    //   174: aload_1
    //   175: invokevirtual 90	java/lang/Exception:printStackTrace	()V
    //   178: aload_0
    //   179: astore_2
    //   180: aload 5
    //   182: ldc 92
    //   184: invokevirtual 85	java/util/ArrayList:add	(Ljava/lang/Object;)Z
    //   187: pop
    //   188: aload_0
    //   189: ifnull +7 -> 196
    //   192: aload_0
    //   193: invokevirtual 97	java/io/Reader:close	()V
    //   196: aload 5
    //   198: areturn
    //   199: aload 4
    //   201: ifnull +17 -> 218
    //   204: aload_3
    //   205: astore_2
    //   206: aload 4
    //   208: invokevirtual 100	java/io/FileWriter:flush	()V
    //   211: aload_3
    //   212: astore_2
    //   213: aload 4
    //   215: invokevirtual 101	java/io/FileWriter:close	()V
    //   218: aload_3
    //   219: astore_2
    //   220: aload 6
    //   222: invokevirtual 105	java/lang/Process:waitFor	()I
    //   225: pop
    //   226: aload_3
    //   227: ifnull -31 -> 196
    //   230: aload_3
    //   231: invokevirtual 97	java/io/Reader:close	()V
    //   234: aload 5
    //   236: areturn
    //   237: astore_0
    //   238: aload_0
    //   239: invokevirtual 106	java/io/IOException:printStackTrace	()V
    //   242: aload 5
    //   244: areturn
    //   245: astore_0
    //   246: aload_0
    //   247: invokevirtual 106	java/io/IOException:printStackTrace	()V
    //   250: aload 5
    //   252: areturn
    //   253: astore_0
    //   254: aconst_null
    //   255: astore_2
    //   256: aload_2
    //   257: ifnull +7 -> 264
    //   260: aload_2
    //   261: invokevirtual 97	java/io/Reader:close	()V
    //   264: aload_0
    //   265: athrow
    //   266: astore_1
    //   267: aload_1
    //   268: invokevirtual 106	java/io/IOException:printStackTrace	()V
    //   271: goto -7 -> 264
    //   274: astore_0
    //   275: goto -19 -> 256
    //   278: astore_1
    //   279: aconst_null
    //   280: astore_0
    //   281: goto -109 -> 172
    // Local variable table:
    //   start	length	slot	name	signature
    //   0	284	0	paramString	String
    //   0	284	1	paramFile	java.io.File
    //   37	224	2	localObject	Object
    //   35	196	3	localInputStreamReader	java.io.InputStreamReader
    //   1	213	4	localFileWriter	java.io.FileWriter
    //   10	241	5	localArrayList	java.util.ArrayList
    //   19	202	6	localProcess	Process
    //   46	70	7	localLineNumberReader	java.io.LineNumberReader
    // Exception table:
    //   from	to	target	type
    //   38	48	169	java/lang/Exception
    //   54	61	169	java/lang/Exception
    //   63	68	169	java/lang/Exception
    //   70	81	169	java/lang/Exception
    //   83	113	169	java/lang/Exception
    //   115	121	169	java/lang/Exception
    //   127	134	169	java/lang/Exception
    //   141	166	169	java/lang/Exception
    //   206	211	169	java/lang/Exception
    //   213	218	169	java/lang/Exception
    //   220	226	169	java/lang/Exception
    //   230	234	237	java/io/IOException
    //   192	196	245	java/io/IOException
    //   12	36	253	finally
    //   260	264	266	java/io/IOException
    //   38	48	274	finally
    //   54	61	274	finally
    //   63	68	274	finally
    //   70	81	274	finally
    //   83	113	274	finally
    //   115	121	274	finally
    //   127	134	274	finally
    //   141	166	274	finally
    //   174	178	274	finally
    //   180	188	274	finally
    //   206	211	274	finally
    //   213	218	274	finally
    //   220	226	274	finally
    //   12	36	278	java/lang/Exception
  }
}


/* Location:              /Users/objectyan/Documents/OY/baiduCarLife_40/dist/classes-dex2jar.jar!/com/baidu/android/pushservice/k/c.class
 * Java compiler version: 6 (50.0)
 * JD-Core Version:       0.7.1
 */