package com.baidu.android.pushservice.d;

public class d
{
  /* Error */
  public static String a(android.content.Context paramContext, String paramString)
  {
    // Byte code:
    //   0: aconst_null
    //   1: astore 4
    //   3: aconst_null
    //   4: astore_3
    //   5: aload_0
    //   6: aload_1
    //   7: invokestatic 16	com/baidu/android/pushservice/j/p:m	(Landroid/content/Context;Ljava/lang/String;)I
    //   10: bipush 52
    //   12: if_icmplt +216 -> 228
    //   15: aload_0
    //   16: invokevirtual 22	android/content/Context:getContentResolver	()Landroid/content/ContentResolver;
    //   19: astore 5
    //   21: aload 5
    //   23: ifnull +205 -> 228
    //   26: aload_0
    //   27: aload_1
    //   28: invokestatic 26	com/baidu/android/pushservice/j/p:z	(Landroid/content/Context;Ljava/lang/String;)Z
    //   31: ifeq +125 -> 156
    //   34: ldc 28
    //   36: astore_2
    //   37: aload 5
    //   39: new 30	java/lang/StringBuilder
    //   42: dup
    //   43: invokespecial 34	java/lang/StringBuilder:<init>	()V
    //   46: ldc 36
    //   48: invokevirtual 40	java/lang/StringBuilder:append	(Ljava/lang/String;)Ljava/lang/StringBuilder;
    //   51: aload_1
    //   52: invokevirtual 40	java/lang/StringBuilder:append	(Ljava/lang/String;)Ljava/lang/StringBuilder;
    //   55: ldc 42
    //   57: invokevirtual 40	java/lang/StringBuilder:append	(Ljava/lang/String;)Ljava/lang/StringBuilder;
    //   60: ldc 44
    //   62: invokevirtual 40	java/lang/StringBuilder:append	(Ljava/lang/String;)Ljava/lang/StringBuilder;
    //   65: aload_2
    //   66: invokevirtual 40	java/lang/StringBuilder:append	(Ljava/lang/String;)Ljava/lang/StringBuilder;
    //   69: invokevirtual 48	java/lang/StringBuilder:toString	()Ljava/lang/String;
    //   72: invokestatic 54	android/net/Uri:parse	(Ljava/lang/String;)Landroid/net/Uri;
    //   75: aconst_null
    //   76: aconst_null
    //   77: aconst_null
    //   78: aconst_null
    //   79: invokevirtual 60	android/content/ContentResolver:query	(Landroid/net/Uri;[Ljava/lang/String;Ljava/lang/String;[Ljava/lang/String;Ljava/lang/String;)Landroid/database/Cursor;
    //   82: astore_1
    //   83: aload_1
    //   84: ifnull +139 -> 223
    //   87: aload_1
    //   88: invokeinterface 66 1 0
    //   93: ifeq +130 -> 223
    //   96: aload_1
    //   97: aload_1
    //   98: getstatic 72	com/baidu/android/pushservice/d/c$e:d	Lcom/baidu/android/pushservice/d/c$e;
    //   101: invokevirtual 75	com/baidu/android/pushservice/d/c$e:name	()Ljava/lang/String;
    //   104: invokeinterface 79 2 0
    //   109: invokeinterface 83 2 0
    //   114: astore_2
    //   115: new 30	java/lang/StringBuilder
    //   118: dup
    //   119: invokespecial 34	java/lang/StringBuilder:<init>	()V
    //   122: ldc 85
    //   124: invokevirtual 40	java/lang/StringBuilder:append	(Ljava/lang/String;)Ljava/lang/StringBuilder;
    //   127: aload_2
    //   128: invokevirtual 40	java/lang/StringBuilder:append	(Ljava/lang/String;)Ljava/lang/StringBuilder;
    //   131: invokevirtual 48	java/lang/StringBuilder:toString	()Ljava/lang/String;
    //   134: aload_0
    //   135: invokestatic 89	com/baidu/android/pushservice/j/p:b	(Ljava/lang/String;Landroid/content/Context;)V
    //   138: aload_2
    //   139: astore_0
    //   140: aload_0
    //   141: astore_2
    //   142: aload_1
    //   143: ifnull +11 -> 154
    //   146: aload_1
    //   147: invokeinterface 92 1 0
    //   152: aload_0
    //   153: astore_2
    //   154: aload_2
    //   155: areturn
    //   156: ldc 94
    //   158: astore_2
    //   159: goto -122 -> 37
    //   162: astore_0
    //   163: aconst_null
    //   164: astore_0
    //   165: aload_3
    //   166: astore_1
    //   167: aload_0
    //   168: astore_2
    //   169: aload_1
    //   170: ifnull -16 -> 154
    //   173: aload_1
    //   174: invokeinterface 92 1 0
    //   179: aload_0
    //   180: areturn
    //   181: astore_1
    //   182: aload_0
    //   183: areturn
    //   184: astore_0
    //   185: aload 4
    //   187: astore_1
    //   188: aload_1
    //   189: ifnull +9 -> 198
    //   192: aload_1
    //   193: invokeinterface 92 1 0
    //   198: aload_0
    //   199: athrow
    //   200: astore_1
    //   201: aload_0
    //   202: areturn
    //   203: astore_1
    //   204: goto -6 -> 198
    //   207: astore_0
    //   208: goto -20 -> 188
    //   211: astore_0
    //   212: aconst_null
    //   213: astore_0
    //   214: goto -47 -> 167
    //   217: astore_0
    //   218: aload_2
    //   219: astore_0
    //   220: goto -53 -> 167
    //   223: aconst_null
    //   224: astore_0
    //   225: goto -85 -> 140
    //   228: aconst_null
    //   229: astore_0
    //   230: aconst_null
    //   231: astore_1
    //   232: goto -92 -> 140
    // Local variable table:
    //   start	length	slot	name	signature
    //   0	235	0	paramContext	android.content.Context
    //   0	235	1	paramString	String
    //   36	183	2	localObject1	Object
    //   4	162	3	localObject2	Object
    //   1	185	4	localObject3	Object
    //   19	19	5	localContentResolver	android.content.ContentResolver
    // Exception table:
    //   from	to	target	type
    //   5	21	162	java/lang/Throwable
    //   26	34	162	java/lang/Throwable
    //   37	83	162	java/lang/Throwable
    //   173	179	181	java/lang/Exception
    //   5	21	184	finally
    //   26	34	184	finally
    //   37	83	184	finally
    //   146	152	200	java/lang/Exception
    //   192	198	203	java/lang/Exception
    //   87	115	207	finally
    //   115	138	207	finally
    //   87	115	211	java/lang/Throwable
    //   115	138	217	java/lang/Throwable
  }
  
  /* Error */
  public static void a(android.content.Context paramContext)
  {
    // Byte code:
    //   0: aconst_null
    //   1: astore 5
    //   3: aload_0
    //   4: invokestatic 101	com/baidu/android/pushservice/PushSettings:b	(Landroid/content/Context;)Ljava/lang/String;
    //   7: astore 7
    //   9: aload 7
    //   11: invokestatic 107	android/text/TextUtils:isEmpty	(Ljava/lang/CharSequence;)Z
    //   14: ifeq +4 -> 18
    //   17: return
    //   18: aload_0
    //   19: invokestatic 110	com/baidu/android/pushservice/j/p:u	(Landroid/content/Context;)Ljava/lang/String;
    //   22: astore 8
    //   24: aload_0
    //   25: aload 8
    //   27: invokestatic 16	com/baidu/android/pushservice/j/p:m	(Landroid/content/Context;Ljava/lang/String;)I
    //   30: invokestatic 115	com/baidu/android/pushservice/a:a	()S
    //   33: if_icmplt +460 -> 493
    //   36: aload_0
    //   37: invokevirtual 22	android/content/Context:getContentResolver	()Landroid/content/ContentResolver;
    //   40: astore 6
    //   42: aload 6
    //   44: ifnull +449 -> 493
    //   47: new 30	java/lang/StringBuilder
    //   50: dup
    //   51: invokespecial 34	java/lang/StringBuilder:<init>	()V
    //   54: ldc 36
    //   56: invokevirtual 40	java/lang/StringBuilder:append	(Ljava/lang/String;)Ljava/lang/StringBuilder;
    //   59: aload 8
    //   61: invokevirtual 40	java/lang/StringBuilder:append	(Ljava/lang/String;)Ljava/lang/StringBuilder;
    //   64: ldc 42
    //   66: invokevirtual 40	java/lang/StringBuilder:append	(Ljava/lang/String;)Ljava/lang/StringBuilder;
    //   69: ldc 44
    //   71: invokevirtual 40	java/lang/StringBuilder:append	(Ljava/lang/String;)Ljava/lang/StringBuilder;
    //   74: ldc 117
    //   76: invokevirtual 40	java/lang/StringBuilder:append	(Ljava/lang/String;)Ljava/lang/StringBuilder;
    //   79: invokevirtual 48	java/lang/StringBuilder:toString	()Ljava/lang/String;
    //   82: invokestatic 54	android/net/Uri:parse	(Ljava/lang/String;)Landroid/net/Uri;
    //   85: astore 8
    //   87: new 30	java/lang/StringBuilder
    //   90: dup
    //   91: invokespecial 34	java/lang/StringBuilder:<init>	()V
    //   94: getstatic 122	com/baidu/android/pushservice/d/c$d:b	Lcom/baidu/android/pushservice/d/c$d;
    //   97: invokevirtual 123	com/baidu/android/pushservice/d/c$d:name	()Ljava/lang/String;
    //   100: invokevirtual 40	java/lang/StringBuilder:append	(Ljava/lang/String;)Ljava/lang/StringBuilder;
    //   103: ldc 125
    //   105: invokevirtual 40	java/lang/StringBuilder:append	(Ljava/lang/String;)Ljava/lang/StringBuilder;
    //   108: getstatic 128	com/baidu/android/pushservice/d/c$d:h	Lcom/baidu/android/pushservice/d/c$d;
    //   111: invokevirtual 123	com/baidu/android/pushservice/d/c$d:name	()Ljava/lang/String;
    //   114: invokevirtual 40	java/lang/StringBuilder:append	(Ljava/lang/String;)Ljava/lang/StringBuilder;
    //   117: ldc -126
    //   119: invokevirtual 40	java/lang/StringBuilder:append	(Ljava/lang/String;)Ljava/lang/StringBuilder;
    //   122: getstatic 133	com/baidu/android/pushservice/d/c$d:e	Lcom/baidu/android/pushservice/d/c$d;
    //   125: invokevirtual 123	com/baidu/android/pushservice/d/c$d:name	()Ljava/lang/String;
    //   128: invokevirtual 40	java/lang/StringBuilder:append	(Ljava/lang/String;)Ljava/lang/StringBuilder;
    //   131: ldc -121
    //   133: invokevirtual 40	java/lang/StringBuilder:append	(Ljava/lang/String;)Ljava/lang/StringBuilder;
    //   136: invokevirtual 48	java/lang/StringBuilder:toString	()Ljava/lang/String;
    //   139: astore 9
    //   141: new 30	java/lang/StringBuilder
    //   144: dup
    //   145: invokespecial 34	java/lang/StringBuilder:<init>	()V
    //   148: getstatic 128	com/baidu/android/pushservice/d/c$d:h	Lcom/baidu/android/pushservice/d/c$d;
    //   151: invokevirtual 123	com/baidu/android/pushservice/d/c$d:name	()Ljava/lang/String;
    //   154: invokevirtual 40	java/lang/StringBuilder:append	(Ljava/lang/String;)Ljava/lang/StringBuilder;
    //   157: ldc -119
    //   159: invokevirtual 40	java/lang/StringBuilder:append	(Ljava/lang/String;)Ljava/lang/StringBuilder;
    //   162: bipush 7
    //   164: invokevirtual 140	java/lang/StringBuilder:append	(I)Ljava/lang/StringBuilder;
    //   167: invokevirtual 48	java/lang/StringBuilder:toString	()Ljava/lang/String;
    //   170: astore 10
    //   172: aload 6
    //   174: aload 8
    //   176: aconst_null
    //   177: aload 9
    //   179: iconst_3
    //   180: anewarray 142	java/lang/String
    //   183: dup
    //   184: iconst_0
    //   185: aload 7
    //   187: aastore
    //   188: dup
    //   189: iconst_1
    //   190: invokestatic 148	java/lang/System:currentTimeMillis	()J
    //   193: invokestatic 152	java/lang/String:valueOf	(J)Ljava/lang/String;
    //   196: aastore
    //   197: dup
    //   198: iconst_2
    //   199: invokestatic 148	java/lang/System:currentTimeMillis	()J
    //   202: ldc2_w 153
    //   205: lsub
    //   206: invokestatic 152	java/lang/String:valueOf	(J)Ljava/lang/String;
    //   209: aastore
    //   210: aload 10
    //   212: invokevirtual 60	android/content/ContentResolver:query	(Landroid/net/Uri;[Ljava/lang/String;Ljava/lang/String;[Ljava/lang/String;Ljava/lang/String;)Landroid/database/Cursor;
    //   215: astore 6
    //   217: aload 6
    //   219: astore 5
    //   221: aload 5
    //   223: astore 6
    //   225: aload 5
    //   227: ifnull +269 -> 496
    //   230: iconst_0
    //   231: istore_1
    //   232: aload 5
    //   234: astore 6
    //   236: aload 5
    //   238: invokeinterface 157 1 0
    //   243: ifeq +253 -> 496
    //   246: aload 5
    //   248: aload 5
    //   250: getstatic 159	com/baidu/android/pushservice/d/c$d:d	Lcom/baidu/android/pushservice/d/c$d;
    //   253: invokevirtual 123	com/baidu/android/pushservice/d/c$d:name	()Ljava/lang/String;
    //   256: invokeinterface 79 2 0
    //   261: invokeinterface 163 2 0
    //   266: lstore_3
    //   267: aload_0
    //   268: lload_3
    //   269: invokestatic 152	java/lang/String:valueOf	(J)Ljava/lang/String;
    //   272: invokestatic 166	com/baidu/android/pushservice/j/p:s	(Landroid/content/Context;Ljava/lang/String;)Z
    //   275: ifne -43 -> 232
    //   278: aload 5
    //   280: aload 5
    //   282: getstatic 169	com/baidu/android/pushservice/d/c$d:g	Lcom/baidu/android/pushservice/d/c$d;
    //   285: invokevirtual 123	com/baidu/android/pushservice/d/c$d:name	()Ljava/lang/String;
    //   288: invokeinterface 79 2 0
    //   293: invokeinterface 173 2 0
    //   298: astore 6
    //   300: aload 6
    //   302: ifnull -70 -> 232
    //   305: aload 6
    //   307: arraylength
    //   308: ifeq -76 -> 232
    //   311: aload_0
    //   312: aload 7
    //   314: aload 6
    //   316: invokestatic 179	com/baidu/android/pushservice/jni/BaiduAppSSOJni:getDecrypted	(Landroid/content/Context;Ljava/lang/String;[B)[B
    //   319: astore 6
    //   321: aload 5
    //   323: aload 5
    //   325: getstatic 128	com/baidu/android/pushservice/d/c$d:h	Lcom/baidu/android/pushservice/d/c$d;
    //   328: invokevirtual 123	com/baidu/android/pushservice/d/c$d:name	()Ljava/lang/String;
    //   331: invokeinterface 79 2 0
    //   336: invokeinterface 163 2 0
    //   341: pop2
    //   342: aload 5
    //   344: aload 5
    //   346: getstatic 182	com/baidu/android/pushservice/d/c$d:c	Lcom/baidu/android/pushservice/d/c$d;
    //   349: invokevirtual 123	com/baidu/android/pushservice/d/c$d:name	()Ljava/lang/String;
    //   352: invokeinterface 79 2 0
    //   357: invokeinterface 186 2 0
    //   362: istore_2
    //   363: aload 5
    //   365: aload 5
    //   367: getstatic 189	com/baidu/android/pushservice/d/c$d:f	Lcom/baidu/android/pushservice/d/c$d;
    //   370: invokevirtual 123	com/baidu/android/pushservice/d/c$d:name	()Ljava/lang/String;
    //   373: invokeinterface 79 2 0
    //   378: invokeinterface 173 2 0
    //   383: astore 8
    //   385: new 191	android/content/Intent
    //   388: dup
    //   389: invokespecial 192	android/content/Intent:<init>	()V
    //   392: astore 9
    //   394: aload 9
    //   396: ldc -62
    //   398: aload 7
    //   400: invokevirtual 198	android/content/Intent:putExtra	(Ljava/lang/String;Ljava/lang/String;)Landroid/content/Intent;
    //   403: pop
    //   404: aload 9
    //   406: ldc -56
    //   408: lload_3
    //   409: invokestatic 152	java/lang/String:valueOf	(J)Ljava/lang/String;
    //   412: invokevirtual 198	android/content/Intent:putExtra	(Ljava/lang/String;Ljava/lang/String;)Landroid/content/Intent;
    //   415: pop
    //   416: aload 9
    //   418: ldc -54
    //   420: iload_2
    //   421: invokevirtual 205	android/content/Intent:putExtra	(Ljava/lang/String;I)Landroid/content/Intent;
    //   424: pop
    //   425: aload 9
    //   427: ldc -49
    //   429: aload 6
    //   431: invokevirtual 210	android/content/Intent:putExtra	(Ljava/lang/String;[B)Landroid/content/Intent;
    //   434: pop
    //   435: aload 9
    //   437: ldc -44
    //   439: aload 8
    //   441: invokevirtual 210	android/content/Intent:putExtra	(Ljava/lang/String;[B)Landroid/content/Intent;
    //   444: pop
    //   445: aload 9
    //   447: ldc -42
    //   449: iconst_1
    //   450: invokevirtual 217	android/content/Intent:putExtra	(Ljava/lang/String;Z)Landroid/content/Intent;
    //   453: pop
    //   454: aload_0
    //   455: aload 9
    //   457: ldc -37
    //   459: aload_0
    //   460: invokevirtual 222	android/content/Context:getPackageName	()Ljava/lang/String;
    //   463: invokestatic 225	com/baidu/android/pushservice/j/p:a	(Landroid/content/Context;Landroid/content/Intent;Ljava/lang/String;Ljava/lang/String;)I
    //   466: pop
    //   467: iload_1
    //   468: iconst_1
    //   469: iadd
    //   470: istore_2
    //   471: iload_2
    //   472: istore_1
    //   473: iload_2
    //   474: iconst_2
    //   475: if_icmple -243 -> 232
    //   478: aload 5
    //   480: ifnull -463 -> 17
    //   483: aload 5
    //   485: invokeinterface 92 1 0
    //   490: return
    //   491: astore_0
    //   492: return
    //   493: aconst_null
    //   494: astore 6
    //   496: aload 6
    //   498: ifnull -481 -> 17
    //   501: aload 6
    //   503: invokeinterface 92 1 0
    //   508: return
    //   509: astore_0
    //   510: return
    //   511: astore_0
    //   512: aconst_null
    //   513: astore 5
    //   515: aload 5
    //   517: ifnull -500 -> 17
    //   520: aload 5
    //   522: invokeinterface 92 1 0
    //   527: return
    //   528: astore_0
    //   529: return
    //   530: astore_0
    //   531: aload 5
    //   533: ifnull +10 -> 543
    //   536: aload 5
    //   538: invokeinterface 92 1 0
    //   543: aload_0
    //   544: athrow
    //   545: astore 5
    //   547: goto -4 -> 543
    //   550: astore_0
    //   551: goto -20 -> 531
    //   554: astore_0
    //   555: goto -40 -> 515
    // Local variable table:
    //   start	length	slot	name	signature
    //   0	558	0	paramContext	android.content.Context
    //   231	242	1	i	int
    //   362	114	2	j	int
    //   266	143	3	l	long
    //   1	536	5	localObject1	Object
    //   545	1	5	localException	Exception
    //   40	462	6	localObject2	Object
    //   7	392	7	str1	String
    //   22	418	8	localObject3	Object
    //   139	317	9	localObject4	Object
    //   170	41	10	str2	String
    // Exception table:
    //   from	to	target	type
    //   483	490	491	java/lang/Exception
    //   501	508	509	java/lang/Exception
    //   18	42	511	java/lang/Throwable
    //   47	217	511	java/lang/Throwable
    //   520	527	528	java/lang/Exception
    //   18	42	530	finally
    //   47	217	530	finally
    //   536	543	545	java/lang/Exception
    //   236	300	550	finally
    //   305	467	550	finally
    //   236	300	554	java/lang/Throwable
    //   305	467	554	java/lang/Throwable
  }
  
  /* Error */
  public static String b(android.content.Context paramContext, String paramString)
  {
    // Byte code:
    //   0: aconst_null
    //   1: astore 4
    //   3: aconst_null
    //   4: astore_3
    //   5: aload_0
    //   6: aload_1
    //   7: invokestatic 16	com/baidu/android/pushservice/j/p:m	(Landroid/content/Context;Ljava/lang/String;)I
    //   10: bipush 52
    //   12: if_icmplt +216 -> 228
    //   15: aload_0
    //   16: invokevirtual 22	android/content/Context:getContentResolver	()Landroid/content/ContentResolver;
    //   19: astore 5
    //   21: aload 5
    //   23: ifnull +205 -> 228
    //   26: aload_0
    //   27: aload_1
    //   28: invokestatic 26	com/baidu/android/pushservice/j/p:z	(Landroid/content/Context;Ljava/lang/String;)Z
    //   31: ifeq +125 -> 156
    //   34: ldc 28
    //   36: astore_2
    //   37: aload 5
    //   39: new 30	java/lang/StringBuilder
    //   42: dup
    //   43: invokespecial 34	java/lang/StringBuilder:<init>	()V
    //   46: ldc 36
    //   48: invokevirtual 40	java/lang/StringBuilder:append	(Ljava/lang/String;)Ljava/lang/StringBuilder;
    //   51: aload_1
    //   52: invokevirtual 40	java/lang/StringBuilder:append	(Ljava/lang/String;)Ljava/lang/StringBuilder;
    //   55: ldc 42
    //   57: invokevirtual 40	java/lang/StringBuilder:append	(Ljava/lang/String;)Ljava/lang/StringBuilder;
    //   60: ldc 44
    //   62: invokevirtual 40	java/lang/StringBuilder:append	(Ljava/lang/String;)Ljava/lang/StringBuilder;
    //   65: aload_2
    //   66: invokevirtual 40	java/lang/StringBuilder:append	(Ljava/lang/String;)Ljava/lang/StringBuilder;
    //   69: invokevirtual 48	java/lang/StringBuilder:toString	()Ljava/lang/String;
    //   72: invokestatic 54	android/net/Uri:parse	(Ljava/lang/String;)Landroid/net/Uri;
    //   75: aconst_null
    //   76: aconst_null
    //   77: aconst_null
    //   78: aconst_null
    //   79: invokevirtual 60	android/content/ContentResolver:query	(Landroid/net/Uri;[Ljava/lang/String;Ljava/lang/String;[Ljava/lang/String;Ljava/lang/String;)Landroid/database/Cursor;
    //   82: astore_1
    //   83: aload_1
    //   84: ifnull +139 -> 223
    //   87: aload_1
    //   88: invokeinterface 66 1 0
    //   93: ifeq +130 -> 223
    //   96: aload_1
    //   97: aload_1
    //   98: getstatic 227	com/baidu/android/pushservice/d/c$e:e	Lcom/baidu/android/pushservice/d/c$e;
    //   101: invokevirtual 75	com/baidu/android/pushservice/d/c$e:name	()Ljava/lang/String;
    //   104: invokeinterface 79 2 0
    //   109: invokeinterface 83 2 0
    //   114: astore_2
    //   115: new 30	java/lang/StringBuilder
    //   118: dup
    //   119: invokespecial 34	java/lang/StringBuilder:<init>	()V
    //   122: ldc -27
    //   124: invokevirtual 40	java/lang/StringBuilder:append	(Ljava/lang/String;)Ljava/lang/StringBuilder;
    //   127: aload_2
    //   128: invokevirtual 40	java/lang/StringBuilder:append	(Ljava/lang/String;)Ljava/lang/StringBuilder;
    //   131: invokevirtual 48	java/lang/StringBuilder:toString	()Ljava/lang/String;
    //   134: aload_0
    //   135: invokestatic 89	com/baidu/android/pushservice/j/p:b	(Ljava/lang/String;Landroid/content/Context;)V
    //   138: aload_2
    //   139: astore_0
    //   140: aload_0
    //   141: astore_2
    //   142: aload_1
    //   143: ifnull +11 -> 154
    //   146: aload_1
    //   147: invokeinterface 92 1 0
    //   152: aload_0
    //   153: astore_2
    //   154: aload_2
    //   155: areturn
    //   156: ldc 94
    //   158: astore_2
    //   159: goto -122 -> 37
    //   162: astore_0
    //   163: aconst_null
    //   164: astore_0
    //   165: aload_3
    //   166: astore_1
    //   167: aload_0
    //   168: astore_2
    //   169: aload_1
    //   170: ifnull -16 -> 154
    //   173: aload_1
    //   174: invokeinterface 92 1 0
    //   179: aload_0
    //   180: areturn
    //   181: astore_1
    //   182: aload_0
    //   183: areturn
    //   184: astore_0
    //   185: aload 4
    //   187: astore_1
    //   188: aload_1
    //   189: ifnull +9 -> 198
    //   192: aload_1
    //   193: invokeinterface 92 1 0
    //   198: aload_0
    //   199: athrow
    //   200: astore_1
    //   201: aload_0
    //   202: areturn
    //   203: astore_1
    //   204: goto -6 -> 198
    //   207: astore_0
    //   208: goto -20 -> 188
    //   211: astore_0
    //   212: aconst_null
    //   213: astore_0
    //   214: goto -47 -> 167
    //   217: astore_0
    //   218: aload_2
    //   219: astore_0
    //   220: goto -53 -> 167
    //   223: aconst_null
    //   224: astore_0
    //   225: goto -85 -> 140
    //   228: aconst_null
    //   229: astore_0
    //   230: aconst_null
    //   231: astore_1
    //   232: goto -92 -> 140
    // Local variable table:
    //   start	length	slot	name	signature
    //   0	235	0	paramContext	android.content.Context
    //   0	235	1	paramString	String
    //   36	183	2	localObject1	Object
    //   4	162	3	localObject2	Object
    //   1	185	4	localObject3	Object
    //   19	19	5	localContentResolver	android.content.ContentResolver
    // Exception table:
    //   from	to	target	type
    //   5	21	162	java/lang/Throwable
    //   26	34	162	java/lang/Throwable
    //   37	83	162	java/lang/Throwable
    //   173	179	181	java/lang/Exception
    //   5	21	184	finally
    //   26	34	184	finally
    //   37	83	184	finally
    //   146	152	200	java/lang/Exception
    //   192	198	203	java/lang/Exception
    //   87	115	207	finally
    //   115	138	207	finally
    //   87	115	211	java/lang/Throwable
    //   115	138	217	java/lang/Throwable
  }
  
  /* Error */
  public static int c(android.content.Context paramContext, String paramString)
  {
    // Byte code:
    //   0: aconst_null
    //   1: astore 5
    //   3: aload_0
    //   4: aload_1
    //   5: invokestatic 16	com/baidu/android/pushservice/j/p:m	(Landroid/content/Context;Ljava/lang/String;)I
    //   8: bipush 52
    //   10: if_icmplt +215 -> 225
    //   13: aload_0
    //   14: invokevirtual 22	android/content/Context:getContentResolver	()Landroid/content/ContentResolver;
    //   17: astore 6
    //   19: aload 6
    //   21: ifnull +204 -> 225
    //   24: aload_0
    //   25: aload_1
    //   26: invokestatic 26	com/baidu/android/pushservice/j/p:z	(Landroid/content/Context;Ljava/lang/String;)Z
    //   29: ifeq +125 -> 154
    //   32: ldc 28
    //   34: astore 4
    //   36: aload 6
    //   38: new 30	java/lang/StringBuilder
    //   41: dup
    //   42: invokespecial 34	java/lang/StringBuilder:<init>	()V
    //   45: ldc 36
    //   47: invokevirtual 40	java/lang/StringBuilder:append	(Ljava/lang/String;)Ljava/lang/StringBuilder;
    //   50: aload_1
    //   51: invokevirtual 40	java/lang/StringBuilder:append	(Ljava/lang/String;)Ljava/lang/StringBuilder;
    //   54: ldc 42
    //   56: invokevirtual 40	java/lang/StringBuilder:append	(Ljava/lang/String;)Ljava/lang/StringBuilder;
    //   59: ldc 44
    //   61: invokevirtual 40	java/lang/StringBuilder:append	(Ljava/lang/String;)Ljava/lang/StringBuilder;
    //   64: aload 4
    //   66: invokevirtual 40	java/lang/StringBuilder:append	(Ljava/lang/String;)Ljava/lang/StringBuilder;
    //   69: invokevirtual 48	java/lang/StringBuilder:toString	()Ljava/lang/String;
    //   72: invokestatic 54	android/net/Uri:parse	(Ljava/lang/String;)Landroid/net/Uri;
    //   75: aconst_null
    //   76: aconst_null
    //   77: aconst_null
    //   78: aconst_null
    //   79: invokevirtual 60	android/content/ContentResolver:query	(Landroid/net/Uri;[Ljava/lang/String;Ljava/lang/String;[Ljava/lang/String;Ljava/lang/String;)Landroid/database/Cursor;
    //   82: astore_1
    //   83: aload_1
    //   84: ifnull +136 -> 220
    //   87: aload_1
    //   88: invokeinterface 66 1 0
    //   93: ifeq +127 -> 220
    //   96: aload_1
    //   97: aload_1
    //   98: getstatic 231	com/baidu/android/pushservice/d/c$e:b	Lcom/baidu/android/pushservice/d/c$e;
    //   101: invokevirtual 75	com/baidu/android/pushservice/d/c$e:name	()Ljava/lang/String;
    //   104: invokeinterface 79 2 0
    //   109: invokeinterface 186 2 0
    //   114: istore_2
    //   115: new 30	java/lang/StringBuilder
    //   118: dup
    //   119: invokespecial 34	java/lang/StringBuilder:<init>	()V
    //   122: ldc -23
    //   124: invokevirtual 40	java/lang/StringBuilder:append	(Ljava/lang/String;)Ljava/lang/StringBuilder;
    //   127: iload_2
    //   128: invokevirtual 140	java/lang/StringBuilder:append	(I)Ljava/lang/StringBuilder;
    //   131: invokevirtual 48	java/lang/StringBuilder:toString	()Ljava/lang/String;
    //   134: aload_0
    //   135: invokestatic 89	com/baidu/android/pushservice/j/p:b	(Ljava/lang/String;Landroid/content/Context;)V
    //   138: iload_2
    //   139: istore_3
    //   140: aload_1
    //   141: ifnull +11 -> 152
    //   144: aload_1
    //   145: invokeinterface 92 1 0
    //   150: iload_2
    //   151: istore_3
    //   152: iload_3
    //   153: ireturn
    //   154: ldc 94
    //   156: astore 4
    //   158: goto -122 -> 36
    //   161: astore_0
    //   162: iconst_0
    //   163: istore_2
    //   164: aconst_null
    //   165: astore_1
    //   166: iload_2
    //   167: istore_3
    //   168: aload_1
    //   169: ifnull -17 -> 152
    //   172: aload_1
    //   173: invokeinterface 92 1 0
    //   178: iload_2
    //   179: ireturn
    //   180: astore_0
    //   181: iload_2
    //   182: ireturn
    //   183: astore_0
    //   184: aload 5
    //   186: astore_1
    //   187: aload_1
    //   188: ifnull +9 -> 197
    //   191: aload_1
    //   192: invokeinterface 92 1 0
    //   197: aload_0
    //   198: athrow
    //   199: astore_0
    //   200: iload_2
    //   201: ireturn
    //   202: astore_1
    //   203: goto -6 -> 197
    //   206: astore_0
    //   207: goto -20 -> 187
    //   210: astore_0
    //   211: iconst_0
    //   212: istore_2
    //   213: goto -47 -> 166
    //   216: astore_0
    //   217: goto -51 -> 166
    //   220: iconst_0
    //   221: istore_2
    //   222: goto -84 -> 138
    //   225: iconst_0
    //   226: istore_2
    //   227: aconst_null
    //   228: astore_1
    //   229: goto -91 -> 138
    // Local variable table:
    //   start	length	slot	name	signature
    //   0	232	0	paramContext	android.content.Context
    //   0	232	1	paramString	String
    //   114	113	2	i	int
    //   139	29	3	j	int
    //   34	123	4	str	String
    //   1	184	5	localObject	Object
    //   17	20	6	localContentResolver	android.content.ContentResolver
    // Exception table:
    //   from	to	target	type
    //   3	19	161	java/lang/Throwable
    //   24	32	161	java/lang/Throwable
    //   36	83	161	java/lang/Throwable
    //   172	178	180	java/lang/Exception
    //   3	19	183	finally
    //   24	32	183	finally
    //   36	83	183	finally
    //   144	150	199	java/lang/Exception
    //   191	197	202	java/lang/Exception
    //   87	115	206	finally
    //   115	138	206	finally
    //   87	115	210	java/lang/Throwable
    //   115	138	216	java/lang/Throwable
  }
  
  /* Error */
  public static int d(android.content.Context paramContext, String paramString)
  {
    // Byte code:
    //   0: aconst_null
    //   1: astore 5
    //   3: aconst_null
    //   4: astore 6
    //   6: iconst_0
    //   7: istore_3
    //   8: aload 6
    //   10: astore 4
    //   12: aload_0
    //   13: aload_1
    //   14: invokestatic 236	com/baidu/android/pushservice/j/p:C	(Landroid/content/Context;Ljava/lang/String;)I
    //   17: istore_2
    //   18: iload_2
    //   19: ifle +19 -> 38
    //   22: iconst_0
    //   23: ifeq +11 -> 34
    //   26: new 238	java/lang/NullPointerException
    //   29: dup
    //   30: invokespecial 239	java/lang/NullPointerException:<init>	()V
    //   33: athrow
    //   34: iload_2
    //   35: istore_3
    //   36: iload_3
    //   37: ireturn
    //   38: iload_2
    //   39: istore_3
    //   40: aload 6
    //   42: astore 4
    //   44: aload_0
    //   45: invokevirtual 22	android/content/Context:getContentResolver	()Landroid/content/ContentResolver;
    //   48: astore 7
    //   50: aload 7
    //   52: ifnull +270 -> 322
    //   55: iload_2
    //   56: istore_3
    //   57: aload 6
    //   59: astore 4
    //   61: aload 7
    //   63: new 30	java/lang/StringBuilder
    //   66: dup
    //   67: invokespecial 34	java/lang/StringBuilder:<init>	()V
    //   70: ldc 36
    //   72: invokevirtual 40	java/lang/StringBuilder:append	(Ljava/lang/String;)Ljava/lang/StringBuilder;
    //   75: aload_1
    //   76: invokevirtual 40	java/lang/StringBuilder:append	(Ljava/lang/String;)Ljava/lang/StringBuilder;
    //   79: ldc 42
    //   81: invokevirtual 40	java/lang/StringBuilder:append	(Ljava/lang/String;)Ljava/lang/StringBuilder;
    //   84: ldc 44
    //   86: invokevirtual 40	java/lang/StringBuilder:append	(Ljava/lang/String;)Ljava/lang/StringBuilder;
    //   89: ldc 28
    //   91: invokevirtual 40	java/lang/StringBuilder:append	(Ljava/lang/String;)Ljava/lang/StringBuilder;
    //   94: invokevirtual 48	java/lang/StringBuilder:toString	()Ljava/lang/String;
    //   97: invokestatic 54	android/net/Uri:parse	(Ljava/lang/String;)Landroid/net/Uri;
    //   100: aconst_null
    //   101: aconst_null
    //   102: aconst_null
    //   103: aconst_null
    //   104: invokevirtual 60	android/content/ContentResolver:query	(Landroid/net/Uri;[Ljava/lang/String;Ljava/lang/String;[Ljava/lang/String;Ljava/lang/String;)Landroid/database/Cursor;
    //   107: astore_0
    //   108: aload_0
    //   109: ifnull +59 -> 168
    //   112: aload_0
    //   113: astore 4
    //   115: aload_0
    //   116: astore 5
    //   118: aload_0
    //   119: invokeinterface 66 1 0
    //   124: ifeq +198 -> 322
    //   127: aload_0
    //   128: astore 4
    //   130: aload_0
    //   131: aload_0
    //   132: getstatic 241	com/baidu/android/pushservice/d/c$e:c	Lcom/baidu/android/pushservice/d/c$e;
    //   135: invokevirtual 75	com/baidu/android/pushservice/d/c$e:name	()Ljava/lang/String;
    //   138: invokeinterface 79 2 0
    //   143: invokeinterface 186 2 0
    //   148: istore_3
    //   149: iload_3
    //   150: istore_2
    //   151: iload_2
    //   152: istore_3
    //   153: aload_0
    //   154: ifnull -118 -> 36
    //   157: aload_0
    //   158: invokeinterface 92 1 0
    //   163: iload_2
    //   164: ireturn
    //   165: astore_0
    //   166: iload_2
    //   167: ireturn
    //   168: aload_0
    //   169: astore 4
    //   171: aload 7
    //   173: new 30	java/lang/StringBuilder
    //   176: dup
    //   177: invokespecial 34	java/lang/StringBuilder:<init>	()V
    //   180: ldc 36
    //   182: invokevirtual 40	java/lang/StringBuilder:append	(Ljava/lang/String;)Ljava/lang/StringBuilder;
    //   185: aload_1
    //   186: invokevirtual 40	java/lang/StringBuilder:append	(Ljava/lang/String;)Ljava/lang/StringBuilder;
    //   189: ldc 42
    //   191: invokevirtual 40	java/lang/StringBuilder:append	(Ljava/lang/String;)Ljava/lang/StringBuilder;
    //   194: ldc 44
    //   196: invokevirtual 40	java/lang/StringBuilder:append	(Ljava/lang/String;)Ljava/lang/StringBuilder;
    //   199: ldc 94
    //   201: invokevirtual 40	java/lang/StringBuilder:append	(Ljava/lang/String;)Ljava/lang/StringBuilder;
    //   204: invokevirtual 48	java/lang/StringBuilder:toString	()Ljava/lang/String;
    //   207: invokestatic 54	android/net/Uri:parse	(Ljava/lang/String;)Landroid/net/Uri;
    //   210: aconst_null
    //   211: aconst_null
    //   212: aconst_null
    //   213: aconst_null
    //   214: invokevirtual 60	android/content/ContentResolver:query	(Landroid/net/Uri;[Ljava/lang/String;Ljava/lang/String;[Ljava/lang/String;Ljava/lang/String;)Landroid/database/Cursor;
    //   217: astore_1
    //   218: aload_1
    //   219: ifnull +98 -> 317
    //   222: aload_1
    //   223: invokeinterface 66 1 0
    //   228: ifeq +89 -> 317
    //   231: aload_1
    //   232: aload_1
    //   233: getstatic 241	com/baidu/android/pushservice/d/c$e:c	Lcom/baidu/android/pushservice/d/c$e;
    //   236: invokevirtual 75	com/baidu/android/pushservice/d/c$e:name	()Ljava/lang/String;
    //   239: invokeinterface 79 2 0
    //   244: invokeinterface 186 2 0
    //   249: istore_3
    //   250: aload_1
    //   251: astore_0
    //   252: iload_3
    //   253: istore_2
    //   254: goto -103 -> 151
    //   257: astore_0
    //   258: iload_3
    //   259: istore_2
    //   260: aconst_null
    //   261: astore_0
    //   262: iload_2
    //   263: istore_3
    //   264: aload_0
    //   265: ifnull -229 -> 36
    //   268: aload_0
    //   269: invokeinterface 92 1 0
    //   274: iload_2
    //   275: ireturn
    //   276: astore_0
    //   277: iload_2
    //   278: ireturn
    //   279: astore_0
    //   280: aload 4
    //   282: astore_1
    //   283: aload_1
    //   284: ifnull +9 -> 293
    //   287: aload_1
    //   288: invokeinterface 92 1 0
    //   293: aload_0
    //   294: athrow
    //   295: astore_0
    //   296: goto -262 -> 34
    //   299: astore_1
    //   300: goto -7 -> 293
    //   303: astore_0
    //   304: goto -21 -> 283
    //   307: astore_1
    //   308: goto -46 -> 262
    //   311: astore_0
    //   312: aload_1
    //   313: astore_0
    //   314: goto -52 -> 262
    //   317: aload_1
    //   318: astore_0
    //   319: goto -168 -> 151
    //   322: aload 5
    //   324: astore_0
    //   325: goto -174 -> 151
    // Local variable table:
    //   start	length	slot	name	signature
    //   0	328	0	paramContext	android.content.Context
    //   0	328	1	paramString	String
    //   17	261	2	i	int
    //   7	257	3	j	int
    //   10	271	4	localObject1	Object
    //   1	322	5	localContext	android.content.Context
    //   4	54	6	localObject2	Object
    //   48	124	7	localContentResolver	android.content.ContentResolver
    // Exception table:
    //   from	to	target	type
    //   157	163	165	java/lang/Exception
    //   12	18	257	java/lang/Throwable
    //   44	50	257	java/lang/Throwable
    //   61	108	257	java/lang/Throwable
    //   268	274	276	java/lang/Exception
    //   12	18	279	finally
    //   44	50	279	finally
    //   61	108	279	finally
    //   118	127	279	finally
    //   130	149	279	finally
    //   171	218	279	finally
    //   26	34	295	java/lang/Exception
    //   287	293	299	java/lang/Exception
    //   222	250	303	finally
    //   118	127	307	java/lang/Throwable
    //   130	149	307	java/lang/Throwable
    //   171	218	307	java/lang/Throwable
    //   222	250	311	java/lang/Throwable
  }
  
  /* Error */
  public static String e(android.content.Context paramContext, String paramString)
  {
    // Byte code:
    //   0: aconst_null
    //   1: astore 4
    //   3: aconst_null
    //   4: astore_3
    //   5: aload_0
    //   6: aload_1
    //   7: invokestatic 16	com/baidu/android/pushservice/j/p:m	(Landroid/content/Context;Ljava/lang/String;)I
    //   10: bipush 52
    //   12: if_icmplt +216 -> 228
    //   15: aload_0
    //   16: invokevirtual 22	android/content/Context:getContentResolver	()Landroid/content/ContentResolver;
    //   19: astore 5
    //   21: aload 5
    //   23: ifnull +205 -> 228
    //   26: aload_0
    //   27: aload_1
    //   28: invokestatic 26	com/baidu/android/pushservice/j/p:z	(Landroid/content/Context;Ljava/lang/String;)Z
    //   31: ifeq +125 -> 156
    //   34: ldc 28
    //   36: astore_2
    //   37: aload 5
    //   39: new 30	java/lang/StringBuilder
    //   42: dup
    //   43: invokespecial 34	java/lang/StringBuilder:<init>	()V
    //   46: ldc 36
    //   48: invokevirtual 40	java/lang/StringBuilder:append	(Ljava/lang/String;)Ljava/lang/StringBuilder;
    //   51: aload_1
    //   52: invokevirtual 40	java/lang/StringBuilder:append	(Ljava/lang/String;)Ljava/lang/StringBuilder;
    //   55: ldc 42
    //   57: invokevirtual 40	java/lang/StringBuilder:append	(Ljava/lang/String;)Ljava/lang/StringBuilder;
    //   60: ldc 44
    //   62: invokevirtual 40	java/lang/StringBuilder:append	(Ljava/lang/String;)Ljava/lang/StringBuilder;
    //   65: aload_2
    //   66: invokevirtual 40	java/lang/StringBuilder:append	(Ljava/lang/String;)Ljava/lang/StringBuilder;
    //   69: invokevirtual 48	java/lang/StringBuilder:toString	()Ljava/lang/String;
    //   72: invokestatic 54	android/net/Uri:parse	(Ljava/lang/String;)Landroid/net/Uri;
    //   75: aconst_null
    //   76: aconst_null
    //   77: aconst_null
    //   78: aconst_null
    //   79: invokevirtual 60	android/content/ContentResolver:query	(Landroid/net/Uri;[Ljava/lang/String;Ljava/lang/String;[Ljava/lang/String;Ljava/lang/String;)Landroid/database/Cursor;
    //   82: astore_1
    //   83: aload_1
    //   84: ifnull +139 -> 223
    //   87: aload_1
    //   88: invokeinterface 66 1 0
    //   93: ifeq +130 -> 223
    //   96: aload_1
    //   97: aload_1
    //   98: getstatic 243	com/baidu/android/pushservice/d/c$e:h	Lcom/baidu/android/pushservice/d/c$e;
    //   101: invokevirtual 75	com/baidu/android/pushservice/d/c$e:name	()Ljava/lang/String;
    //   104: invokeinterface 79 2 0
    //   109: invokeinterface 83 2 0
    //   114: astore_2
    //   115: new 30	java/lang/StringBuilder
    //   118: dup
    //   119: invokespecial 34	java/lang/StringBuilder:<init>	()V
    //   122: ldc -11
    //   124: invokevirtual 40	java/lang/StringBuilder:append	(Ljava/lang/String;)Ljava/lang/StringBuilder;
    //   127: aload_2
    //   128: invokevirtual 40	java/lang/StringBuilder:append	(Ljava/lang/String;)Ljava/lang/StringBuilder;
    //   131: invokevirtual 48	java/lang/StringBuilder:toString	()Ljava/lang/String;
    //   134: aload_0
    //   135: invokestatic 89	com/baidu/android/pushservice/j/p:b	(Ljava/lang/String;Landroid/content/Context;)V
    //   138: aload_2
    //   139: astore_0
    //   140: aload_0
    //   141: astore_2
    //   142: aload_1
    //   143: ifnull +11 -> 154
    //   146: aload_1
    //   147: invokeinterface 92 1 0
    //   152: aload_0
    //   153: astore_2
    //   154: aload_2
    //   155: areturn
    //   156: ldc 94
    //   158: astore_2
    //   159: goto -122 -> 37
    //   162: astore_0
    //   163: aconst_null
    //   164: astore_0
    //   165: aload_3
    //   166: astore_1
    //   167: aload_0
    //   168: astore_2
    //   169: aload_1
    //   170: ifnull -16 -> 154
    //   173: aload_1
    //   174: invokeinterface 92 1 0
    //   179: aload_0
    //   180: areturn
    //   181: astore_1
    //   182: aload_0
    //   183: areturn
    //   184: astore_0
    //   185: aload 4
    //   187: astore_1
    //   188: aload_1
    //   189: ifnull +9 -> 198
    //   192: aload_1
    //   193: invokeinterface 92 1 0
    //   198: aload_0
    //   199: athrow
    //   200: astore_1
    //   201: aload_0
    //   202: areturn
    //   203: astore_1
    //   204: goto -6 -> 198
    //   207: astore_0
    //   208: goto -20 -> 188
    //   211: astore_0
    //   212: aconst_null
    //   213: astore_0
    //   214: goto -47 -> 167
    //   217: astore_0
    //   218: aload_2
    //   219: astore_0
    //   220: goto -53 -> 167
    //   223: aconst_null
    //   224: astore_0
    //   225: goto -85 -> 140
    //   228: aconst_null
    //   229: astore_0
    //   230: aconst_null
    //   231: astore_1
    //   232: goto -92 -> 140
    // Local variable table:
    //   start	length	slot	name	signature
    //   0	235	0	paramContext	android.content.Context
    //   0	235	1	paramString	String
    //   36	183	2	localObject1	Object
    //   4	162	3	localObject2	Object
    //   1	185	4	localObject3	Object
    //   19	19	5	localContentResolver	android.content.ContentResolver
    // Exception table:
    //   from	to	target	type
    //   5	21	162	java/lang/Throwable
    //   26	34	162	java/lang/Throwable
    //   37	83	162	java/lang/Throwable
    //   173	179	181	java/lang/Exception
    //   5	21	184	finally
    //   26	34	184	finally
    //   37	83	184	finally
    //   146	152	200	java/lang/Exception
    //   192	198	203	java/lang/Exception
    //   87	115	207	finally
    //   115	138	207	finally
    //   87	115	211	java/lang/Throwable
    //   115	138	217	java/lang/Throwable
  }
  
  /* Error */
  public static String f(android.content.Context paramContext, String paramString)
  {
    // Byte code:
    //   0: aconst_null
    //   1: astore 4
    //   3: aconst_null
    //   4: astore_3
    //   5: aload_0
    //   6: aload_1
    //   7: invokestatic 16	com/baidu/android/pushservice/j/p:m	(Landroid/content/Context;Ljava/lang/String;)I
    //   10: bipush 52
    //   12: if_icmplt +216 -> 228
    //   15: aload_0
    //   16: invokevirtual 22	android/content/Context:getContentResolver	()Landroid/content/ContentResolver;
    //   19: astore 5
    //   21: aload 5
    //   23: ifnull +205 -> 228
    //   26: aload_0
    //   27: aload_1
    //   28: invokestatic 26	com/baidu/android/pushservice/j/p:z	(Landroid/content/Context;Ljava/lang/String;)Z
    //   31: ifeq +125 -> 156
    //   34: ldc 28
    //   36: astore_2
    //   37: aload 5
    //   39: new 30	java/lang/StringBuilder
    //   42: dup
    //   43: invokespecial 34	java/lang/StringBuilder:<init>	()V
    //   46: ldc 36
    //   48: invokevirtual 40	java/lang/StringBuilder:append	(Ljava/lang/String;)Ljava/lang/StringBuilder;
    //   51: aload_1
    //   52: invokevirtual 40	java/lang/StringBuilder:append	(Ljava/lang/String;)Ljava/lang/StringBuilder;
    //   55: ldc 42
    //   57: invokevirtual 40	java/lang/StringBuilder:append	(Ljava/lang/String;)Ljava/lang/StringBuilder;
    //   60: ldc 44
    //   62: invokevirtual 40	java/lang/StringBuilder:append	(Ljava/lang/String;)Ljava/lang/StringBuilder;
    //   65: aload_2
    //   66: invokevirtual 40	java/lang/StringBuilder:append	(Ljava/lang/String;)Ljava/lang/StringBuilder;
    //   69: invokevirtual 48	java/lang/StringBuilder:toString	()Ljava/lang/String;
    //   72: invokestatic 54	android/net/Uri:parse	(Ljava/lang/String;)Landroid/net/Uri;
    //   75: aconst_null
    //   76: aconst_null
    //   77: aconst_null
    //   78: aconst_null
    //   79: invokevirtual 60	android/content/ContentResolver:query	(Landroid/net/Uri;[Ljava/lang/String;Ljava/lang/String;[Ljava/lang/String;Ljava/lang/String;)Landroid/database/Cursor;
    //   82: astore_1
    //   83: aload_1
    //   84: ifnull +139 -> 223
    //   87: aload_1
    //   88: invokeinterface 66 1 0
    //   93: ifeq +130 -> 223
    //   96: aload_1
    //   97: aload_1
    //   98: getstatic 248	com/baidu/android/pushservice/d/c$e:i	Lcom/baidu/android/pushservice/d/c$e;
    //   101: invokevirtual 75	com/baidu/android/pushservice/d/c$e:name	()Ljava/lang/String;
    //   104: invokeinterface 79 2 0
    //   109: invokeinterface 83 2 0
    //   114: astore_2
    //   115: new 30	java/lang/StringBuilder
    //   118: dup
    //   119: invokespecial 34	java/lang/StringBuilder:<init>	()V
    //   122: ldc -6
    //   124: invokevirtual 40	java/lang/StringBuilder:append	(Ljava/lang/String;)Ljava/lang/StringBuilder;
    //   127: aload_2
    //   128: invokevirtual 40	java/lang/StringBuilder:append	(Ljava/lang/String;)Ljava/lang/StringBuilder;
    //   131: invokevirtual 48	java/lang/StringBuilder:toString	()Ljava/lang/String;
    //   134: aload_0
    //   135: invokestatic 89	com/baidu/android/pushservice/j/p:b	(Ljava/lang/String;Landroid/content/Context;)V
    //   138: aload_2
    //   139: astore_0
    //   140: aload_0
    //   141: astore_2
    //   142: aload_1
    //   143: ifnull +11 -> 154
    //   146: aload_1
    //   147: invokeinterface 92 1 0
    //   152: aload_0
    //   153: astore_2
    //   154: aload_2
    //   155: areturn
    //   156: ldc 94
    //   158: astore_2
    //   159: goto -122 -> 37
    //   162: astore_0
    //   163: aconst_null
    //   164: astore_0
    //   165: aload_3
    //   166: astore_1
    //   167: aload_0
    //   168: astore_2
    //   169: aload_1
    //   170: ifnull -16 -> 154
    //   173: aload_1
    //   174: invokeinterface 92 1 0
    //   179: aload_0
    //   180: areturn
    //   181: astore_1
    //   182: aload_0
    //   183: areturn
    //   184: astore_0
    //   185: aload 4
    //   187: astore_1
    //   188: aload_1
    //   189: ifnull +9 -> 198
    //   192: aload_1
    //   193: invokeinterface 92 1 0
    //   198: aload_0
    //   199: athrow
    //   200: astore_1
    //   201: aload_0
    //   202: areturn
    //   203: astore_1
    //   204: goto -6 -> 198
    //   207: astore_0
    //   208: goto -20 -> 188
    //   211: astore_0
    //   212: aconst_null
    //   213: astore_0
    //   214: goto -47 -> 167
    //   217: astore_0
    //   218: aload_2
    //   219: astore_0
    //   220: goto -53 -> 167
    //   223: aconst_null
    //   224: astore_0
    //   225: goto -85 -> 140
    //   228: aconst_null
    //   229: astore_0
    //   230: aconst_null
    //   231: astore_1
    //   232: goto -92 -> 140
    // Local variable table:
    //   start	length	slot	name	signature
    //   0	235	0	paramContext	android.content.Context
    //   0	235	1	paramString	String
    //   36	183	2	localObject1	Object
    //   4	162	3	localObject2	Object
    //   1	185	4	localObject3	Object
    //   19	19	5	localContentResolver	android.content.ContentResolver
    // Exception table:
    //   from	to	target	type
    //   5	21	162	java/lang/Throwable
    //   26	34	162	java/lang/Throwable
    //   37	83	162	java/lang/Throwable
    //   173	179	181	java/lang/Exception
    //   5	21	184	finally
    //   26	34	184	finally
    //   37	83	184	finally
    //   146	152	200	java/lang/Exception
    //   192	198	203	java/lang/Exception
    //   87	115	207	finally
    //   115	138	207	finally
    //   87	115	211	java/lang/Throwable
    //   115	138	217	java/lang/Throwable
  }
  
  /* Error */
  public static String g(android.content.Context paramContext, String paramString)
  {
    // Byte code:
    //   0: aconst_null
    //   1: astore 4
    //   3: aconst_null
    //   4: astore_3
    //   5: aload_0
    //   6: aload_1
    //   7: invokestatic 16	com/baidu/android/pushservice/j/p:m	(Landroid/content/Context;Ljava/lang/String;)I
    //   10: bipush 52
    //   12: if_icmplt +216 -> 228
    //   15: aload_0
    //   16: invokevirtual 22	android/content/Context:getContentResolver	()Landroid/content/ContentResolver;
    //   19: astore 5
    //   21: aload 5
    //   23: ifnull +205 -> 228
    //   26: aload_0
    //   27: aload_1
    //   28: invokestatic 26	com/baidu/android/pushservice/j/p:z	(Landroid/content/Context;Ljava/lang/String;)Z
    //   31: ifeq +125 -> 156
    //   34: ldc 28
    //   36: astore_2
    //   37: aload 5
    //   39: new 30	java/lang/StringBuilder
    //   42: dup
    //   43: invokespecial 34	java/lang/StringBuilder:<init>	()V
    //   46: ldc 36
    //   48: invokevirtual 40	java/lang/StringBuilder:append	(Ljava/lang/String;)Ljava/lang/StringBuilder;
    //   51: aload_1
    //   52: invokevirtual 40	java/lang/StringBuilder:append	(Ljava/lang/String;)Ljava/lang/StringBuilder;
    //   55: ldc 42
    //   57: invokevirtual 40	java/lang/StringBuilder:append	(Ljava/lang/String;)Ljava/lang/StringBuilder;
    //   60: ldc 44
    //   62: invokevirtual 40	java/lang/StringBuilder:append	(Ljava/lang/String;)Ljava/lang/StringBuilder;
    //   65: aload_2
    //   66: invokevirtual 40	java/lang/StringBuilder:append	(Ljava/lang/String;)Ljava/lang/StringBuilder;
    //   69: invokevirtual 48	java/lang/StringBuilder:toString	()Ljava/lang/String;
    //   72: invokestatic 54	android/net/Uri:parse	(Ljava/lang/String;)Landroid/net/Uri;
    //   75: aconst_null
    //   76: aconst_null
    //   77: aconst_null
    //   78: aconst_null
    //   79: invokevirtual 60	android/content/ContentResolver:query	(Landroid/net/Uri;[Ljava/lang/String;Ljava/lang/String;[Ljava/lang/String;Ljava/lang/String;)Landroid/database/Cursor;
    //   82: astore_1
    //   83: aload_1
    //   84: ifnull +139 -> 223
    //   87: aload_1
    //   88: invokeinterface 66 1 0
    //   93: ifeq +130 -> 223
    //   96: aload_1
    //   97: aload_1
    //   98: getstatic 253	com/baidu/android/pushservice/d/c$e:j	Lcom/baidu/android/pushservice/d/c$e;
    //   101: invokevirtual 75	com/baidu/android/pushservice/d/c$e:name	()Ljava/lang/String;
    //   104: invokeinterface 79 2 0
    //   109: invokeinterface 83 2 0
    //   114: astore_2
    //   115: new 30	java/lang/StringBuilder
    //   118: dup
    //   119: invokespecial 34	java/lang/StringBuilder:<init>	()V
    //   122: ldc -1
    //   124: invokevirtual 40	java/lang/StringBuilder:append	(Ljava/lang/String;)Ljava/lang/StringBuilder;
    //   127: aload_2
    //   128: invokevirtual 40	java/lang/StringBuilder:append	(Ljava/lang/String;)Ljava/lang/StringBuilder;
    //   131: invokevirtual 48	java/lang/StringBuilder:toString	()Ljava/lang/String;
    //   134: aload_0
    //   135: invokestatic 89	com/baidu/android/pushservice/j/p:b	(Ljava/lang/String;Landroid/content/Context;)V
    //   138: aload_2
    //   139: astore_0
    //   140: aload_0
    //   141: astore_2
    //   142: aload_1
    //   143: ifnull +11 -> 154
    //   146: aload_1
    //   147: invokeinterface 92 1 0
    //   152: aload_0
    //   153: astore_2
    //   154: aload_2
    //   155: areturn
    //   156: ldc 94
    //   158: astore_2
    //   159: goto -122 -> 37
    //   162: astore_0
    //   163: aconst_null
    //   164: astore_0
    //   165: aload_3
    //   166: astore_1
    //   167: aload_0
    //   168: astore_2
    //   169: aload_1
    //   170: ifnull -16 -> 154
    //   173: aload_1
    //   174: invokeinterface 92 1 0
    //   179: aload_0
    //   180: areturn
    //   181: astore_1
    //   182: aload_0
    //   183: areturn
    //   184: astore_0
    //   185: aload 4
    //   187: astore_1
    //   188: aload_1
    //   189: ifnull +9 -> 198
    //   192: aload_1
    //   193: invokeinterface 92 1 0
    //   198: aload_0
    //   199: athrow
    //   200: astore_1
    //   201: aload_0
    //   202: areturn
    //   203: astore_1
    //   204: goto -6 -> 198
    //   207: astore_0
    //   208: goto -20 -> 188
    //   211: astore_0
    //   212: aconst_null
    //   213: astore_0
    //   214: goto -47 -> 167
    //   217: astore_0
    //   218: aload_2
    //   219: astore_0
    //   220: goto -53 -> 167
    //   223: aconst_null
    //   224: astore_0
    //   225: goto -85 -> 140
    //   228: aconst_null
    //   229: astore_0
    //   230: aconst_null
    //   231: astore_1
    //   232: goto -92 -> 140
    // Local variable table:
    //   start	length	slot	name	signature
    //   0	235	0	paramContext	android.content.Context
    //   0	235	1	paramString	String
    //   36	183	2	localObject1	Object
    //   4	162	3	localObject2	Object
    //   1	185	4	localObject3	Object
    //   19	19	5	localContentResolver	android.content.ContentResolver
    // Exception table:
    //   from	to	target	type
    //   5	21	162	java/lang/Throwable
    //   26	34	162	java/lang/Throwable
    //   37	83	162	java/lang/Throwable
    //   173	179	181	java/lang/Exception
    //   5	21	184	finally
    //   26	34	184	finally
    //   37	83	184	finally
    //   146	152	200	java/lang/Exception
    //   192	198	203	java/lang/Exception
    //   87	115	207	finally
    //   115	138	207	finally
    //   87	115	211	java/lang/Throwable
    //   115	138	217	java/lang/Throwable
  }
}


/* Location:              /Users/objectyan/Documents/OY/baiduCarLife_40/dist/classes-dex2jar.jar!/com/baidu/android/pushservice/d/d.class
 * Java compiler version: 6 (50.0)
 * JD-Core Version:       0.7.1
 */