package com.baidu.ufosdk.b;

public final class a
{
  /* Error */
  public static String a()
  {
    // Byte code:
    //   0: new 10	java/util/ArrayList
    //   3: dup
    //   4: invokespecial 14	java/util/ArrayList:<init>	()V
    //   7: astore_2
    //   8: aload_2
    //   9: ldc 16
    //   11: invokeinterface 22 2 0
    //   16: pop
    //   17: new 10	java/util/ArrayList
    //   20: dup
    //   21: invokespecial 14	java/util/ArrayList:<init>	()V
    //   24: astore_3
    //   25: aload_3
    //   26: iconst_4
    //   27: anewarray 24	java/lang/String
    //   30: dup
    //   31: iconst_0
    //   32: ldc 26
    //   34: aastore
    //   35: dup
    //   36: iconst_1
    //   37: ldc 28
    //   39: aastore
    //   40: dup
    //   41: iconst_2
    //   42: ldc 30
    //   44: aastore
    //   45: dup
    //   46: iconst_3
    //   47: ldc 32
    //   49: aastore
    //   50: invokestatic 38	java/util/Arrays:asList	([Ljava/lang/Object;)Ljava/util/List;
    //   53: invokeinterface 42 2 0
    //   58: pop
    //   59: aload_3
    //   60: ldc 26
    //   62: invokeinterface 46 2 0
    //   67: istore_0
    //   68: iload_0
    //   69: iflt +48 -> 117
    //   72: iload_0
    //   73: aload_3
    //   74: invokeinterface 50 1 0
    //   79: if_icmpge +38 -> 117
    //   82: invokestatic 54	com/baidu/ufosdk/util/i:a	()I
    //   85: bipush 8
    //   87: if_icmpge +30 -> 117
    //   90: aload_3
    //   91: iload_0
    //   92: iconst_1
    //   93: iadd
    //   94: invokeinterface 58 2 0
    //   99: pop
    //   100: aload_3
    //   101: iload_0
    //   102: invokeinterface 58 2 0
    //   107: pop
    //   108: aload_3
    //   109: ldc 60
    //   111: invokeinterface 22 2 0
    //   116: pop
    //   117: new 62	com/baidu/ufosdk/util/e
    //   120: dup
    //   121: invokespecial 63	com/baidu/ufosdk/util/e:<init>	()V
    //   124: astore_1
    //   125: aload_2
    //   126: aload_3
    //   127: invokeinterface 42 2 0
    //   132: pop
    //   133: invokestatic 69	java/lang/Runtime:getRuntime	()Ljava/lang/Runtime;
    //   136: aload_2
    //   137: aload_2
    //   138: invokeinterface 50 1 0
    //   143: anewarray 24	java/lang/String
    //   146: invokeinterface 73 2 0
    //   151: checkcast 75	[Ljava/lang/String;
    //   154: invokevirtual 79	java/lang/Runtime:exec	([Ljava/lang/String;)Ljava/lang/Process;
    //   157: astore_3
    //   158: new 81	java/io/BufferedReader
    //   161: dup
    //   162: new 83	java/io/InputStreamReader
    //   165: dup
    //   166: aload_3
    //   167: invokevirtual 89	java/lang/Process:getInputStream	()Ljava/io/InputStream;
    //   170: invokespecial 92	java/io/InputStreamReader:<init>	(Ljava/io/InputStream;)V
    //   173: sipush 8192
    //   176: invokespecial 95	java/io/BufferedReader:<init>	(Ljava/io/Reader;I)V
    //   179: astore_2
    //   180: new 97	java/lang/Thread
    //   183: dup
    //   184: new 99	com/baidu/ufosdk/b/b
    //   187: dup
    //   188: aload_3
    //   189: invokespecial 102	com/baidu/ufosdk/b/b:<init>	(Ljava/lang/Process;)V
    //   192: invokespecial 105	java/lang/Thread:<init>	(Ljava/lang/Runnable;)V
    //   195: invokevirtual 108	java/lang/Thread:start	()V
    //   198: aload_2
    //   199: invokevirtual 111	java/io/BufferedReader:readLine	()Ljava/lang/String;
    //   202: astore_3
    //   203: aload_3
    //   204: ifnull +30 -> 234
    //   207: aload_1
    //   208: new 113	java/lang/StringBuilder
    //   211: dup
    //   212: aload_3
    //   213: invokestatic 117	java/lang/String:valueOf	(Ljava/lang/Object;)Ljava/lang/String;
    //   216: invokespecial 120	java/lang/StringBuilder:<init>	(Ljava/lang/String;)V
    //   219: ldc 122
    //   221: invokevirtual 126	java/lang/StringBuilder:append	(Ljava/lang/String;)Ljava/lang/StringBuilder;
    //   224: invokevirtual 129	java/lang/StringBuilder:toString	()Ljava/lang/String;
    //   227: invokevirtual 132	java/util/LinkedList:add	(Ljava/lang/Object;)Z
    //   230: pop
    //   231: goto -33 -> 198
    //   234: aload_1
    //   235: invokevirtual 133	java/util/LinkedList:toString	()Ljava/lang/String;
    //   238: astore_1
    //   239: aload_1
    //   240: astore_2
    //   241: aload_1
    //   242: invokevirtual 136	java/lang/String:length	()I
    //   245: ldc -119
    //   247: if_icmple +30 -> 277
    //   250: aload_1
    //   251: aload_1
    //   252: invokevirtual 136	java/lang/String:length	()I
    //   255: ldc -119
    //   257: isub
    //   258: aload_1
    //   259: invokevirtual 136	java/lang/String:length	()I
    //   262: iconst_1
    //   263: isub
    //   264: invokevirtual 141	java/lang/String:substring	(II)Ljava/lang/String;
    //   267: astore_2
    //   268: aload_2
    //   269: areturn
    //   270: astore_2
    //   271: aload_1
    //   272: areturn
    //   273: astore_1
    //   274: ldc -113
    //   276: astore_2
    //   277: aload_2
    //   278: areturn
    // Local variable table:
    //   start	length	slot	name	signature
    //   67	35	0	i	int
    //   124	148	1	localObject1	Object
    //   273	1	1	localIOException1	java.io.IOException
    //   7	262	2	localObject2	Object
    //   270	1	2	localIOException2	java.io.IOException
    //   276	2	2	str	String
    //   24	189	3	localObject3	Object
    // Exception table:
    //   from	to	target	type
    //   241	268	270	java/io/IOException
    //   133	198	273	java/io/IOException
    //   198	203	273	java/io/IOException
    //   207	231	273	java/io/IOException
    //   234	239	273	java/io/IOException
  }
}


/* Location:              /Users/objectyan/Documents/OY/baiduCarLife_40/dist/classes2-dex2jar.jar!/com/baidu/ufosdk/b/a.class
 * Java compiler version: 6 (50.0)
 * JD-Core Version:       0.7.1
 */